Workbook

Sheet Rekap Rata Rata keseluruhan
A1: Model | B1: Chunking | C1: Top K | D1: Faithfulness | E1: Answer_Relevancy | F1: Context_Precision | G1: Context_Recall
A2: LaBSE | B2: 32 | C2: 3 | D2: =ROUND(AVERAGE('Labse Top K=3 Chunk = 32'!E1:E81), 4) -> 0.6197 | E2: =ROUND(AVERAGE('Labse Top K=3 Chunk = 32'!F1:F81),4) -> 0.6622 | F2: =ROUND(AVERAGE('Labse Top K=3 Chunk = 32'!G1:G81),4) -> 0.5708 | G2: =ROUND(AVERAGE('Labse Top K=3 Chunk = 32'!H1:H81),4) -> 0.6389
A3: LaBSE | B3: 32 | C3: 5 | D3: =ROUND(AVERAGE('Labse Top K=5 Chunk = 32'!E1:E81), 4) -> 0.6125 | E3: =ROUND(AVERAGE('Labse Top K=5 Chunk = 32'!F1:F81), 4) -> 0.7231 | F3: =ROUND(AVERAGE('Labse Top K=5 Chunk = 32'!G1:G81), 4) -> 0.5948 | G3: =ROUND(AVERAGE('Labse Top K=5 Chunk = 32'!H1:H81), 4) -> 0.7326
A4: LaBSE | B4: 64 | C4: 3 | D4: =ROUND(AVERAGE('Labse Top K=3 Chunk = 64'!E1:E81),4) -> 0.601 | E4: =AVERAGE('Labse Top K=3 Chunk = 64'!F1:F81) -> 0.6182625 | F4: =AVERAGE('Labse Top K=3 Chunk = 64'!G1:G81) -> 0.5759625 | G4: =AVERAGE('Labse Top K=3 Chunk = 64'!H1:H81) -> 0.691675
A5: LaBSE | B5: 64 | C5: 5 | D5: =ROUND(AVERAGE('Labse Top K=5 Chunk = 64'!E1:E81), 4) -> 0.6201 | E5: =ROUND(AVERAGE('Labse Top K=5 Chunk = 64'!F1:F81), 4) -> 0.6538 | F5: =ROUND(AVERAGE('Labse Top K=5 Chunk = 64'!G1:G81), 4) -> 0.6122 | G5: =ROUND(AVERAGE('Labse Top K=5 Chunk = 64'!H1:H81), 4) -> 0.7232
A6: BGE-M3 | B6: 32 | C6: 3 | D6: =ROUND(AVERAGE('BGE-M3 Top K = 3 , Chunk 32'!E2:E81),4) -> 0.7034 | E6: =ROUND(AVERAGE('BGE-M3 Top K = 3 , Chunk 32'!F2:F81),4) -> 0.824 | F6: =ROUND(AVERAGE('BGE-M3 Top K = 3 , Chunk 32'!G2:G81),4) -> 0.801 | G6: =ROUND(AVERAGE('BGE-M3 Top K = 3 , Chunk 32'!H2:H81),4) -> 0.6744
A7: BGE-M3 | B7: 32 | C7: 5 | D7: =ROUND(AVERAGE('BGE-M3 Top K = 5 , Chunk 32'!E1:E81),4) -> 0.7621 | E7: =ROUND(AVERAGE('BGE-M3 Top K = 5 , Chunk 32'!F1:F81),4) -> 0.8566 | F7: =ROUND(AVERAGE('BGE-M3 Top K = 5 , Chunk 32'!G1:G81),4) -> 0.8008 | G7: =ROUND(AVERAGE('BGE-M3 Top K = 5 , Chunk 32'!H1:H81),4) -> 0.702
A8: BGE-M3 | B8: 64 | C8: 3 | D8: =ROUND(AVERAGE('BGE-M3 Top K = 3 , Chunk 64'!E2:E81),4) -> 0.6878 | E8: =ROUND(AVERAGE('BGE-M3 Top K = 3 , Chunk 64'!F2:F81),4) -> 0.814 | F8: =ROUND(AVERAGE('BGE-M3 Top K = 3 , Chunk 64'!G2:G81),4) -> 0.8291 | G8: =ROUND(AVERAGE('BGE-M3 Top K = 3 , Chunk 64'!H2:H81),4) -> 0.764
A9: BGE-M3 | B9: 64 | C9: 5 | D9: =ROUND(AVERAGE('BGE-M3 Top K = 5 , Chunk 64'!E2:E81),4) -> 0.7224 | E9: =ROUND(AVERAGE('BGE-M3 Top K = 5 , Chunk 64'!F2:F81),4) -> 0.8459 | F9: =ROUND(AVERAGE('BGE-M3 Top K = 5 , Chunk 64'!G2:G81),4) -> 0.856 | G9: =ROUND(AVERAGE('BGE-M3 Top K = 5 , Chunk 64'!H2:H81),4) -> 0.8132
A14: Question Type | B14: Chunking | C14: Top-K | D14: Faithfulness | E14: Answer Relevancy | F14: Context Precision | G14: Context Recall
A15: Trend Analysis | B15: 32 | C15: 3 | D15: =ROUND(AVERAGE(E35,E51),4) -> 0.6244 | E15: =ROUND(AVERAGE(F35,F51),4) -> 0.8222 | F15: =ROUND(AVERAGE(G35,G51),4) -> 0.7458 | G15: =ROUND(AVERAGE(H35,H51),4) -> 0.7289
A16: Gap Detection | B16: 32 | C16: 3 | D16: =ROUND(AVERAGE(E36,E52),4) -> 0.7117 | E16: =ROUND(AVERAGE(F36,F52),4) -> 0.7454 | F16: =ROUND(AVERAGE(G36,G52),4) -> 0.7416 | G16: =ROUND(AVERAGE(H36,H52),4) -> 0.7094
A17: Comparative Synthesis | B17: 32 | C17: 3 | D17: =ROUND(AVERAGE(E37,E53),4) -> 0.6516 | E17: =ROUND(AVERAGE(F37,F53),4) -> 0.77 | F17: =ROUND(AVERAGE(G37,G53),4) -> 0.6813 | G17: =ROUND(AVERAGE(H37,H53),4) -> 0.5079
A18: Evidence-based QA | B18: 32 | C18: 3 | D18: =ROUND(AVERAGE(E38,E54),4) -> 0.6587 | E18: =ROUND(AVERAGE(F38,F54),4) -> 0.6352 | F18: =ROUND(AVERAGE(G38,G54),4) -> 0.575 | G18: =ROUND(AVERAGE(H38,H54),4) -> 0.6807
A19: Trend Analysis | B19: 32 | C19: 5 | D19: =ROUND(AVERAGE(E39,E55),4) -> 0.7558 | E19: =ROUND(AVERAGE(F39,F55),4) -> 0.8059 | F19: =ROUND(AVERAGE(G39,G55),4) -> 0.7173 | G19: =ROUND(AVERAGE(H39,H55),4) -> 0.7243
A20: Gap Detection | B20: 32 | C20: 5 | D20: =ROUND(AVERAGE(E40,E56),4) -> 0.7413 | E20: =ROUND(AVERAGE(F40,F56),4) -> 0.7326 | F20: =ROUND(AVERAGE(G40,G56),4) -> 0.7803 | G20: =ROUND(AVERAGE(H40,H56),4) -> 0.754
A21: Comparative Synthesis | B21: 32 | C21: 5 | D21: =ROUND(AVERAGE(E41,E57),4) -> 0.5977 | E21: =ROUND(AVERAGE(F41,F57),4) -> 0.8386 | F21: =ROUND(AVERAGE(G41,G57),4) -> 0.7274 | G21: =ROUND(AVERAGE(H41,H57),4) -> 0.5908
A22: Evidence-based QA | B22: 32 | C22: 5 | D22: =ROUND(AVERAGE(E42,E58),4) -> 0.6545 | E22: =ROUND(AVERAGE(F42,F58),4) -> 0.7824 | F22: =ROUND(AVERAGE(G42,G58),4) -> 0.5664 | G22: =ROUND(AVERAGE(H42,H58),4) -> 0.7492
A23: Trend Analysis | B23: 64 | C23: 3 | D23: =ROUND(AVERAGE(E43,E59),4) -> 0.6096 | E23: =ROUND(AVERAGE(F43,F59),4) -> 0.7707 | F23: =ROUND(AVERAGE(G43,G59),4) -> 0.7187 | G23: =ROUND(AVERAGE(H43,H59),4) -> 0.8024
A24: Gap Detection | B24: 64 | C24: 3 | D24: =ROUND(AVERAGE(E44,E60),4) -> 0.6773 | E24: =ROUND(AVERAGE(F44,F60),4) -> 0.6593 | F24: =ROUND(AVERAGE(G44,G60),4) -> 0.7479 | G24: =ROUND(AVERAGE(H44,H60),4) -> 0.7245
A25: Comparative Synthesis | B25: 64 | C25: 3 | D25: =ROUND(AVERAGE(E45,E61),4) -> 0.647 | E25: =ROUND(AVERAGE(F45,F61),4) -> 0.8355 | F25: =ROUND(AVERAGE(G45,G61),4) -> 0.75 | G25: =ROUND(AVERAGE(H45,H61),4) -> 0.5907
A26: Evidence-based QA | B26: 64 | C26: 3 | D26: =ROUND(AVERAGE(E46,E62),4) -> 0.6439 | E26: =ROUND(AVERAGE(F46,F62),4) -> 0.5991 | F26: =ROUND(AVERAGE(G46,G62),4) -> 0.5937 | G26: =ROUND(AVERAGE(H46,H62),4) -> 0.6986
... A30: Evidence-based QA | B30: 64 | C30: 5 | D30: =ROUND(AVERAGE(E50,E66),4) -> 0.7206 | E30: =ROUND(AVERAGE(F50,F66),4) -> 0.6462 | F30: =ROUND(AVERAGE(G50,G66),4) -> 0.5946 | G30: =ROUND(AVERAGE(H50,H66),4) -> 0.7324
A34: Model | B34: Question Type | C34: Chunking | D34: Top-K | E34: Faithfulness | F34: Answer Relevancy | G34: Context Precision | H34: Context Recall
A35: LaBSE | B35: Trend Analysis | C35: 32 | D35: 3 | E35: =IFERROR(__xludf.DUMMYFUNCTION("IFERROR( ROUND( AVERAGE( FILTER( 'Labse Top K=3 Chunk = 32'!E:E, TRIM('Labse Top K=3 Chunk = 32'!J:J)=""Trend Analysis"" ) ), 4), ""Data tidak ada"" ) "),0.6127) -> 0.6127 | F35: =IFERROR(__xludf.DUMMYFUNCTION("IFERROR( ROUND( AVERAGE( FILTER( 'Labse Top K=3 Chunk = 32'!F:F, TRIM('Labse Top K=3 Chunk = 32'!J:J)=""Trend Analysis"" ) ), 4), ""Data tidak ada"" ) "),0.7325) -> 0.7325 | G35: =IFERROR(__xludf.DUMMYFUNCTION("IFERROR( ROUND( AVERAGE( FILTER( 'Labse Top K=3 Chunk = 32'!G:G, TRIM('Labse Top K=3 Chunk = 32'!J:J)=""Trend Analysis"" ) ), 4), ""Data tidak ada"" ) "),0.5957) -> 0.5957 | H35: =IFERROR(__xludf.DUMMYFUNCTION("IFERROR( ROUND( AVERAGE( FILTER( 'Labse Top K=3 Chunk = 32'!H:H, TRIM('Labse Top K=3 Chunk = 32'!J:J)=""Trend Analysis"" ) ), 4), ""Data tidak ada"" ) "),0.7044) -> 0.7044
A36: LaBSE | B36: Gap Detection | C36: 32 | D36: 3 | E36: =IFERROR(__xludf.DUMMYFUNCTION("IFERROR( ROUND( AVERAGE( FILTER( 'Labse Top K=3 Chunk = 32'!E:E, TRIM('Labse Top K=3 Chunk = 32'!J:J)=""Gap Detection"" ) ), 4), ""Data tidak ada"" ) "),0.6613) -> 0.6613 | F36: =IFERROR(__xludf.DUMMYFUNCTION("IFERROR( ROUND( AVERAGE( FILTER( 'Labse Top K=3 Chunk = 32'!F:F, TRIM('Labse Top K=3 Chunk = 32'!J:J)=""Gap Detection"" ) ), 4), ""Data tidak ada"" ) "),0.7531) -> 0.7531 | G36: =IFERROR(__xludf.DUMMYFUNCTION("IFERROR( ROUND( AVERAGE( FILTER( 'Labse Top K=3 Chunk = 32'!G:G, TRIM('Labse Top K=3 Chunk = 32'!J:J)=""Gap Detection"" ) ), 4), ""Data tidak ada"" ) "),0.6499) -> 0.6499 | H36: =IFERROR(__xludf.DUMMYFUNCTION("IFERROR( ROUND( AVERAGE( FILTER( 'Labse Top K=3 Chunk = 32'!H:H, TRIM('Labse Top K=3 Chunk = 32'!J:J)=""Gap Detection"" ) ), 4), ""Data tidak ada"" ) "),0.6894) -> 0.6894
A37: LaBSE | B37: Comparative Synthesis | C37: 32 | D37: 3 | E37: =IFERROR(__xludf.DUMMYFUNCTION("IFERROR( ROUND( AVERAGE( FILTER( 'Labse Top K=3 Chunk = 32'!E:E, TRIM('Labse Top K=3 Chunk = 32'!J:J)=""Comparative Synthesis"" ) ), 4), ""Data tidak ada"" ) "),0.6087) -> 0.6087 | F37: =IFERROR(__xludf.DUMMYFUNCTION("IFERROR( ROUND( AVERAGE( FILTER( 'Labse Top K=3 Chunk = 32'!F:F, TRIM('Labse Top K=3 Chunk = 32'!J:J)=""Comparative Synthesis"" ) ), 4), ""Data tidak ada"" ) "),0.6743) -> 0.6743 | G37: =IFERROR(__xludf.DUMMYFUNCTION("IFERROR( ROUND( AVERAGE( FILTER( 'Labse Top K=3 Chunk = 32'!G:G, TRIM('Labse Top K=3 Chunk = 32'!J:J)=""Comparative Synthesis"" ) ), 4), ""Data tidak ada"" ) "),0.575) -> 0.575 | H37: =IFERROR(__xludf.DUMMYFUNCTION("IFERROR( ROUND( AVERAGE( FILTER( 'Labse Top K=3 Chunk = 32'!H:H, TRIM('Labse Top K=3 Chunk = 32'!J:J)=""Comparative Synthesis"" ) ), 4), ""Data tidak ada"" ) "),0.4945) -> 0.4945
A38: LaBSE | B38: Evidence-based QA | C38: 32 | D38: 3 | E38: =IFERROR(__xludf.DUMMYFUNCTION("IFERROR( ROUND( AVERAGE( FILTER( 'Labse Top K=3 Chunk = 32'!E:E, TRIM('Labse Top K=3 Chunk = 32'!J:J)=""Evidence-based QA"" ) ), 4), ""Data tidak ada"" ) "),0.5962) -> 0.5962 | F38: =IFERROR(__xludf.DUMMYFUNCTION("IFERROR( ROUND( AVERAGE( FILTER( 'Labse Top K=3 Chunk = 32'!F:F, TRIM('Labse Top K=3 Chunk = 32'!J:J)=""Evidence-based QA"" ) ), 4), ""Data tidak ada"" ) "),0.4891) -> 0.4891 | G38: =IFERROR(__xludf.DUMMYFUNCTION("IFERROR( ROUND( AVERAGE( FILTER( 'Labse Top K=3 Chunk = 32'!G:G, TRIM('Labse Top K=3 Chunk = 32'!J:J)=""Evidence-based QA"" ) ), 4), ""Data tidak ada"" ) "),0.4625) -> 0.4625 | H38: =IFERROR(__xludf.DUMMYFUNCTION("IFERROR( ROUND( AVERAGE( FILTER( 'Labse Top K=3 Chunk = 32'!H:H, TRIM('Labse Top K=3 Chunk = 32'!J:J)=""Evidence-based QA"" ) ), 4), ""Data tidak ada"" ) "),0.6675) -> 0.6675
A39: LaBSE | B39: Trend Analysis | C39: 32 | D39: 5 | E39: =IFERROR(__xludf.DUMMYFUNCTION("IFERROR( ROUND( AVERAGE( FILTER( 'Labse Top K=5 Chunk = 32'!E:E, TRIM('Labse Top K=5 Chunk = 32'!J:J)=""Trend Analysis"" ) ), 4), ""Data tidak ada"" ) "),0.7202) -> 0.7202 | F39: =IFERROR(__xludf.DUMMYFUNCTION("IFERROR( ROUND( AVERAGE( FILTER( 'Labse Top K=5 Chunk = 32'!F:F, TRIM('Labse Top K=5 Chunk = 32'!J:J)=""Trend Analysis"" ) ), 4), ""Data tidak ada"" ) "),0.7294) -> 0.7294 | G39: =IFERROR(__xludf.DUMMYFUNCTION("IFERROR( ROUND( AVERAGE( FILTER( 'Labse Top K=5 Chunk = 32'!G:G, TRIM('Labse Top K=5 Chunk = 32'!J:J)=""Trend Analysis"" ) ), 4), ""Data tidak ada"" ) "),0.5473) -> 0.5473 | H39: =IFERROR(__xludf.DUMMYFUNCTION("IFERROR( ROUND( AVERAGE( FILTER( 'Labse Top K=5 Chunk = 32'!H:H, TRIM('Labse Top K=5 Chunk = 32'!J:J)=""Trend Analysis"" ) ), 4), ""Data tidak ada"" ) "),0.785) -> 0.785
A40: LaBSE | B40: Gap Detection | C40: 32 | D40: 5 | E40: =IFERROR(__xludf.DUMMYFUNCTION("IFERROR( ROUND( AVERAGE( FILTER( 'Labse Top K=5 Chunk = 32'!E:E, TRIM('Labse Top K=5 Chunk = 32'!J:J)=""Gap Detection"" ) ), 4), ""Data tidak ada"" ) "),0.6301) -> 0.6301 | F40: =IFERROR(__xludf.DUMMYFUNCTION("IFERROR( ROUND( AVERAGE( FILTER( 'Labse Top K=5 Chunk = 32'!F:F, TRIM('Labse Top K=5 Chunk = 32'!J:J)=""Gap Detection"" ) ), 4), ""Data tidak ada"" ) "),0.6617) -> 0.6617 | G40: =IFERROR(__xludf.DUMMYFUNCTION("IFERROR( ROUND( AVERAGE( FILTER( 'Labse Top K=5 Chunk = 32'!G:G, TRIM('Labse Top K=5 Chunk = 32'!J:J)=""Gap Detection"" ) ), 4), ""Data tidak ada"" ) "),0.7106) -> 0.7106 | H40: =IFERROR(__xludf.DUMMYFUNCTION("IFERROR( ROUND( AVERAGE( FILTER( 'Labse Top K=5 Chunk = 32'!H:H, TRIM('Labse Top K=5 Chunk = 32'!J:J)=""Gap Detection"" ) ), 4), ""Data tidak ada"" ) "),0.7442) -> 0.7442
A41: LaBSE | B41: Comparative Synthesis | C41: 32 | D41: 5 | E41: =IFERROR(__xludf.DUMMYFUNCTION("IFERROR( ROUND( AVERAGE( FILTER( 'Labse Top K=5 Chunk = 32'!E:E, TRIM('Labse Top K=5 Chunk = 32'!J:J)=""Comparative Synthesis"" ) ), 4), ""Data tidak ada"" ) "),0.5153) -> 0.5153 | F41: =IFERROR(__xludf.DUMMYFUNCTION("IFERROR( ROUND( AVERAGE( FILTER( 'Labse Top K=5 Chunk = 32'!F:F, TRIM('Labse Top K=5 Chunk = 32'!J:J)=""Comparative Synthesis"" ) ), 4), ""Data tidak ada"" ) "),0.8072) -> 0.8072 | G41: =IFERROR(__xludf.DUMMYFUNCTION("IFERROR( ROUND( AVERAGE( FILTER( 'Labse Top K=5 Chunk = 32'!G:G, TRIM('Labse Top K=5 Chunk = 32'!J:J)=""Comparative Synthesis"" ) ), 4), ""Data tidak ada"" ) "),0.644) -> 0.644 | H41: =IFERROR(__xludf.DUMMYFUNCTION("IFERROR( ROUND( AVERAGE( FILTER( 'Labse Top K=5 Chunk = 32'!H:H, TRIM('Labse Top K=5 Chunk = 32'!J:J)=""Comparative Synthesis"" ) ), 4), ""Data tidak ada"" ) "),0.596) -> 0.596
A42: LaBSE | B42: Evidence-based QA | C42: 32 | D42: 5 | E42: =IFERROR(__xludf.DUMMYFUNCTION("IFERROR( ROUND( AVERAGE( FILTER( 'Labse Top K=5 Chunk = 32'!E:E, TRIM('Labse Top K=5 Chunk = 32'!J:J)=""Evidence-based QA"" ) ), 4), ""Data tidak ada"" ) "),0.5844) -> 0.5844 | F42: =IFERROR(__xludf.DUMMYFUNCTION("IFERROR( ROUND( AVERAGE( FILTER( 'Labse Top K=5 Chunk = 32'!F:F, TRIM('Labse Top K=5 Chunk = 32'!J:J)=""Evidence-based QA"" ) ), 4), ""Data tidak ada"" ) "),0.6942) -> 0.6942 | G42: =IFERROR(__xludf.DUMMYFUNCTION("IFERROR( ROUND( AVERAGE( FILTER( 'Labse Top K=5 Chunk = 32'!G:G, TRIM('Labse Top K=5 Chunk = 32'!J:J)=""Evidence-based QA"" ) ), 4), ""Data tidak ada"" ) "),0.4773) -> 0.4773 | H42: =IFERROR(__xludf.DUMMYFUNCTION("IFERROR( ROUND( AVERAGE( FILTER( 'Labse Top K=3 Chunk = 64'!H:H, TRIM('Labse Top K=3 Chunk = 64'!J:J)=""Evidence-based QA"" ) ), 4), ""Data tidak ada"" ) "),0.7034) -> 0.7034
A43: LaBSE | B43: Trend Analysis | C43: 64 | D43: 3 | E43: =IFERROR(__xludf.DUMMYFUNCTION("IFERROR( ROUND( AVERAGE( FILTER( 'Labse Top K=3 Chunk = 64'!E:E, TRIM('Labse Top K=3 Chunk = 64'!J:J)=""Trend Analysis"" ) ), 4), ""Data tidak ada"" ) "),0.5604) -> 0.5604 | F43: =IFERROR(__xludf.DUMMYFUNCTION("IFERROR( ROUND( AVERAGE( FILTER( 'Labse Top K=3 Chunk = 64'!F:F, TRIM('Labse Top K=3 Chunk = 64'!J:J)=""Trend Analysis"" ) ), 4), ""Data tidak ada"" ) "),0.6707) -> 0.6707 | G43: =IFERROR(__xludf.DUMMYFUNCTION("IFERROR( ROUND( AVERAGE( FILTER( 'Labse Top K=3 Chunk = 64'!G:G, TRIM('Labse Top K=3 Chunk = 64'!J:J)=""Trend Analysis"" ) ), 4), ""Data tidak ada"" ) "),0.4957) -> 0.4957 | H43: =IFERROR(__xludf.DUMMYFUNCTION("IFERROR( ROUND( AVERAGE( FILTER( 'Labse Top K=3 Chunk = 64'!H:H, TRIM('Labse Top K=3 Chunk = 64'!J:J)=""Trend Analysis"" ) ), 4), ""Data tidak ada"" ) "),0.7846) -> 0.7846
A44: LaBSE | B44: Gap Detection | C44: 64 | D44: 3 | E44: =IFERROR(__xludf.DUMMYFUNCTION("IFERROR( ROUND( AVERAGE( FILTER( 'Labse Top K=3 Chunk = 64'!E:E, TRIM('Labse Top K=3 Chunk = 64'!J:J)=""Gap Detection"" ) ), 4), ""Data tidak ada"" ) "),0.6381) -> 0.6381 | F44: =IFERROR(__xludf.DUMMYFUNCTION("IFERROR( ROUND( AVERAGE( FILTER( 'Labse Top K=3 Chunk = 64'!F:F, TRIM('Labse Top K=3 Chunk = 64'!J:J)=""Gap Detection"" ) ), 4), ""Data tidak ada"" ) "),0.5786) -> 0.5786 | G44: =IFERROR(__xludf.DUMMYFUNCTION("IFERROR( ROUND( AVERAGE( FILTER( 'Labse Top K=3 Chunk = 64'!G:G, TRIM('Labse Top K=3 Chunk = 64'!J:J)=""Gap Detection"" ) ), 4), ""Data tidak ada"" ) "),0.6916) -> 0.6916 | H44: =IFERROR(__xludf.DUMMYFUNCTION("IFERROR( ROUND( AVERAGE( FILTER( 'Labse Top K=3 Chunk = 64'!H:H, TRIM('Labse Top K=3 Chunk = 64'!J:J)=""Gap Detection"" ) ), 4), ""Data tidak ada"" ) "),0.6686) -> 0.6686
A45: LaBSE | B45: Comparative Synthesis | C45: 64 | D45: 3 | E45: =IFERROR(__xludf.DUMMYFUNCTION("IFERROR( ROUND( AVERAGE( FILTER( 'Labse Top K=3 Chunk = 64'!E:E, TRIM('Labse Top K=3 Chunk = 64'!J:J)=""Comparative Synthesis"" ) ), 4), ""Data tidak ada"" ) "),0.6239) -> 0.6239 | F45: =IFERROR(__xludf.DUMMYFUNCTION("IFERROR( ROUND( AVERAGE( FILTER( 'Labse Top K=3 Chunk = 64'!F:F, TRIM('Labse Top K=3 Chunk = 64'!J:J)=""Comparative Synthesis"" ) ), 4), ""Data tidak ada"" ) "),0.7929) -> 0.7929 | G45: =IFERROR(__xludf.DUMMYFUNCTION("IFERROR( ROUND( AVERAGE( FILTER( 'Labse Top K=3 Chunk = 64'!G:G, TRIM('Labse Top K=3 Chunk = 64'!J:J)=""Comparative Synthesis"" ) ), 4), ""Data tidak ada"" ) "),0.6583) -> 0.6583 | H45: =IFERROR(__xludf.DUMMYFUNCTION("IFERROR( ROUND( AVERAGE( FILTER( 'Labse Top K=5 Chunk = 64'!H:H, TRIM('Labse Top K=5 Chunk = 64'!J:J)=""Comparative Synthesis"" ) ), 4), ""Data tidak ada"" ) "),0.5604) -> 0.5604
A46: LaBSE | B46: Evidence-based QA | C46: 64 | D46: 3 | E46: =IFERROR(__xludf.DUMMYFUNCTION("IFERROR( ROUND( AVERAGE( FILTER( 'Labse Top K=3 Chunk = 64'!E:E, TRIM('Labse Top K=3 Chunk = 64'!J:J)=""Evidence-based QA"" ) ), 4), ""Data tidak ada"" ) "),0.5819) -> 0.5819 | F46: =IFERROR(__xludf.DUMMYFUNCTION("IFERROR( ROUND( AVERAGE( FILTER( 'Labse Top K=3 Chunk = 64'!F:F, TRIM('Labse Top K=3 Chunk = 64'!J:J)=""Evidence-based QA"" ) ), 4), ""Data tidak ada"" ) "),0.4309) -> 0.4309 | G46: =IFERROR(__xludf.DUMMYFUNCTION("IFERROR( ROUND( AVERAGE( FILTER( 'Labse Top K=3 Chunk = 64'!G:G, TRIM('Labse Top K=3 Chunk = 64'!J:J)=""Evidence-based QA"" ) ), 4), ""Data tidak ada"" ) "),0.4583) -> 0.4583 | H46: =IFERROR(__xludf.DUMMYFUNCTION("IFERROR( ROUND( AVERAGE( FILTER( 'Labse Top K=3 Chunk = 64'!H:H, TRIM('Labse Top K=3 Chunk = 64'!J:J)=""Evidence-based QA"" ) ), 4), ""Data tidak ada"" ) "),0.7034) -> 0.7034
A47: LaBSE | B47: Trend Analysis | C47: 64 | D47: 5 | E47: =IFERROR(__xludf.DUMMYFUNCTION("IFERROR( ROUND( AVERAGE( FILTER( 'Labse Top K=5 Chunk = 64'!E:E, TRIM('Labse Top K=5 Chunk = 64'!J:J)=""Trend Analysis"" ) ), 4), ""Data tidak ada"" ) "),0.6096) -> 0.6096 | F47: =IFERROR(__xludf.DUMMYFUNCTION("IFERROR( ROUND( AVERAGE( FILTER( 'Labse Top K=5 Chunk = 64'!F:F, TRIM('Labse Top K=5 Chunk = 64'!J:J)=""Trend Analysis"" ) ), 4), ""Data tidak ada"" ) "),0.7837) -> 0.7837 | G47: =IFERROR(__xludf.DUMMYFUNCTION("IFERROR( ROUND( AVERAGE( FILTER( 'Labse Top K=5 Chunk = 64'!G:G, TRIM('Labse Top K=5 Chunk = 64'!J:J)=""Trend Analysis"" ) ), 4), ""Data tidak ada"" ) "),0.6506) -> 0.6506 | H47: =IFERROR(__xludf.DUMMYFUNCTION("IFERROR( ROUND( AVERAGE( FILTER( 'Labse Top K=5 Chunk = 64'!H:H, TRIM('Labse Top K=5 Chunk = 64'!J:J)=""Trend Analysis"" ) ), 4), ""Data tidak ada"" ) "),0.7875) -> 0.7875
A48: LaBSE | B48: Gap Detection | C48: 64 | D48: 5 | E48: =IFERROR(__xludf.DUMMYFUNCTION("IFERROR( ROUND( AVERAGE( FILTER( 'Labse Top K=5 Chunk = 64'!E:E, TRIM('Labse Top K=5 Chunk = 64'!J:J)=""Gap Detection"" ) ), 4), ""Data tidak ada"" ) "),0.5862) -> 0.5862 | F48: =IFERROR(__xludf.DUMMYFUNCTION("IFERROR( ROUND( AVERAGE( FILTER( 'Labse Top K=5 Chunk = 64'!F:F, TRIM('Labse Top K=5 Chunk = 64'!J:J)=""Gap Detection"" ) ), 4), ""Data tidak ada"" ) "),0.641) -> 0.641 | G48: =IFERROR(__xludf.DUMMYFUNCTION("IFERROR( ROUND( AVERAGE( FILTER( 'Labse Top K=5 Chunk = 64'!G:G, TRIM('Labse Top K=5 Chunk = 64'!J:J)=""Gap Detection"" ) ), 4), ""Data tidak ada"" ) "),0.7229) -> 0.7229 | H48: =IFERROR(__xludf.DUMMYFUNCTION("IFERROR( ROUND( AVERAGE( FILTER( 'Labse Top K=5 Chunk = 64'!H:H, TRIM('Labse Top K=5 Chunk = 64'!J:J)=""Gap Detection"" ) ), 4), ""Data tidak ada"" ) "),0.778) -> 0.778
A49: LaBSE | B49: Comparative Synthesis | C49: 64 | D49: 5 | E49: =IFERROR(__xludf.DUMMYFUNCTION("IFERROR( ROUND( AVERAGE( FILTER( 'Labse Top K=5 Chunk = 64'!E:E, TRIM('Labse Top K=5 Chunk = 64'!J:J)=""Comparative Synthesis"" ) ), 4), ""Data tidak ada"" ) "),0.6026) -> 0.6026 | F49: =IFERROR(__xludf.DUMMYFUNCTION("IFERROR( ROUND( AVERAGE( FILTER( 'Labse Top K=5 Chunk = 64'!F:F, TRIM('Labse Top K=5 Chunk = 64'!J:J)=""Comparative Synthesis"" ) ), 4), ""Data tidak ada"" ) "),0.6917) -> 0.6917 | G49: =IFERROR(__xludf.DUMMYFUNCTION("IFERROR( ROUND( AVERAGE( FILTER( 'Labse Top K=5 Chunk = 64'!G:G, TRIM('Labse Top K=5 Chunk = 64'!J:J)=""Comparative Synthesis"" ) ), 4), ""Data tidak ada"" ) "),0.6328) -> 0.6328 | H49: =IFERROR(__xludf.DUMMYFUNCTION("IFERROR( ROUND( AVERAGE( FILTER( 'Labse Top K=5 Chunk = 64'!H:H, TRIM('Labse Top K=5 Chunk = 64'!J:J)=""Comparative Synthesis"" ) ), 4), ""Data tidak ada"" ) "),0.5604) -> 0.5604
A50: LaBSE | B50: Evidence-based QA | C50: 64 | D50: 5 | E50: =IFERROR(__xludf.DUMMYFUNCTION("IFERROR( ROUND( AVERAGE( FILTER( 'Labse Top K=5 Chunk = 64'!E:E, TRIM('Labse Top K=5 Chunk = 64'!J:J)=""Evidence-based QA"" ) ), 4), ""Data tidak ada"" ) "),0.6823) -> 0.6823 | F50: =IFERROR(__xludf.DUMMYFUNCTION("IFERROR( ROUND( AVERAGE( FILTER( 'Labse Top K=5 Chunk = 64'!F:F, TRIM('Labse Top K=5 Chunk = 64'!J:J)=""Evidence-based QA"" ) ), 4), ""Data tidak ada"" ) "),0.499) -> 0.499 | G50: =IFERROR(__xludf.DUMMYFUNCTION("IFERROR( ROUND( AVERAGE( FILTER( 'Labse Top K=5 Chunk = 64'!G:G, TRIM('Labse Top K=5 Chunk = 64'!J:J)=""Evidence-based QA"" ) ), 4), ""Data tidak ada"" ) "),0.4427) -> 0.4427 | H50: =IFERROR(__xludf.DUMMYFUNCTION("IFERROR( ROUND( AVERAGE( FILTER( 'Labse Top K=5 Chunk = 64'!H:H, TRIM('Labse Top K=5 Chunk = 64'!J:J)=""Evidence-based QA"" ) ), 4), ""Data tidak ada"" ) "),0.7671) -> 0.7671
A51: BGE-M3 | B51: Trend Analysis | C51: 32 | D51: 3 | E51: =IFERROR(__xludf.DUMMYFUNCTION("IFERROR( ROUND( AVERAGE( FILTER( 'BGE-M3 Top K = 3 , Chunk 32'!E:E, TRIM('BGE-M3 Top K = 3 , Chunk 32'!J:J)=""Trend Analysis"" ) ), 4), ""Data tidak ada"" ) "),0.6361) -> 0.6361 | F51: =IFERROR(__xludf.DUMMYFUNCTION("IFERROR( ROUND( AVERAGE( FILTER( 'BGE-M3 Top K = 3 , Chunk 32'!F:F, TRIM('BGE-M3 Top K = 3 , Chunk 32'!J:J)=""Trend Analysis"" ) ), 4), ""Data tidak ada"" ) "),0.9118) -> 0.9118 | G51: =IFERROR(__xludf.DUMMYFUNCTION("IFERROR( ROUND( AVERAGE( FILTER( 'BGE-M3 Top K = 3 , Chunk 32'!G:G, TRIM('BGE-M3 Top K = 3 , Chunk 32'!J:J)=""Trend Analysis"" ) ), 4), ""Data tidak ada"" ) "),0.8958) -> 0.8958 | H51: =IFERROR(__xludf.DUMMYFUNCTION("IFERROR( ROUND( AVERAGE( FILTER( 'BGE-M3 Top K = 3 , Chunk 32'!H:H, TRIM('BGE-M3 Top K = 3 , Chunk 32'!J:J)=""Trend Analysis"" ) ), 4), ""Data tidak ada"" ) "),0.7534) -> 0.7534
A52: BGE-M3 | B52: Gap Detection | C52: 32 | D52: 3 | E52: =IFERROR(__xludf.DUMMYFUNCTION("IFERROR( ROUND( AVERAGE( FILTER( 'BGE-M3 Top K = 3 , Chunk 32'!E:E, TRIM('BGE-M3 Top K = 3 , Chunk 32'!J:J)=""Gap Detection"" ) ), 4), ""Data tidak ada"" ) "),0.7621) -> 0.7621 | F52: =IFERROR(__xludf.DUMMYFUNCTION("IFERROR( ROUND( AVERAGE( FILTER( 'BGE-M3 Top K = 3 , Chunk 32'!F:F, TRIM('BGE-M3 Top K = 3 , Chunk 32'!J:J)=""Gap Detection"" ) ), 4), ""Data tidak ada"" ) "),0.7377) -> 0.7377 | G52: =IFERROR(__xludf.DUMMYFUNCTION("IFERROR( ROUND( AVERAGE( FILTER( 'BGE-M3 Top K = 3 , Chunk 32'!G:G, TRIM('BGE-M3 Top K = 3 , Chunk 32'!J:J)=""Gap Detection"" ) ), 4), ""Data tidak ada"" ) "),0.8333) -> 0.8333 | H52: =IFERROR(__xludf.DUMMYFUNCTION("IFERROR( ROUND( AVERAGE( FILTER( 'BGE-M3 Top K = 3 , Chunk 32'!H:H, TRIM('BGE-M3 Top K = 3 , Chunk 32'!J:J)=""Gap Detection"" ) ), 4), ""Data tidak ada"" ) "),0.7293) -> 0.7293
A53: BGE-M3 | B53: Comparative Synthesis | C53: 32 | D53: 3 | E53: =IFERROR(__xludf.DUMMYFUNCTION("IFERROR( ROUND( AVERAGE( FILTER( 'BGE-M3 Top K = 3 , Chunk 32'!E:E, TRIM('BGE-M3 Top K = 3 , Chunk 32'!J:J)=""Comparative Synthesis"" ) ), 4), ""Data tidak ada"" ) "),0.6944) -> 0.6944 | F53: =IFERROR(__xludf.DUMMYFUNCTION("IFERROR( ROUND( AVERAGE( FILTER( 'BGE-M3 Top K = 3 , Chunk 32'!F:F, TRIM('BGE-M3 Top K = 3 , Chunk 32'!J:J)=""Comparative Synthesis"" ) ), 4), ""Data tidak ada"" ) "),0.8656) -> 0.8656 | G53: =IFERROR(__xludf.DUMMYFUNCTION("IFERROR( ROUND( AVERAGE( FILTER( 'BGE-M3 Top K = 3 , Chunk 32'!G:G, TRIM('BGE-M3 Top K = 3 , Chunk 32'!J:J)=""Comparative Synthesis"" ) ), 4), ""Data tidak ada"" ) "),0.7875) -> 0.7875 | H53: =IFERROR(__xludf.DUMMYFUNCTION("IFERROR( ROUND( AVERAGE( FILTER( 'BGE-M3 Top K = 3 , Chunk 32'!H:H, TRIM('BGE-M3 Top K = 3 , Chunk 32'!J:J)=""Comparative Synthesis"" ) ), 4), ""Data tidak ada"" ) "),0.5212) -> 0.5212
A54: BGE-M3 | B54: Evidence-based QA | C54: 32 | D54: 3 | E54: =IFERROR(__xludf.DUMMYFUNCTION("IFERROR( ROUND( AVERAGE( FILTER( 'BGE-M3 Top K = 3 , Chunk 32'!E:E, TRIM('BGE-M3 Top K = 3 , Chunk 32'!J:J)=""Evidence-based QA"" ) ), 4), ""Data tidak ada"" ) "),0.7211) -> 0.7211 | F54: =IFERROR(__xludf.DUMMYFUNCTION("IFERROR( ROUND( AVERAGE( FILTER( 'BGE-M3 Top K = 3 , Chunk 32'!F:F, TRIM('BGE-M3 Top K = 3 , Chunk 32'!J:J)=""Evidence-based QA"" ) ), 4), ""Data tidak ada"" ) "),0.7812) -> 0.7812 | G54: =IFERROR(__xludf.DUMMYFUNCTION("IFERROR( ROUND( AVERAGE( FILTER( 'BGE-M3 Top K = 3 , Chunk 32'!G:G, TRIM('BGE-M3 Top K = 3 , Chunk 32'!J:J)=""Evidence-based QA"" ) ), 4), ""Data tidak ada"" ) "),0.6875) -> 0.6875 | H54: =IFERROR(__xludf.DUMMYFUNCTION("IFERROR( ROUND( AVERAGE( FILTER( 'BGE-M3 Top K = 3 , Chunk 32'!H:H, TRIM('BGE-M3 Top K = 3 , Chunk 32'!J:J)=""Evidence-based QA"" ) ), 4), ""Data tidak ada"" ) "),0.6938) -> 0.6938
A55: BGE-M3 | B55: Trend Analysis | C55: 32 | D55: 5 | E55: =IFERROR(__xludf.DUMMYFUNCTION("IFERROR( ROUND( AVERAGE( FILTER( 'BGE-M3 Top K = 5 , Chunk 32'!E:E, TRIM('BGE-M3 Top K = 5 , Chunk 32'!J:J)=""Trend Analysis"" ) ), 4), ""Data tidak ada"" ) "),0.7913) -> 0.7913 | F55: =IFERROR(__xludf.DUMMYFUNCTION("IFERROR( ROUND( AVERAGE( FILTER( 'BGE-M3 Top K = 5 , Chunk 32'!F:F, TRIM('BGE-M3 Top K = 5 , Chunk 32'!J:J)=""Trend Analysis"" ) ), 4), ""Data tidak ada"" ) "),0.8824) -> 0.8824 | G55: =IFERROR(__xludf.DUMMYFUNCTION("IFERROR( ROUND( AVERAGE( FILTER( 'BGE-M3 Top K = 5 , Chunk 32'!G:G, TRIM('BGE-M3 Top K = 5 , Chunk 32'!J:J)=""Trend Analysis"" ) ), 4), ""Data tidak ada"" ) "),0.8873) -> 0.8873 | H55: =IFERROR(__xludf.DUMMYFUNCTION("IFERROR( ROUND( AVERAGE( FILTER( 'BGE-M3 Top K = 5 , Chunk 32'!H:H, TRIM('BGE-M3 Top K = 5 , Chunk 32'!J:J)=""Trend Analysis"" ) ), 4), ""Data tidak ada"" ) "),0.6636) -> 0.6636
A56: BGE-M3 | B56: Gap Detection | C56: 32 | D56: 5 | E56: =IFERROR(__xludf.DUMMYFUNCTION("IFERROR( ROUND( AVERAGE( FILTER( 'BGE-M3 Top K = 5 , Chunk 32'!E:E, TRIM('BGE-M3 Top K = 5 , Chunk 32'!J:J)=""Gap Detection"" ) ), 4), ""Data tidak ada"" ) "),0.8524) -> 0.8524 | F56: =IFERROR(__xludf.DUMMYFUNCTION("IFERROR( ROUND( AVERAGE( FILTER( 'BGE-M3 Top K = 5 , Chunk 32'!F:F, TRIM('BGE-M3 Top K = 5 , Chunk 32'!J:J)=""Gap Detection"" ) ), 4), ""Data tidak ada"" ) "),0.8035) -> 0.8035 | G56: =IFERROR(__xludf.DUMMYFUNCTION("IFERROR( ROUND( AVERAGE( FILTER( 'BGE-M3 Top K = 5 , Chunk 32'!G:G, TRIM('BGE-M3 Top K = 5 , Chunk 32'!J:J)=""Gap Detection"" ) ), 4), ""Data tidak ada"" ) "),0.8499) -> 0.8499 | H56: =IFERROR(__xludf.DUMMYFUNCTION("IFERROR( ROUND( AVERAGE( FILTER( 'BGE-M3 Top K = 5 , Chunk 32'!H:H, TRIM('BGE-M3 Top K = 5 , Chunk 32'!J:J)=""Gap Detection"" ) ), 4), ""Data tidak ada"" ) "),0.7638) -> 0.7638
A57: BGE-M3 | B57: Comparative Synthesis | C57: 32 | D57: 5 | E57: =IFERROR(__xludf.DUMMYFUNCTION("IFERROR( ROUND( AVERAGE( FILTER( 'BGE-M3 Top K = 5 , Chunk 32'!E:E, TRIM('BGE-M3 Top K = 5 , Chunk 32'!J:J)=""Comparative Synthesis"" ) ), 4), ""Data tidak ada"" ) "),0.6801) -> 0.6801 | F57: =IFERROR(__xludf.DUMMYFUNCTION("IFERROR( ROUND( AVERAGE( FILTER( 'BGE-M3 Top K = 5 , Chunk 32'!F:F, TRIM('BGE-M3 Top K = 5 , Chunk 32'!J:J)=""Comparative Synthesis"" ) ), 4), ""Data tidak ada"" ) "),0.87) -> 0.87 | G57: =IFERROR(__xludf.DUMMYFUNCTION("IFERROR( ROUND( AVERAGE( FILTER( 'BGE-M3 Top K = 5 , Chunk 32'!G:G, TRIM('BGE-M3 Top K = 5 , Chunk 32'!J:J)=""Comparative Synthesis"" ) ), 4), ""Data tidak ada"" ) "),0.8107) -> 0.8107 | H57: =IFERROR(__xludf.DUMMYFUNCTION("IFERROR( ROUND( AVERAGE( FILTER( 'BGE-M3 Top K = 5 , Chunk 32'!H:H, TRIM('BGE-M3 Top K = 5 , Chunk 32'!J:J)=""Comparative Synthesis"" ) ), 4), ""Data tidak ada"" ) "),0.5855) -> 0.5855
A58: BGE-M3 | B58: Evidence-based QA | C58: 32 | D58: 5 | E58: =IFERROR(__xludf.DUMMYFUNCTION("IFERROR( ROUND( AVERAGE( FILTER( 'BGE-M3 Top K = 5 , Chunk 32'!E:E, TRIM('BGE-M3 Top K = 5 , Chunk 32'!J:J)=""Evidence-based QA"" ) ), 4), ""Data tidak ada"" ) "),0.7246) -> 0.7246 | F58: =IFERROR(__xludf.DUMMYFUNCTION("IFERROR( ROUND( AVERAGE( FILTER( 'BGE-M3 Top K = 5 , Chunk 32'!F:F, TRIM('BGE-M3 Top K = 5 , Chunk 32'!J:J)=""Evidence-based QA"" ) ), 4), ""Data tidak ada"" ) "),0.8706) -> 0.8706 | G58: =IFERROR(__xludf.DUMMYFUNCTION("IFERROR( ROUND( AVERAGE( FILTER( 'BGE-M3 Top K = 5 , Chunk 32'!G:G, TRIM('BGE-M3 Top K = 5 , Chunk 32'!J:J)=""Evidence-based QA"" ) ), 4), ""Data tidak ada"" ) "),0.6554) -> 0.6554 | H58: =IFERROR(__xludf.DUMMYFUNCTION("IFERROR( ROUND( AVERAGE( FILTER( 'BGE-M3 Top K = 5 , Chunk 32'!H:H, TRIM('BGE-M3 Top K = 5 , Chunk 32'!J:J)=""Evidence-based QA"" ) ), 4), ""Data tidak ada"" ) "),0.795) -> 0.795
A59: BGE-M3 | B59: Trend Analysis | C59: 64 | D59: 3 | E59: =IFERROR(__xludf.DUMMYFUNCTION("IFERROR( ROUND( AVERAGE( FILTER( 'BGE-M3 Top K = 3 , Chunk 64'!E:E, TRIM('BGE-M3 Top K = 3 , Chunk 64'!J:J)=""Trend Analysis"" ) ), 4), ""Data tidak ada"" ) "),0.6587) -> 0.6587 | F59: =IFERROR(__xludf.DUMMYFUNCTION("IFERROR( ROUND( AVERAGE( FILTER( 'BGE-M3 Top K = 3 , Chunk 64'!F:F, TRIM('BGE-M3 Top K = 3 , Chunk 64'!J:J)=""Trend Analysis"" ) ), 4), ""Data tidak ada"" ) "),0.8707) -> 0.8707 | G59: =IFERROR(__xludf.DUMMYFUNCTION("IFERROR( ROUND( AVERAGE( FILTER( 'BGE-M3 Top K = 3 , Chunk 64'!G:G, TRIM('BGE-M3 Top K = 3 , Chunk 64'!J:J)=""Trend Analysis"" ) ), 4), ""Data tidak ada"" ) "),0.9417) -> 0.9417 | H59: =IFERROR(__xludf.DUMMYFUNCTION("IFERROR( ROUND( AVERAGE( FILTER( 'BGE-M3 Top K = 3 , Chunk 64'!H:H, TRIM('BGE-M3 Top K = 3 , Chunk 64'!J:J)=""Trend Analysis"" ) ), 4), ""Data tidak ada"" ) "),0.8202) -> 0.8202
A60: BGE-M3 | B60: Gap Detection | C60: 64 | D60: 3 | E60: =IFERROR(__xludf.DUMMYFUNCTION("IFERROR( ROUND( AVERAGE( FILTER( 'BGE-M3 Top K = 3 , Chunk 64'!E:E, TRIM('BGE-M3 Top K = 3 , Chunk 64'!J:J)=""Gap Detection"" ) ), 4), ""Data tidak ada"" ) "),0.7165) -> 0.7165 | F60: =IFERROR(__xludf.DUMMYFUNCTION("IFERROR( ROUND( AVERAGE( FILTER( 'BGE-M3 Top K = 3 , Chunk 64'!F:F, TRIM('BGE-M3 Top K = 3 , Chunk 64'!J:J)=""Gap Detection"" ) ), 4), ""Data tidak ada"" ) "),0.74) -> 0.74 | G60: =IFERROR(__xludf.DUMMYFUNCTION("IFERROR( ROUND( AVERAGE( FILTER( 'BGE-M3 Top K = 3 , Chunk 64'!G:G, TRIM('BGE-M3 Top K = 3 , Chunk 64'!J:J)=""Gap Detection"" ) ), 4), ""Data tidak ada"" ) "),0.8041) -> 0.8041 | H60: =IFERROR(__xludf.DUMMYFUNCTION("IFERROR( ROUND( AVERAGE( FILTER( 'BGE-M3 Top K = 3 , Chunk 64'!H:H, TRIM('BGE-M3 Top K = 3 , Chunk 64'!J:J)=""Gap Detection"" ) ), 4), ""Data tidak ada"" ) "),0.7804) -> 0.7804
A61: BGE-M3 | B61: Comparative Synthesis | C61: 64 | D61: 3 | E61: =IFERROR(__xludf.DUMMYFUNCTION("IFERROR( ROUND( AVERAGE( FILTER( 'BGE-M3 Top K = 3 , Chunk 64'!E:E, TRIM('BGE-M3 Top K = 3 , Chunk 64'!J:J)=""Comparative Synthesis"" ) ), 4), ""Data tidak ada"" ) "),0.6701) -> 0.6701 | F61: =IFERROR(__xludf.DUMMYFUNCTION("IFERROR( ROUND( AVERAGE( FILTER( 'BGE-M3 Top K = 3 , Chunk 64'!F:F, TRIM('BGE-M3 Top K = 3 , Chunk 64'!J:J)=""Comparative Synthesis"" ) ), 4), ""Data tidak ada"" ) "),0.878) -> 0.878 | G61: =IFERROR(__xludf.DUMMYFUNCTION("IFERROR( ROUND( AVERAGE( FILTER( 'BGE-M3 Top K = 3 , Chunk 64'!G:G, TRIM('BGE-M3 Top K = 3 , Chunk 64'!J:J)=""Comparative Synthesis"" ) ), 4), ""Data tidak ada"" ) "),0.8416) -> 0.8416 | H61: =IFERROR(__xludf.DUMMYFUNCTION("IFERROR( ROUND( AVERAGE( FILTER( 'BGE-M3 Top K = 3 , Chunk 64'!H:H, TRIM('BGE-M3 Top K = 3 , Chunk 64'!J:J)=""Comparative Synthesis"" ) ), 4), ""Data tidak ada"" ) "),0.621) -> 0.621
A62: BGE-M3 | B62: Evidence-based QA | C62: 64 | D62: 3 | E62: =IFERROR(__xludf.DUMMYFUNCTION("IFERROR( ROUND( AVERAGE( FILTER( 'BGE-M3 Top K = 3 , Chunk 64'!E:E, TRIM('BGE-M3 Top K = 3 , Chunk 64'!J:J)=""Evidence-based QA"" ) ), 4), ""Data tidak ada"" ) "),0.7058) -> 0.7058 | F62: =IFERROR(__xludf.DUMMYFUNCTION("IFERROR( ROUND( AVERAGE( FILTER( 'BGE-M3 Top K = 3 , Chunk 64'!F:F, TRIM('BGE-M3 Top K = 3 , Chunk 64'!J:J)=""Evidence-based QA"" ) ), 4), ""Data tidak ada"" ) "),0.7673) -> 0.7673 | G62: =IFERROR(__xludf.DUMMYFUNCTION("IFERROR( ROUND( AVERAGE( FILTER( 'BGE-M3 Top K = 3 , Chunk 64'!G:G, TRIM('BGE-M3 Top K = 3 , Chunk 64'!J:J)=""Evidence-based QA"" ) ), 4), ""Data tidak ada"" ) "),0.7291) -> 0.7291 | H62: =IFERROR(__xludf.DUMMYFUNCTION("IFERROR( ROUND( AVERAGE( FILTER( 'BGE-M3 Top K = 3 , Chunk 32'!H:H, TRIM('BGE-M3 Top K = 3 , Chunk 32'!J:J)=""Evidence-based QA"" ) ), 4), ""Data tidak ada"" ) "),0.6938) -> 0.6938
A63: BGE-M3 | B63: Trend Analysis | C63: 64 | D63: 5 | E63: =IFERROR(__xludf.DUMMYFUNCTION("IFERROR( ROUND( AVERAGE( FILTER( 'BGE-M3 Top K = 5 , Chunk 64'!E:E, TRIM('BGE-M3 Top K = 5 , Chunk 64'!J:J)=""Trend Analysis"" ) ), 4), ""Data tidak ada"" ) "),0.6507) -> 0.6507 | F63: =IFERROR(__xludf.DUMMYFUNCTION("IFERROR( ROUND( AVERAGE( FILTER( 'BGE-M3 Top K = 3 , Chunk 64'!F:F, TRIM('BGE-M3 Top K = 3 , Chunk 64'!J:J)=""Trend Analysis"" ) ), 4), ""Data tidak ada"" ) "),0.8707) -> 0.8707 | G63: =IFERROR(__xludf.DUMMYFUNCTION("IFERROR( ROUND( AVERAGE( FILTER( 'BGE-M3 Top K = 5 , Chunk 64'!G:G, TRIM('BGE-M3 Top K = 5 , Chunk 64'!J:J)=""Trend Analysis"" ) ), 4), ""Data tidak ada"" ) "),0.8588) -> 0.8588 | H63: =IFERROR(__xludf.DUMMYFUNCTION("IFERROR( ROUND( AVERAGE( FILTER( 'BGE-M3 Top K = 5 , Chunk 64'!H:H, TRIM('BGE-M3 Top K = 5 , Chunk 64'!J:J)=""Trend Analysis"" ) ), 4), ""Data tidak ada"" ) "),0.94) -> 0.94
A64: BGE-M3 | B64: Gap Detection | C64: 64 | D64: 5 | E64: =IFERROR(__xludf.DUMMYFUNCTION("IFERROR( ROUND( AVERAGE( FILTER( 'BGE-M3 Top K = 5 , Chunk 64'!E:E, TRIM('BGE-M3 Top K = 5 , Chunk 64'!J:J)=""Gap Detection"" ) ), 4), ""Data tidak ada"" ) "),0.8059) -> 0.8059 | F64: =IFERROR(__xludf.DUMMYFUNCTION("IFERROR( ROUND( AVERAGE( FILTER( 'BGE-M3 Top K = 5 , Chunk 64'!F:F, TRIM('BGE-M3 Top K = 5 , Chunk 64'!J:J)=""Gap Detection"" ) ), 4), ""Data tidak ada"" ) "),0.8214) -> 0.8214 | G64: =IFERROR(__xludf.DUMMYFUNCTION("IFERROR( ROUND( AVERAGE( FILTER( 'BGE-M3 Top K = 5 , Chunk 64'!G:G, TRIM('BGE-M3 Top K = 5 , Chunk 64'!J:J)=""Gap Detection"" ) ), 4), ""Data tidak ada"" ) "),0.914) -> 0.914 | H64: =IFERROR(__xludf.DUMMYFUNCTION("IFERROR( ROUND( AVERAGE( FILTER( 'BGE-M3 Top K = 5 , Chunk 64'!H:H, TRIM('BGE-M3 Top K = 5 , Chunk 64'!J:J)=""Gap Detection"" ) ), 4), ""Data tidak ada"" ) "),0.8268) -> 0.8268
A65: BGE-M3 | B65: Comparative Synthesis | C65: 64 | D65: 5 | E65: =IFERROR(__xludf.DUMMYFUNCTION("IFERROR( ROUND( AVERAGE( FILTER( 'BGE-M3 Top K = 5 , Chunk 64'!E:E, TRIM('BGE-M3 Top K = 5 , Chunk 64'!J:J)=""Comparative Synthesis"" ) ), 4), ""Data tidak ada"" ) "),0.6741) -> 0.6741 | F65: =IFERROR(__xludf.DUMMYFUNCTION("IFERROR( ROUND( AVERAGE( FILTER( 'BGE-M3 Top K = 5 , Chunk 64'!F:F, TRIM('BGE-M3 Top K = 5 , Chunk 64'!J:J)=""Comparative Synthesis"" ) ), 4), ""Data tidak ada"" ) "),0.8884) -> 0.8884 | G65: =IFERROR(__xludf.DUMMYFUNCTION("IFERROR( ROUND( AVERAGE( FILTER( 'BGE-M3 Top K = 5 , Chunk 64'!G:G, TRIM('BGE-M3 Top K = 5 , Chunk 64'!J:J)=""Comparative Synthesis"" ) ), 4), ""Data tidak ada"" ) "),0.9046) -> 0.9046 | H65: =IFERROR(__xludf.DUMMYFUNCTION("IFERROR( ROUND( AVERAGE( FILTER( 'BGE-M3 Top K = 5 , Chunk 64'!H:H, TRIM('BGE-M3 Top K = 5 , Chunk 64'!J:J)=""Comparative Synthesis"" ) ), 4), ""Data tidak ada"" ) "),0.7884) -> 0.7884
A66: BGE-M3 | B66: Evidence-based QA | C66: 64 | D66: 5 | E66: =IFERROR(__xludf.DUMMYFUNCTION("IFERROR( ROUND( AVERAGE( FILTER( 'BGE-M3 Top K = 5 , Chunk 64'!E:E, TRIM('BGE-M3 Top K = 5 , Chunk 64'!J:J)=""Evidence-based QA"" ) ), 4), ""Data tidak ada"" ) "),0.7589) -> 0.7589 | F66: =IFERROR(__xludf.DUMMYFUNCTION("IFERROR( ROUND( AVERAGE( FILTER( 'BGE-M3 Top K = 5 , Chunk 64'!F:F, TRIM('BGE-M3 Top K = 5 , Chunk 64'!J:J)=""Evidence-based QA"" ) ), 4), ""Data tidak ada"" ) "),0.7934) -> 0.7934 | G66: =IFERROR(__xludf.DUMMYFUNCTION("IFERROR( ROUND( AVERAGE( FILTER( 'BGE-M3 Top K = 5 , Chunk 64'!G:G, TRIM('BGE-M3 Top K = 5 , Chunk 64'!J:J)=""Evidence-based QA"" ) ), 4), ""Data tidak ada"" ) "),0.7465) -> 0.7465 | H66: =IFERROR(__xludf.DUMMYFUNCTION("IFERROR( ROUND( AVERAGE( FILTER( 'BGE-M3 Top K = 5 , Chunk 64'!H:H, TRIM('BGE-M3 Top K = 5 , Chunk 64'!J:J)=""Evidence-based QA"" ) ), 4), ""Data tidak ada"" ) "),0.6977) -> 0.6977
A69: Error Analisis
A71: Model | B71: Chunking | C71: Top K | D71: Faithfulness | E71: Answer_Relevancy | F71: Context_Precision | G71: Context_Recall
A72: LaBSE | B72: 32 | C72: 3 | D72: =COUNTIF('Labse Top K=3 Chunk = 32'!E:E,"<=0.5") -> 30 | E72: =COUNTIF('Labse Top K=3 Chunk = 32'!F:F,"<=0.5") -> 16 | F72: =COUNTIF('Labse Top K=3 Chunk = 32'!G:G,"<=0.5") -> 35 | G72: =COUNTIF('Labse Top K=3 Chunk = 32'!H:H,"<=0.5") -> 30
A73: LaBSE | B73: 32 | C73: 5 | D73: =COUNTIF('Labse Top K=5 Chunk = 32'!E:E,"<=0.5") -> 28 | E73: =COUNTIF('Labse Top K=5 Chunk = 32'!F:F,"<=0.5") -> 14 | F73: =COUNTIF('Labse Top K=5 Chunk = 32'!G:G,"<=0.5") -> 36 | G73: =COUNTIF('Labse Top K=5 Chunk = 32'!H:H,"<=0.5") -> 18
A74: LaBSE | B74: 64 | C74: 3 | D74: =COUNTIF('Labse Top K=3 Chunk = 64'!E:E,"<=0.5") -> 24 | E74: =COUNTIF('Labse Top K=3 Chunk = 64'!F:F,"<=0.5") -> 22 | F74: =COUNTIF('Labse Top K=3 Chunk = 64'!G:G,"<=0.5") -> 35 | G74: =COUNTIF('Labse Top K=3 Chunk = 64'!H:H,"<=0.5") -> 23
A75: LaBSE | B75: 64 | C75: 5 | D75: =COUNTIF('Labse Top K=5 Chunk = 64'!E:E,"<=0.5") -> 28 | E75: =COUNTIF('Labse Top K=5 Chunk = 64'!F:F,"<=0.5") -> 19 | F75: =COUNTIF('Labse Top K=5 Chunk = 64'!G:G,"<=0.5") -> 30 | G75: =COUNTIF('Labse Top K=5 Chunk = 64'!H:H,"<=0.5") -> 19
A76: BGE-M3 | B76: 32 | C76: 3 | D76: =COUNTIF('BGE-M3 Top K = 3 , Chunk 32'!E:E,"<=0.5") -> 15 | E76: =COUNTIF('BGE-M3 Top K = 3 , Chunk 32'!F:F,"<0.5") -> 6 | F76: =COUNTIF('BGE-M3 Top K = 3 , Chunk 32'!G:G,"<0.5") -> 11 | G76: =COUNTIF('BGE-M3 Top K = 3 , Chunk 32'!H:H,"<0.5") -> 23
A77: BGE-M3 | B77: 32 | C77: 5 | D77: =COUNTIF('BGE-M3 Top K = 5 , Chunk 32'!E:E,"<0.5") -> 8 | E77: =COUNTIF('BGE-M3 Top K = 5 , Chunk 32'!F:F,"<0.5") -> 2 | F77: =COUNTIF('BGE-M3 Top K = 5 , Chunk 32'!G:G,"<0.5") -> 11 | G77: =COUNTIF('BGE-M3 Top K = 5 , Chunk 32'!H:H,"<0.5") -> 21
A78: BGE-M3 | B78: 64 | C78: 3 | D78: =COUNTIF('BGE-M3 Top K = 3 , Chunk 64'!E:E,"<=0.5") -> 22 | E78: =COUNTIF('BGE-M3 Top K = 3 , Chunk 64'!F:F,"<=0.5") -> 7 | F78: =COUNTIF('BGE-M3 Top K = 3 , Chunk 64'!G:G,"<=0.5") -> 14 | G78: =COUNTIF('BGE-M3 Top K = 3 , Chunk 64'!H:H,"<=0.5") -> 17
A79: BGE-M3 | B79: 64 | C79: 5 | D79: =COUNTIF('BGE-M3 Top K = 5 , Chunk 64'!E:E,"<=0.5") -> 18 | E79: =COUNTIF('BGE-M3 Top K = 5 , Chunk 64'!F:F,"<=0.5") -> 5 | F79: =COUNTIF('BGE-M3 Top K = 5 , Chunk 64'!G:G,"<=0.5") -> 10 | G79: =COUNTIF('BGE-M3 Top K = 5 , Chunk 64'!H:H,"<=0.5") -> 13
A85: Model | B85: Question Type | C85: Chunking | D85: Top-K | E85: Faithfulness | F85: Answer_Relevancy | G85: Context_Precision | H85: Context_Recall
A86: LaBSE | B86: Trend Analysis | C86: 32 | D86: 3 | E86: =COUNTIFS( 'Labse Top K=3 Chunk = 32'!E:E,"<=0.5", 'Labse Top K=3 Chunk = 32'!J:J,"Trend Analysis " ) -> 8 | F86: =COUNTIFS( 'Labse Top K=3 Chunk = 32'!F:F,"<=0.5", 'Labse Top K=3 Chunk = 32'!J:J,"Trend Analysis " ) -> 2 | G86: =COUNTIFS( 'Labse Top K=3 Chunk = 32'!G:G,"<=0.5", 'Labse Top K=3 Chunk = 32'!J:J,"Trend Analysis " ) -> 8 | H86: =COUNTIFS( 'Labse Top K=3 Chunk = 32'!H:H,"<=0.5", 'Labse Top K=3 Chunk = 32'!J:J,"Trend Analysis " ) -> 6
A87: LaBSE | B87: Gap Detection | C87: 32 | D87: 3 | E87: =COUNTIFS( 'Labse Top K=3 Chunk = 32'!E:E,"<=0.5", 'Labse Top K=3 Chunk = 32'!J:J,"Gap Detection" ) -> 7 | F87: =COUNTIFS( 'Labse Top K=3 Chunk = 32'!F:F,"<=0.5", 'Labse Top K=3 Chunk = 32'!J:J,"Gap Detection" ) -> 2 | G87: =COUNTIFS( 'Labse Top K=3 Chunk = 32'!G:G,"<=0.5", 'Labse Top K=3 Chunk = 32'!J:J,"Gap Detection" ) -> 6 | H87: =COUNTIFS( 'Labse Top K=3 Chunk = 32'!H:H,"<=0.5", 'Labse Top K=3 Chunk = 32'!J:J,"Gap Detection" ) -> 6
A88: LaBSE | B88: Comparative Synthesis | C88: 32 | D88: 3 | E88: =COUNTIFS( 'Labse Top K=3 Chunk = 32'!E:E,"<=0.5", 'Labse Top K=3 Chunk = 32'!J:J,"Comparative Synthesis" ) -> 8 | F88: =COUNTIFS( 'Labse Top K=3 Chunk = 32'!F:F,"<=0.5", 'Labse Top K=3 Chunk = 32'!J:J,"Comparative Synthesis" ) -> 4 | G88: =COUNTIFS( 'Labse Top K=3 Chunk = 32'!G:G,"<=0.5", 'Labse Top K=3 Chunk = 32'!J:J,"Comparative Synthesis" ) -> 10 | H88: =COUNTIFS( 'Labse Top K=3 Chunk = 32'!H:H,"<=0.5", 'Labse Top K=3 Chunk = 32'!J:J,"Comparative Synthesis" ) -> 11
A89: LaBSE | B89: Evidence-based QA | C89: 32 | D89: 3 | E89: =COUNTIFS( 'Labse Top K=3 Chunk = 32'!E:E,"<0.5", 'Labse Top K=3 Chunk = 32'!J:J,"Evidence-based QA" ) -> 5 | F89: =COUNTIFS( 'Labse Top K=3 Chunk = 32'!F:F,"<0.5", 'Labse Top K=3 Chunk = 32'!J:J,"Evidence-based QA" ) -> 8 | G89: =COUNTIFS( 'Labse Top K=3 Chunk = 32'!G:G,"<0.5", 'Labse Top K=3 Chunk = 32'!J:J,"Evidence-based QA" ) -> 10 | H89: =COUNTIFS( 'Labse Top K=3 Chunk = 32'!H:H,"<0.5", 'Labse Top K=3 Chunk = 32'!J:J,"Evidence-based QA" ) -> 7
A90: LaBSE | B90: Trend Analysis | C90: 32 | D90: 5 | E90: =COUNTIFS( 'Labse Top K=5 Chunk = 32'!E:E,"<0.5", 'Labse Top K=5 Chunk = 32'!J:J,"Trend Analysis " ) -> 3 | F90: =COUNTIFS( 'Labse Top K=5 Chunk = 32'!F:F,"<0.5", 'Labse Top K=5 Chunk = 32'!J:J,"Trend Analysis " ) -> 4 | G90: =COUNTIFS( 'Labse Top K=5 Chunk = 32'!G:G,"<0.5", 'Labse Top K=5 Chunk = 32'!J:J,"Trend Analysis " ) -> 9 | H90: =COUNTIFS( 'Labse Top K=5 Chunk = 32'!H:H,"<0.5", 'Labse Top K=5 Chunk = 32'!J:J,"Trend Analysis " ) -> 4
A91: LaBSE | B91: Gap Detection | C91: 32 | D91: 5 | E91: =COUNTIFS( 'Labse Top K=5 Chunk = 32'!E:E,"<0.5", 'Labse Top K=5 Chunk = 32'!J:J,"Gap Detection" ) -> 6 | F91: =COUNTIFS( 'Labse Top K=5 Chunk = 32'!F:F,"<0.5", 'Labse Top K=5 Chunk = 32'!J:J,"Gap Detection" ) -> 4 | G91: =COUNTIFS( 'Labse Top K=5 Chunk = 32'!G:G,"<0.5", 'Labse Top K=5 Chunk = 32'!J:J,"Gap Detection" ) -> 6 | H91: =COUNTIFS( 'Labse Top K=5 Chunk = 32'!H:H,"<0.5", 'Labse Top K=5 Chunk = 32'!J:J,"Gap Detection" ) -> 3
A92: LaBSE | B92: Comparative Synthesis | C92: 32 | D92: 5 | E92: =COUNTIFS( 'Labse Top K=5 Chunk = 32'!E:E,"<0.5", 'Labse Top K=5 Chunk = 32'!J:J,"Comparative Synthesis" ) -> 8 | F92: =COUNTIFS( 'Labse Top K=5 Chunk = 32'!F:F,"<0.5", 'Labse Top K=5 Chunk = 32'!J:J,"Comparative Synthesis" ) -> 1 | G92: =COUNTIFS( 'Labse Top K=5 Chunk = 32'!G:G,"<0.5", 'Labse Top K=5 Chunk = 32'!J:J,"Comparative Synthesis" ) -> 6 | H92: =COUNTIFS( 'Labse Top K=5 Chunk = 32'!H:H,"<0.5", 'Labse Top K=5 Chunk = 32'!J:J,"Comparative Synthesis" ) -> 8
A93: LaBSE | B93: Evidence-based QA | C93: 32 | D93: 5 | E93: =COUNTIFS( 'Labse Top K=5 Chunk = 32'!E:E,"<0.5", 'Labse Top K=5 Chunk = 32'!J:J,"Evidence-based QA" ) -> 7 | F93: =COUNTIFS( 'Labse Top K=5 Chunk = 32'!F:F,"<0.5", 'Labse Top K=5 Chunk = 32'!J:J,"Evidence-based QA" ) -> 5 | G93: =COUNTIFS( 'Labse Top K=5 Chunk = 32'!G:G,"<0.5", 'Labse Top K=5 Chunk = 32'!J:J,"Evidence-based QA" ) -> 12 | H93: =COUNTIFS( 'Labse Top K=5 Chunk = 32'!H:H,"<0.5", 'Labse Top K=5 Chunk = 32'!J:J,"Evidence-based QA" ) -> 3
A94: LaBSE | B94: Trend Analysis | C94: 64 | D94: 3 | E94: =COUNTIFS( 'Labse Top K=3 Chunk = 64'!E:E,"<0.5", 'Labse Top K=3 Chunk = 64'!J:J,"Trend Analysis " ) -> 7 | F94: =COUNTIFS( 'Labse Top K=3 Chunk = 64'!F:F,"<0.5", 'Labse Top K=3 Chunk = 64'!J:J,"Trend Analysis " ) -> 5 | G94: =COUNTIFS( 'Labse Top K=3 Chunk = 64'!G:G,"<0.5", 'Labse Top K=3 Chunk = 64'!J:J,"Trend Analysis " ) -> 8 | H94: =COUNTIFS( 'Labse Top K=3 Chunk = 64'!H:H,"<0.5", 'Labse Top K=3 Chunk = 64'!J:J,"Trend Analysis " ) -> 5
A95: LaBSE | B95: Gap Detection | C95: 64 | D95: 3 | E95: =COUNTIFS( 'Labse Top K=3 Chunk = 64'!E:E,"<0.5", 'Labse Top K=3 Chunk = 64'!J:J,"Gap Detection" ) -> 4 | F95: =COUNTIFS( 'Labse Top K=3 Chunk = 64'!F:F,"<0.5", 'Labse Top K=3 Chunk = 64'!J:J,"Gap Detection" ) -> 6 | G95: =COUNTIFS( 'Labse Top K=3 Chunk = 64'!G:G,"<0.5", 'Labse Top K=3 Chunk = 64'!J:J,"Gap Detection" ) -> 5 | H95: =COUNTIFS( 'Labse Top K=3 Chunk = 64'!H:H,"<0.5", 'Labse Top K=3 Chunk = 64'!J:J,"Gap Detection" ) -> 6
A96: LaBSE | B96: Comparative Synthesis | C96: 64 | D96: 3 | E96: =COUNTIFS( 'Labse Top K=3 Chunk = 64'!E:E,"<0.5", 'Labse Top K=3 Chunk = 64'!J:J,"Comparative Synthesis" ) -> 5 | F96: =COUNTIFS( 'Labse Top K=3 Chunk = 64'!F:F,"<0.5", 'Labse Top K=3 Chunk = 64'!J:J,"Comparative Synthesis" ) -> 1 | G96: =COUNTIFS( 'Labse Top K=3 Chunk = 64'!G:G,"<0.5", 'Labse Top K=3 Chunk = 64'!J:J,"Comparative Synthesis" ) -> 4 | H96: =COUNTIFS( 'Labse Top K=3 Chunk = 64'!H:H,"<0.5", 'Labse Top K=3 Chunk = 64'!J:J,"Comparative Synthesis" ) -> 8
A97: LaBSE | B97: Evidence-based QA | C97: 64 | D97: 3 | E97: =COUNTIFS( 'Labse Top K=3 Chunk = 64'!E:E,"<0.5", 'Labse Top K=3 Chunk = 64'!J:J,"Evidence-based QA" ) -> 5 | F97: =COUNTIFS( 'Labse Top K=3 Chunk = 64'!F:F,"<0.5", 'Labse Top K=3 Chunk = 64'!J:J,"Evidence-based QA" ) -> 10 | G97: =COUNTIFS( 'Labse Top K=3 Chunk = 64'!G:G,"<0.5", 'Labse Top K=3 Chunk = 64'!J:J,"Evidence-based QA" ) -> 11 | H97: =COUNTIFS( 'Labse Top K=3 Chunk = 64'!H:H,"<0.5", 'Labse Top K=3 Chunk = 64'!J:J,"Evidence-based QA" ) -> 4
A98: LaBSE | B98: Trend Analysis | C98: 64 | D98: 5 | E98: =COUNTIFS( 'Labse Top K=5 Chunk = 64'!E:E,"<0.5", 'Labse Top K=5 Chunk = 64'!J:J,"Trend Analysis " ) -> 8 | F98: =COUNTIFS( 'Labse Top K=5 Chunk = 64'!F:F,"<0.5", 'Labse Top K=5 Chunk = 64'!J:J,"Trend Analysis " ) -> 2 | G98: =COUNTIFS( 'Labse Top K=5 Chunk = 64'!G:G,"<0.5", 'Labse Top K=5 Chunk = 64'!J:J,"Trend Analysis " ) -> 5 | H98: =COUNTIFS( 'Labse Top K=5 Chunk = 64'!H:H,"<0.5", 'Labse Top K=5 Chunk = 64'!J:J,"Trend Analysis " ) -> 4
A99: LaBSE | B99: Gap Detection | C99: 64 | D99: 5 | E99: =COUNTIFS( 'Labse Top K=5 Chunk = 64'!E:E,"<0.5", 'Labse Top K=5 Chunk = 64'!J:J,"Gap Detection" ) -> 5 | F99: =COUNTIFS( 'Labse Top K=5 Chunk = 64'!F:F,"<0.5", 'Labse Top K=5 Chunk = 64'!J:J,"Gap Detection" ) -> 5 | G99: =COUNTIFS( 'Labse Top K=5 Chunk = 64'!G:G,"<0.5", 'Labse Top K=5 Chunk = 64'!J:J,"Gap Detection" ) -> 5 | H99: =COUNTIFS( 'Labse Top K=5 Chunk = 64'!H:H,"<0.5", 'Labse Top K=5 Chunk = 64'!J:J,"Gap Detection" ) -> 3
A100: LaBSE | B100: Comparative Synthesis | C100: 64 | D100: 5 | E100: =COUNTIFS( 'Labse Top K=5 Chunk = 64'!E:E,"<0.5", 'Labse Top K=5 Chunk = 64'!J:J,"Comparative Synthesis" ) -> 6 | F100: =COUNTIFS( 'Labse Top K=5 Chunk = 64'!F:F,"<0.5", 'Labse Top K=5 Chunk = 64'!J:J,"Comparative Synthesis" ) -> 3 | G100: =COUNTIFS( 'Labse Top K=5 Chunk = 64'!G:G,"<0.5", 'Labse Top K=5 Chunk = 64'!J:J,"Comparative Synthesis" ) -> 6 | H100: =COUNTIFS( 'Labse Top K=5 Chunk = 64'!H:H,"<0.5", 'Labse Top K=5 Chunk = 64'!J:J,"Comparative Synthesis" ) -> 8
A101: LaBSE | B101: Evidence-based QA | C101: 64 | D101: 5 | E101: =COUNTIFS( 'Labse Top K=5 Chunk = 64'!E:E,"<0.5", 'Labse Top K=5 Chunk = 64'!J:J,"Evidence-based QA" ) -> 3 | F101: =COUNTIFS( 'Labse Top K=5 Chunk = 64'!F:F,"<0.5", 'Labse Top K=5 Chunk = 64'!J:J,"Evidence-based QA" ) -> 9 | G101: =COUNTIFS( 'Labse Top K=5 Chunk = 64'!G:G,"<0.5", 'Labse Top K=5 Chunk = 64'!J:J,"Evidence-based QA" ) -> 12 | H101: =COUNTIFS( 'Labse Top K=5 Chunk = 64'!H:H,"<0.5", 'Labse Top K=5 Chunk = 64'!J:J,"Evidence-based QA" ) -> 3
A102: BGE-M3 | B102: Trend Analysis | C102: 32 | D102: 3 | E102: =COUNTIFS('BGE-M3 Top K = 3 , Chunk 32'!E:E,"<0.5", 'BGE-M3 Top K = 3 , Chunk 32'!J:J,"Trend Analysis ") -> 4 | F102: =COUNTIFS('BGE-M3 Top K = 3 , Chunk 32'!F:F,"<0.5", 'BGE-M3 Top K = 3 , Chunk 32'!J:J,"Trend Analysis ") -> 0 | G102: =COUNTIFS('BGE-M3 Top K = 3 , Chunk 32'!G:G,"<0.5", 'BGE-M3 Top K = 3 , Chunk 32'!J:J,"Trend Analysis ") -> 1 | H102: =COUNTIFS('BGE-M3 Top K = 3 , Chunk 32'!H:H,"<0.5", 'BGE-M3 Top K = 3 , Chunk 32'!J:J,"Trend Analysis ") -> 4
A103: BGE-M3 | B103: Gap Detection | C103: 32 | D103: 3 | E103: =COUNTIFS('BGE-M3 Top K = 3 , Chunk 32'!E:E,"<0.5", 'BGE-M3 Top K = 3 , Chunk 32'!J:J,"Gap Detection") -> 1 | F103: =COUNTIFS('BGE-M3 Top K = 3 , Chunk 32'!F:F,"<0.5", 'BGE-M3 Top K = 3 , Chunk 32'!J:J,"Gap Detection") -> 2 | G103: =COUNTIFS('BGE-M3 Top K = 3 , Chunk 32'!G:G,"<0.5", 'BGE-M3 Top K = 3 , Chunk 32'!J:J,"Gap Detection") -> 2 | H103: =COUNTIFS('BGE-M3 Top K = 3 , Chunk 32'!H:H,"<0.5", 'BGE-M3 Top K = 3 , Chunk 32'!J:J,"Gap Detection") -> 4
A104: BGE-M3 | B104: Comparative Synthesis | C104: 32 | D104: 3 | E104: =COUNTIFS('BGE-M3 Top K = 3 , Chunk 32'!E:E,"<0.5", 'BGE-M3 Top K = 3 , Chunk 32'!J:J,"Comparative Synthesis") -> 4 | F104: =COUNTIFS('BGE-M3 Top K = 3 , Chunk 32'!F:F,"<0.5", 'BGE-M3 Top K = 3 , Chunk 32'!J:J,"Comparative Synthesis") -> 1 | G104: =COUNTIFS('BGE-M3 Top K = 3 , Chunk 32'!G:G,"<0.5", 'BGE-M3 Top K = 3 , Chunk 32'!J:J,"Comparative Synthesis") -> 2 | H104: =COUNTIFS('BGE-M3 Top K = 3 , Chunk 32'!H:H,"<0.5", 'BGE-M3 Top K = 3 , Chunk 32'!J:J,"Comparative Synthesis") -> 9
A105: BGE-M3 | B105: Evidence-based QA | C105: 32 | D105: 3 | E105: =COUNTIFS('BGE-M3 Top K = 3 , Chunk 32'!E:E,"<0.5", 'BGE-M3 Top K = 3 , Chunk 32'!J:J,"Evidence-based QA") -> 1 | F105: =COUNTIFS('BGE-M3 Top K = 3 , Chunk 32'!F:F,"<0.5", 'BGE-M3 Top K = 3 , Chunk 32'!J:J,"Evidence-based QA") -> 3 | G105: =COUNTIFS('BGE-M3 Top K = 3 , Chunk 32'!G:G,"<0.5", 'BGE-M3 Top K = 3 , Chunk 32'!J:J,"Evidence-based QA") -> 6 | H105: =COUNTIFS('BGE-M3 Top K = 3 , Chunk 32'!H:H,"<0.5", 'BGE-M3 Top K = 3 , Chunk 32'!J:J,"Evidence-based QA") -> 6
A106: BGE-M3 | B106: Trend Analysis | C106: 32 | D106: 5 | E106: =COUNTIFS('BGE-M3 Top K = 5 , Chunk 32'!E:E,"<0.5", 'BGE-M3 Top K = 5 , Chunk 32'!J:J,"Trend Analysis ") -> 2 | F106: =COUNTIFS('BGE-M3 Top K = 5 , Chunk 32'!F:F,"<0.5", 'BGE-M3 Top K = 5 , Chunk 32'!J:J,"Trend Analysis ") -> 0 | G106: =COUNTIFS('BGE-M3 Top K = 5 , Chunk 32'!G:G,"<0.5", 'BGE-M3 Top K = 5 , Chunk 32'!J:J,"Trend Analysis ") -> 2 | H106: =COUNTIFS('BGE-M3 Top K = 5 , Chunk 32'!H:H,"<0.5", 'BGE-M3 Top K = 5 , Chunk 32'!J:J,"Trend Analysis ") -> 6
A107: BGE-M3 | B107: Gap Detection | C107: 32 | D107: 5 | E107: =COUNTIFS('BGE-M3 Top K = 5 , Chunk 32'!E:E,"<0.5", 'BGE-M3 Top K = 5 , Chunk 32'!J:J,"Gap Detection") -> 1 | F107: =COUNTIFS('BGE-M3 Top K = 5 , Chunk 32'!F:F,"<0.5", 'BGE-M3 Top K = 5 , Chunk 32'!J:J,"Gap Detection") -> 1 | G107: =COUNTIFS('BGE-M3 Top K = 5 , Chunk 32'!G:G,"<0.5", 'BGE-M3 Top K = 5 , Chunk 32'!J:J,"Gap Detection") -> 2 | H107: =COUNTIFS('BGE-M3 Top K = 5 , Chunk 32'!H:H,"<0.5", 'BGE-M3 Top K = 5 , Chunk 32'!J:J,"Gap Detection") -> 5
A108: BGE-M3 | B108: Comparative Synthesis | C108: 32 | D108: 5 | E108: =COUNTIFS('BGE-M3 Top K = 5 , Chunk 32'!E:E,"<0.5", 'BGE-M3 Top K = 5 , Chunk 32'!J:J,"Comparative Synthesis") -> 3 | F108: =COUNTIFS('BGE-M3 Top K = 5 , Chunk 32'!F:F,"<0.5", 'BGE-M3 Top K = 5 , Chunk 32'!J:J,"Comparative Synthesis") -> 0 | G108: =COUNTIFS('BGE-M3 Top K = 5 , Chunk 32'!G:G,"<0.5", 'BGE-M3 Top K = 5 , Chunk 32'!J:J,"Comparative Synthesis") -> 1 | H108: =COUNTIFS('BGE-M3 Top K = 5 , Chunk 32'!H:H,"<0.5", 'BGE-M3 Top K = 5 , Chunk 32'!J:J,"Comparative Synthesis") -> 8
A109: BGE-M3 | B109: Evidence-based QA | C109: 32 | D109: 5 | E109: =COUNTIFS('BGE-M3 Top K = 5 , Chunk 32'!E:E,"<0.5", 'BGE-M3 Top K = 5 , Chunk 32'!J:J,"Evidence-based QA") -> 2 | F109: =COUNTIFS('BGE-M3 Top K = 5 , Chunk 32'!F:F,"<0.5", 'BGE-M3 Top K = 5 , Chunk 32'!J:J,"Evidence-based QA") -> 1 | G109: =COUNTIFS('BGE-M3 Top K = 5 , Chunk 32'!G:G,"<0.5", 'BGE-M3 Top K = 5 , Chunk 32'!J:J,"Evidence-based QA") -> 6 | H109: =COUNTIFS('BGE-M3 Top K = 5 , Chunk 32'!H:H,"<0.5", 'BGE-M3 Top K = 5 , Chunk 32'!J:J,"Evidence-based QA") -> 2
A110: BGE-M3 | B110: Trend Analysis | C110: 64 | D110: 3 | E110: =COUNTIFS('BGE-M3 Top K = 3 , Chunk 64'!E:E,"<0.5", 'BGE-M3 Top K = 3 , Chunk 64'!J:J,"Trend Analysis ") -> 6 | F110: =COUNTIFS('BGE-M3 Top K = 3 , Chunk 64'!F:F,"<0.5", 'BGE-M3 Top K = 3 , Chunk 64'!J:J,"Trend Analysis ") -> 1 | G110: =COUNTIFS('BGE-M3 Top K = 3 , Chunk 64'!G:G,"<0.5", 'BGE-M3 Top K = 3 , Chunk 64'!J:J,"Trend Analysis ") -> 1 | H110: =COUNTIFS('BGE-M3 Top K = 3 , Chunk 64'!H:H,"<0.5", 'BGE-M3 Top K = 3 , Chunk 64'!J:J,"Trend Analysis ") -> 2
A111: BGE-M3 | B111: Gap Detection | C111: 64 | D111: 3 | E111: =COUNTIFS('BGE-M3 Top K = 3 , Chunk 64'!E:E,"<0.5", 'BGE-M3 Top K = 3 , Chunk 64'!J:J,"Gap Detection") -> 5 | F111: =COUNTIFS('BGE-M3 Top K = 3 , Chunk 64'!F:F,"<0.5", 'BGE-M3 Top K = 3 , Chunk 64'!J:J,"Gap Detection") -> 3 | G111: =COUNTIFS('BGE-M3 Top K = 3 , Chunk 64'!G:G,"<0.5", 'BGE-M3 Top K = 3 , Chunk 64'!J:J,"Gap Detection") -> 4 | H111: =COUNTIFS('BGE-M3 Top K = 3 , Chunk 64'!H:H,"<0.5", 'BGE-M3 Top K = 3 , Chunk 64'!J:J,"Gap Detection") -> 2
A112: BGE-M3 | B112: Comparative Synthesis | C112: 64 | D112: 3 | E112: =COUNTIFS('BGE-M3 Top K = 3 , Chunk 64'!E:E,"<0.5", 'BGE-M3 Top K = 3 , Chunk 64'!J:J,"Comparative Synthesis") -> 5 | F112: =COUNTIFS('BGE-M3 Top K = 3 , Chunk 64'!F:F,"<0.5", 'BGE-M3 Top K = 3 , Chunk 64'!J:J,"Comparative Synthesis") -> 0 | G112: =COUNTIFS('BGE-M3 Top K = 3 , Chunk 64'!G:G,"<0.5", 'BGE-M3 Top K = 3 , Chunk 64'!J:J,"Comparative Synthesis") -> 3 | H112: =COUNTIFS('BGE-M3 Top K = 3 , Chunk 64'!H:H,"<0.5", 'BGE-M3 Top K = 3 , Chunk 64'!J:J,"Comparative Synthesis") -> 7
A113: BGE-M3 | B113: Evidence-based QA | C113: 64 | D113: 3 | E113: =COUNTIFS('BGE-M3 Top K = 3 , Chunk 64'!E:E,"<0.5", 'BGE-M3 Top K = 3 , Chunk 64'!J:J,"Evidence-based QA") -> 4 | F113: =COUNTIFS('BGE-M3 Top K = 3 , Chunk 64'!F:F,"<0.5", 'BGE-M3 Top K = 3 , Chunk 64'!J:J,"Evidence-based QA") -> 3 | G113: =COUNTIFS('BGE-M3 Top K = 3 , Chunk 64'!G:G,"<0.5", 'BGE-M3 Top K = 3 , Chunk 64'!J:J,"Evidence-based QA") -> 4 | H113: =COUNTIFS('BGE-M3 Top K = 3 , Chunk 64'!H:H,"<0.5", 'BGE-M3 Top K = 3 , Chunk 64'!J:J,"Evidence-based QA") -> 3
A114: BGE-M3 | B114: Trend Analysis | C114: 64 | D114: 5 | E114: =COUNTIFS('BGE-M3 Top K = 5 , Chunk 64'!E:E,"<0.5", 'BGE-M3 Top K = 5 , Chunk 64'!J:J,"Trend Analysis ") -> 6 | F114: =COUNTIFS('BGE-M3 Top K = 5 , Chunk 64'!F:F,"<0.5", 'BGE-M3 Top K = 5 , Chunk 64'!J:J,"Trend Analysis ") -> 1 | G114: =COUNTIFS('BGE-M3 Top K = 5 , Chunk 64'!G:G,"<0.5", 'BGE-M3 Top K = 5 , Chunk 64'!J:J,"Trend Analysis ") -> 1 | H114: =COUNTIFS('BGE-M3 Top K = 5 , Chunk 64'!H:H,"<0.5", 'BGE-M3 Top K = 5 , Chunk 64'!J:J,"Trend Analysis ") -> 1
A115: BGE-M3 | B115: Gap Detection | C115: 64 | D115: 5 | E115: =COUNTIFS('BGE-M3 Top K = 5 , Chunk 64'!E:E,"<0.5", 'BGE-M3 Top K = 5 , Chunk 64'!J:J,"Gap Detection") -> 3 | F115: =COUNTIFS('BGE-M3 Top K = 5 , Chunk 64'!F:F,"<0.5", 'BGE-M3 Top K = 5 , Chunk 64'!J:J,"Gap Detection") -> 1 | G115: =COUNTIFS('BGE-M3 Top K = 5 , Chunk 64'!G:G,"<0.5", 'BGE-M3 Top K = 5 , Chunk 64'!J:J,"Gap Detection") -> 1 | H115: =COUNTIFS('BGE-M3 Top K = 5 , Chunk 64'!H:H,"<0.5", 'BGE-M3 Top K = 5 , Chunk 64'!J:J,"Gap Detection") -> 3
A116: BGE-M3 | B116: Comparative Synthesis | C116: 64 | D116: 5 | E116: =COUNTIFS('BGE-M3 Top K = 5 , Chunk 64'!E:E,"<0.5", 'BGE-M3 Top K = 5 , Chunk 64'!J:J,"Comparative Synthesis") -> 4 | F116: =COUNTIFS('BGE-M3 Top K = 5 , Chunk 64'!F:F,"<0.5", 'BGE-M3 Top K = 5 , Chunk 64'!J:J,"Comparative Synthesis") -> 0 | G116: =COUNTIFS('BGE-M3 Top K = 5 , Chunk 64'!G:G,"<0.5", 'BGE-M3 Top K = 5 , Chunk 64'!J:J,"Comparative Synthesis") -> 1 | H116: =COUNTIFS('BGE-M3 Top K = 5 , Chunk 64'!H:H,"<0.5", 'BGE-M3 Top K = 5 , Chunk 64'!J:J,"Comparative Synthesis") -> 4
A117: BGE-M3 | B117: Evidence-based QA | C117: 64 | D117: 5 | E117: =COUNTIFS('BGE-M3 Top K = 5 , Chunk 64'!E:E,"<0.5", 'BGE-M3 Top K = 5 , Chunk 64'!J:J,"Evidence-based QA") -> 2 | F117: =COUNTIFS('BGE-M3 Top K = 5 , Chunk 64'!F:F,"<0.5", 'BGE-M3 Top K = 5 , Chunk 64'!J:J,"Evidence-based QA") -> 3 | G117: =COUNTIFS('BGE-M3 Top K = 5 , Chunk 64'!G:G,"<0.5", 'BGE-M3 Top K = 5 , Chunk 64'!J:J,"Evidence-based QA") -> 5 | H117: =COUNTIFS('BGE-M3 Top K = 5 , Chunk 64'!H:H,"<0.5", 'BGE-M3 Top K = 5 , Chunk 64'!J:J,"Evidence-based QA") -> 5
A120: Jenis error | B120: Sub Category | C120: Jumlah setiap Sub | D120: Total
...

Sheet Rekap hasil seluruh pengujian s
A1: No | B1: Model | C1: Chunking | D1: Top K | E1: Question | F1: Answer | G1: Top_K_Sources | H1: Faithfulness | I1: Answer_Relevancy | J1: Context_Precision | K1: Context_Recall | L1: Image_Path
A2: {=SEQUENCE(640,1)} -> 1 | B2: LaBSE | C2: 32 | D2: 3 | E2: How has the application of AI in supply chain risk management evolved over time? | F2: Direct Summary: The application of AI in supply chain risk management has evolved over time, shifting from a focus on prediction performance to exploring its impact on service models and various segments of the supply chain. Initially, most works focused on prediction performance, but recent studies have expanded to include the investigation of AI's applicability in supply chain risk management. This evolution indicates a growing recognition of AI's potential in supply chain management. Detailed Synthesis: Initially, the application of AI in supply chain risk management focused on prediction performance, as seen in works such as Baryannis et al. (2019) [1]. However, recent studies have expanded to include the investigation of AI's applicability in supply chain risk management, indicating a growing recognition of AI's potential in supply chain management. Recent studies, such as Wang et al. (2025) [2], have explored the application of AI in supply chain management, focusing on its impact on service models at both the front and back ends of the supply chain. The evolution of AI's application in supply chain risk management is also reflected in its increasing adoption across various segments of the supply chain, as seen in the food industry, where AI is being applied in breeding, cultivation, production, processing, safety testing, and more, as discussed in Ding et al. (2025) [3]. Analysis grounded in primary sources: [Baryannis et al., 2019; Wang et al., 2025; Ding et al., 2025]. | G2: Rank #1 Potongan Chunk: same time the resurgence of artificial intelligence ai has led to the investigation of machine learning techniques and their applicability in supply chain risk management however most works focus on prediction performance... Title: predicting supply chain risks using machine learning the tradeoff between performance and interpretability Authors: Baryannis, G.; Dani, S.; Antoniou, G. Score: 0.5620 ----------------- Rank #2 Potongan Chunk: this paper explores the application of artificial intelligence ai in supply chain management focusing on its impact on service models at both the front and back ends of the supply chain sc... Title: is it necessary for the supply chain to implement artificial intelligencedriven sales services at both the frontend and backend stages Authors: Wang, Y.; Gao, J.; Cheng, T.C.E.; Jin, M.; Yue, X.; Wang, H. Score: 0.5546 ----------------- Rank #3 Potongan Chunk: with the rapid development of artificial intelligence ai technology its application in the food industry has become increasingly widespread covering various segments from breeding and cultivation production and processing safety testing and... Title: applications and prospects of artificial intelligence in the food industry Authors: Ding, H.; Song, X.; Dong, G.; Zhang, X.; Wang, C.; Cui, X.; Hou, H.; Huang, H.; Xu, S.; Han, Y.; Yang, Y. Score: 0.5279 | H2: 1 | I2: 0.901 | J2: 1 | K2: 0.875 | L2: =IMAGE("https://drive.google.com/uc?export=view&id=1yWqfLrwrmcdiwdqVorVHl9lGOMhO-QEg")
A3: 2 | B3: LaBSE | C3: 32 | D3: 3 | E3: What were the dominant AI techniques used in early research on supply chain resilience? | F3: Direct Summary: The dominant AI techniques used in early research on supply chain resilience were primarily focused on prediction performance, with most works utilizing machine learning techniques. Detailed Synthesis: According to Doc [3], machine learning techniques were the primary focus in early research on supply chain risk management, with a focus on prediction performance [3]. However, as noted in Doc [1], the majority of AI approaches explored in supply chain research afford little to no explainability, which is a significant limitation [1]. Analysis grounded in primary sources: [Baryannis, G.; Dani, S.; Antoniou, G., 2019; Kosasih, E.E.; Papadakis, E.; Baryannis, G.; Brintrup, A., 2024]. | G3: Rank #1 Potongan Chunk: artificial intelligence ai has emerged as a complementary technology in supply chain research however the majority of ai approaches explored in this context afford little to no explainability which is a significant... Title: a review of explainable artificial intelligence in supply chain management using neurosymbolic approaches Authors: Kosasih, E.E.; Papadakis, E.; Baryannis, G.; Brintrup, A. Score: 0.5819 ----------------- Rank #2 Potongan Chunk: study aims primarily to provide insight into the artificial intelligence ai tools used in supply chain management processes using the supply chain operations reference scor approach it also seeks to examine the... Title: exploring the power of artificial intelligence in supply chain management a literature review on the artificial intelligence applications and tools used in supply chains and their distribution according to the scor method Authors: Harrir, M.M.; Triqui, L. Score: 0.5498 ----------------- Rank #3 Potongan Chunk: same time the resurgence of artificial intelligence ai has led to the investigation of machine learning techniques and their applicability in supply chain risk management however most works focus on prediction performance... Title: predicting supply chain risks using machine learning the tradeoff between performance and interpretability Authors: Baryannis, G.; Dani, S.; Antoniou, G. Score: 0.5465 | H3: 0.429 | I3: 1 | J3: 0.333 | K3: 1 | L3: =IMAGE("https://drive.google.com/uc?export=view&id=1FxO3OeVVwVfdbWaVF-TiLUcIeXutQ-6f")
A4: 3 | B4: LaBSE | C4: 32 | D4: 3 | E4: How did machine learning adoption change SCRM research after 2015? | F4: Direct Summary: Machine learning adoption significantly impacted SCRM research after 2015, as evident from the increasing number of studies exploring its applications in SCM. This shift is attributed to the growing interest in leveraging AI and ML for more efficient and sustainable supply chain management. Detailed Synthesis: According to Doc [3], the rapid growth of interest in deep learning, a class of machine learning algorithms, in SCM has led to an urgent need for an updated systematic review on research development [1]. As stated in Doc [1], this study examined articles published since 2015 to understand the current status, future possibilities, and capabilities of ML in supporting environmentally friendly development [2]. Similarly, Doc [2] highlights the importance of AI and ML in effectively adopting and implementing the circular economy in real-world practices [3]. Analysis grounded in primary sources: Hosseinnia Shavaki, F.H.; Ebrahimi Ghahnavieh, A. (2023), Noman, A.A.; Akter, U.H.; Pranto, T.H.; Haque, A.K.M.B. (2022), Claude, B.M.J.; Sibali, L.L. (2024). | G4: Rank #1 Potongan Chunk: use machine learning ml a new technique approach this study examined articles published since 2015 to understand better the current status future possibilities and capabilities of ml in supporting environmentally friendly development... Title: application of machine learning for environmentally friendly advancement exploring biomassderived materials in wastewater treatment and agricultural sector a review Authors: Claude, B.M.J.; Sibali, L.L. Score: 0.4867 ----------------- Rank #2 Potongan Chunk: later on by reusing recycling and remanufacturing innovative technologies like artificial intelligence ai and machine learningml provide vital assistance in effectively adopting and implementing ce in realworld practices this study explores the... Title: machine learning and artificial intelligence in circular economy a bibliometric analysis and systematic literature review Authors: Noman, A.A.; Akter, U.H.; Pranto, T.H.; Haque, A.K.M.B. Score: 0.4789 ----------------- Rank #3 Potongan Chunk: rapidly growing interest in the application of deep learning a class of machine learning algorithms in scm has urged the need for an uptodate systematic review on the research development the main... Title: applications of deep learning into supply chain management a systematic literature review and a framework for future research Authors: Hosseinnia Shavaki, F.H.; Ebrahimi Ghahnavieh, A. Score: 0.4678 | H4: 1 | I4: 0.827 | J4: 1 | K4: 0.333 | L4: =IMAGE("https://drive.google.com/uc?export=view&id=1dV58gtSqEiTa5kdZ6WMlUDwpnp4_jjSm")
A5: 4 | B5: LaBSE | C5: 32 | D5: 3 | E5: What role did predictive analytics play in early supply chain risk mitigation studies? | F5: Direct Summary: Predictive analytics played a crucial role in early supply chain risk mitigation studies, particularly in identifying and mitigating risks in retail supply chains and agricultural supply chains. This was achieved through the application of big data analytics and machine learning techniques. Detailed Synthesis: Predictive analytics was used to identify and mitigate risks in retail supply chains, as seen in the study by Xue et al. (2019) [1], which employed a difference measure method based on moment generating function and fuzzy data stream clustering. Big data analytics was applied to mitigate supply chain social risk in manufacturing supply chains, as demonstrated by Venkatesh et al. (2017) [2], who explored the application of big data analytics in mitigating supply chain social risk. Predictive analytics was also used in agricultural supply chains, as seen in the study by Han et al. (2024) [3], which employed big data-driven risk decision-making and safety management strategies. Analysis grounded in primary sources: [Xue et al., 2019; Venkatesh et al., 2017; Han et al., 2024]. | G5: Rank #1 Potongan Chunk: the research of the difference measure method for risk probability distribution plays a key role in the early warning decisionmaking management of retail supply chain unconventional emergency however the common difference measure... Title: difference measure method of risk probability distribution based on moment generating function and fuzzy data stream clustering Authors: Xue, H.; Yuan, Y.; Jiang, C.; Cai, B.-Y. Score: 0.5337 ----------------- Rank #2 Potongan Chunk: importance to the sustainable enterprise the aim of this research is to explore the application of big data analytics in mitigating supply chain social risk and to demonstrate how such mitigation can... Title: mitigating supply chain risk via sustainability using big data analytics evidence from the manufacturing supply chain Authors: Venkatesh, V.; Delgado, C.; Hazen, B.T.; Patel, P. Score: 0.4937 ----------------- Rank #3 Potongan Chunk: adopt effective risk management strategies is paramount contemporary studies have explored the utilization of big data in decisionmaking processes specific to agricultural supply chain risks predominantly concentrating on preliminary risk prediction and... Title: big datadriven risk decisionmaking and safety management in agricultural supply chains Authors: Han, G.; Pan, X.; Zhang, X. Score: 0.4916 | H5: 0.571 | I5: 1 | J5: 1 | K5: 1 | L5: =IMAGE("https://drive.google.com/uc?export=view&id=1A27oO-piM3pvWsnAMdr8bRcHquE5OX4D")
A6: 5 | B6: LaBSE | C6: 32 | D6: 3 | E6: How has deep learning influenced recent supply chain resilience models? | F6: Direct Summary: Deep learning has significantly influenced recent supply chain resilience models by enabling advanced techniques such as predictive analytics and machine learning algorithms to improve efficiency and visibility in supply chain management. Detailed Synthesis: Deep learning has been used to develop predictive models that can forecast demand and supply, enabling supply chain managers to make informed decisions and improve resilience [1]. The use of deep Q-learning has been shown to improve supply chain management procedures by enabling data-driven decision making and optimizing supply chain operations [2]. Advanced deep learning techniques have also been used to develop optimized provenance systems that can improve visibility and transparency in the supply chain, reducing the risk of disruptions and improving resilience [3]. Analysis grounded in primary sources: [Ghodake et al., 2024; Abekoon et al., 2024; Khan et al., 2020]. | G6: Rank #1 Potongan Chunk: notable gains above baseline methods highlighting the importance of dql in supply chain management this study demonstrates how deep qlearning has the ability to completely change supply chain management procedures in todays... Title: enhancing supply chain management efficiency a datadriven approach using predictive analytics and machine learning algorithms Authors: Ghodake, S.P.; Malkar, V.R.; Santosh, K.; Jabasheela, L.; Abdufattokhov, S.; Gopi, A. Score: 0.5184 ----------------- Rank #2 Potongan Chunk: this study reviews recent advancements in food science and technology analyzing their impact on the development of intelligent food packaging within the complex food supply chain modern food technology has brought about... Title: a comprehensive review to evaluate the synergy of intelligent food packaging with modern food technology and artificial intelligence field Authors: Abekoon, T.; Buthpitiya, B.L.S.K.; Sajindra, H.; Samarakoon, E.R.J.; Jayakody, J.A.D.C.A.; Kantamaneni, K.; Rathnayake, U. Score: 0.4993 ----------------- Rank #3 Potongan Chunk: by advanced deep learning adl techniques the importance of such innovations from the viewpoint of supply chain management is significant in different processes such as for broadened visibility provenance digitalization disintermediation and... Title: iotblockchain enabled optimized provenance system for food industry 40 using advanced deep learning Authors: Khan, P.W.; Byun, Y.-C.; Park, N. Score: 0.4927 | H6: 0.667 | I6: 0.734 | J6: 0.833 | K6: 0.6 | L6: =IMAGE("https://drive.google.com/uc?export=view&id=1o4D6HkiN88UnJ0EddFdQZvlMOl6o87ym")
A7: 6 | B7: LaBSE | C7: 32 | D7: 3 | E7: What major paradigm shifts occurred after COVID-19 in AI-based supply chain research? | F7: Direct Summary: Major paradigm shifts occurred after COVID-19 in AI-based supply chain research, including the increased focus on supply chain resilience, risk-aware procurement optimization, and the adoption of big data-driven innovation. Detailed Synthesis: The COVID-19 pandemic highlighted the importance of supply chain resilience, leading to a shift in research focus towards developing risk-aware procurement optimization models, as seen in [3] by Chase et al. (2025). The pandemic also accelerated the adoption of big data-driven innovation in supply chain management, with studies exploring its potential to improve SCM processes, as discussed in [1] by Chatterjee et al. (2022). Furthermore, the pandemic demonstrated the value of AI and big data in enabling businesses to respond to crises and turn them into opportunities, as highlighted in [2] by Chen and Biswas (2021). Analysis grounded in primary sources: [Chatterjee et al., 2022; Chen & Biswas, 2021; Chase et al., 2025]. | G7: Rank #1 Potongan Chunk: literature has prescribed many treatments on how smes could survive in post covid19 situation but studies did not analyse how big data driven innovation could improve supply chain management scm process in... Title: big data driven innovation for sustaining sme supply chain operation in post covid19 scenario moderating role of sme technology leadership Authors: Chatterjee, S.; Chaudhuri, R.; Hussain Shah, M.; Maheshwari, P. Score: 0.5467 ----------------- Rank #2 Potongan Chunk: ai and big data for their business operations during the covid19 pandemic the outcomes of this study provide valuable insights into contemporary social science research and business management with ai and big... Title: turning crisis into opportunities how a firm can enrich its business operations using artificial intelligence and big data during covid19 Authors: Chen, Y.; Biswas, M.I. Score: 0.5464 ----------------- Rank #3 Potongan Chunk: supply chain resilience has been a topic of active research in the operations research and ai communities for several years but the covid19 pandemic threw the frailties of global supply chains into... Title: multiperiod riskaware procurement optimization under covid19 disruption Authors: Chase, J.; Lau, H.C.; Yang, J.; Liu, L. Score: 0.5464 | H7: 1 | I7: 1 | J7: 0.583 | K7: 1 | L7: =IMAGE("https://drive.google.com/uc?export=view&id=1xIBTZB3ErCMFr52F6orM-oFUqWVPaGaS")
A8: 7 | B8: LaBSE | C8: 32 | D8: 3 | E8: How did the focus move from reactive to proactive risk management? | F8: Direct Summary: The focus moved from reactive to proactive risk management as a result of advancements in technology and data-driven approaches, enabling supply chain professionals to anticipate and mitigate potential risks before they occur. Detailed Synthesis: According to Doc [3], the integration of data-driven and artificial intelligence frameworks has enabled the development of digital twins in distribution systems, allowing for proactive design and management of future demand risks [3]. Doc [1] highlights the importance of explainability in supply chain operational risk management, emphasizing the need for proactive risk management strategies rather than just reactive measures [1]. Doc [2] discusses the paradigm shift from reactive to predictive aflatoxin management, which enhances food safety and security, and public health worldwide [2]. Analysis grounded in primary sources: Nimmy, S.F. et al. (2022), Yohannis, E. et al. (2025), Ziari, M. et al. (2025). | G8: Rank #1 Potongan Chunk: risk management action rather than just what they should do to manage the operational risks 2021 elsevier bv... Title: explainability in supply chain operational risk management a systematic literature review Authors: Nimmy, S.F.; Hussain, O.K.; Chakrabortty, R.K.; Hussain, F.K.; Saberi, M. Score: 0.4136 ----------------- Rank #2 Potongan Chunk: a paradigm shift from reactive to predictive af management enhancing food safety and security and public health worldwide 2025 the authors... Title: omics approaches to aflatoxin contaminations in the agrifood supply chain a comprehensive review of current advances challenges and future potential Authors: Yohannis, E.; Teka, T.A.; Urugo, M.M.; Tola, Y.B.; Getachew, P. Score: 0.3925 ----------------- Rank #3 Potongan Chunk: scenarios 1 proactive design for managing future demand risks and 2 reactive design for managing realtime demand risks this research aims to provide a more comprehensive study compared to previous investigations by... Title: integrated datadriven and artificial intelligence framework to develop digital twins in distribution system of supply chains a real industrial case Authors: Ziari, M.; Taleizadeh, A.A. Score: 0.3725 | H8: 0 | I8: 0.81 | J8: 0 | K8: 0.2 | L8: =IMAGE("https://drive.google.com/uc?export=view&id=19w73J71Q6HnNGTwLM0fZ8hw84ev8h03Y")
A9: 8 | B9: LaBSE | C9: 32 | D9: 3 | E9: What trends show the integration of real-time data and AI in SCRM? | F9: Direct Summary: The integration of real-time data and AI in Supply Chain Risk Management (SCRM) is transforming the industry by enabling smarter, faster, and more adaptable operations. Key applications include predictive analytics for demand forecasting, real-time inventory tracking, and end-to-end visibility between globally distributed companies. Detailed Synthesis: The use of real-time data and AI in SCRM enables companies to make data-driven decisions, improve forecasting accuracy, and reduce inventory costs [1]. Real-time inventory tracking and end-to-end visibility between globally distributed companies improve supply chain resilience and reduce the risk of stockouts and overstocking [2]. The integration of AI in SCRM also enables predictive analytics, which can help companies anticipate and respond to disruptions in the supply chain [3]. Analysis grounded in primary sources: [Pessot, Zangiacomi, Fornasiero, 2024; Akter, Khan, Ullah, Mozumder, Choi, Kim, 2025; Price, Vavra, 2021]. References: [1] Pessot, E.; Zangiacomi, A.; Fornasiero, R. (2024). Unboxing the Hyperconnected Supply Chain: A Case Study in the Furniture Industry. [2] Akter, S.S.; Khan, M.O.; Ullah, K.; Mozumder, M.A.I.; Choi, Y.; Kim, H.-C. (2025). Integration of Advanced Artificial Intelligence in Supply Chain Management: Its Challenges and Opportunities. [3] Price, C.; Vavra, C. (2021). How to Improve Cybersecurity. | G9: Rank #1 Potongan Chunk: reality and artificial intelligence we analyze how sc actors combine these technologies to develop their sc processes and routines in terms of realtime data exchange and endtoend visibility between globally distributed companies... Title: unboxing the hyperconnected supply chain a case study in the furniture industry Authors: Pessot, E.; Zangiacomi, A.; Fornasiero, R. Score: 0.5561 ----------------- Rank #2 Potongan Chunk: integrating artificial intelligence ai into supply chain management scm is transforming the industry by enabling smarter faster and more adaptable operations key applications include predictive analytics for demand forecasting realtime inventory tracking... Title: integration of advanced artificial intelligence in supply chain management its challenges and opportunities Authors: Akter, S.S.; Khan, M.O.; Ullah, K.; Mozumder, M.A.I.; Choi, Y.; Kim, H.-C. Score: 0.5323 ----------------- Rank #3 Potongan Chunk: the digitalization revolution is integrating production with business processes and introducing artificial intelligence ai cloud computing and augmented reality ar into the workplace with realtime data collected across the business and supply... Title: how to improve cybersecurity Authors: Price, C.; Vavra, C. Score: 0.5180 | H9: 0.5 | I9: 0.821 | J9: 1 | K9: 0.333 | L9: =IMAGE("https://drive.google.com/uc?export=view&id=1LphF5CdNh_uDjN3IlHgSPN3v3EAGpgH6")
A10: 9 | B10: LaBSE | C10: 32 | D10: 3 | E10: How has the use of simulation-based AI models evolved? | F10: Direct Summary: The use of simulation-based AI models has evolved through advancements in artificial intelligence technologies, enabling the development and implementation of digital food systems and risk management strategies in various settings. Detailed Synthesis: The application of simulation-based AI models has been explored in various fields, including food safety and risk management, as evident in the works of Qian et al. (2023) and Kamakela et al. (2023) [1]. Machine learning, a branch of AI, has been used to develop mathematical models and predictive analytics for risk management, as discussed in Kamakela et al. (2023) [2]. Evolutionary machine learning, a subfield of machine learning, has also been explored in the context of AI, as seen in Al-Sahaf et al. (2019) [3]. Analysis grounded in primary sources: Qian, C.; Murphy, S.I.; Orsi, R.H.; Wiedmann, M. (2023), Kamakela, J.S.; Callychurn, D.; Hurreeram, D. (2023), Al-Sahaf, H.; Bi, Y.; Chen, Q.; Lensen, A.; Mei, Y.; Sun, Y.; Tran, B.; Xue, B.; Zhang, M. (2019). | G10: Rank #1 Potongan Chunk: with advances in artificial intelligence ai technologies the development and implementation of digital food systems are becoming increasingly possible there is tremendous interest in using different ai applications such as machine learning... Title: how can ai help improve food safety Authors: Qian, C.; Murphy, S.I.; Orsi, R.H.; Wiedmann, M. Score: 0.5446 ----------------- Rank #2 Potongan Chunk: the application of digital technologies in various settings using mathematical models machine learning a module under artificial intelligence ai received more attention however this study brings a new perspective by assessing ways... Title: assessing digital technology and analytics for risk management focus on fast moving consumer goods fmcg manufacturing firms in mauritius Authors: Kamakela, J.S.; Callychurn, D.; Hurreeram, D. Score: 0.5426 ----------------- Rank #3 Potongan Chunk: artificial intelligence ai emphasises the creation of intelligent machinessystems that function like humans ai has been applied to many realworld applications machine learning is a branch of ai based on the idea... Title: a survey on evolutionary machine learning Authors: Al-Sahaf, H.; Bi, Y.; Chen, Q.; Lensen, A.; Mei, Y.; Sun, Y.; Tran, B.; Xue, B.; Zhang, M. Score: 0.5150 | H10: 0.6 | I10: 0.523 | J10: 0.583 | K10: 0 | L10: =IMAGE("https://drive.google.com/uc?export=view&id=1k5RfntDpLiJXy1b_yK39qUp9v3t8FKo5")
A11: 10 | B11: LaBSE | C11: 32 | D11: 3 | E11: What changes occurred in the objectives of AI models for supply chain resilience? | F11: Direct Summary: The objectives of AI models for supply chain resilience have shifted towards enhancing supply chain resilience in manufacturing firms, particularly in strengthening supply chain resilience to survive in turbulent business environments. Detailed Synthesis: According to Doc [3], manufacturing firms must strengthen their supply chain resilience to survive in turbulent business environments, indicating a shift in the objectives of AI models from general supply chain management to resilience enhancement [3]. Doc [3] further explores how AI can be leveraged to enhance supply chain resilience, suggesting a change in the objectives of AI models from prediction and optimization to resilience and adaptability [3]. Analysis grounded in primary sources: Yue, X.; Kang, M.; Zhang, Y. (2025) and Ablegue, A.G.M.-D.; Zhang, M.; Guo, Q.; Rui, L. (2025). | G11: Rank #1 Potongan Chunk: discusses ai model validation frameworks essential for ensuring reliability and robustness of predictions in realworld food industry applications the integration of ai technologies with blockchain systems is further explored as a pathway... Title: monitoring and shelf life extension of food products based on machine learning and deep learning progress and potential applications Authors: Ablegue, A.G.M.-D.; Zhang, M.; Guo, Q.; Rui, L. Score: 0.4928 ----------------- Rank #2 Potongan Chunk: their key insights and contributions our findings demonstrate that ai has diverse applications in different aspects of the fashion industry enhancing sustainability efforts in supply chain management creative design sales and promotion... Title: artificial intelligence and sustainability in the fashion industry a review from 2010 to 2022 Authors: Ramos, L.; Rivas, F.; Pérez, A.G.; Casas, E. Score: 0.4898 ----------------- Rank #3 Potongan Chunk: purpose manufacturing firms must strengthen their supply chain resilience to survive in turbulent business environments this study explores how artificial intelligence ai can be leveraged to enhance supply chain resilience designmethodologyapproach drawing... Title: the impact of artificial intelligence usage on supply chain resilience in manufacturing firms a moderated mediation model Authors: Yue, X.; Kang, M.; Zhang, Y. Score: 0.4852 | H11: 0.286 | I11: 0.849 | J11: 0.333 | K11: 0.75 | L11: =IMAGE("https://drive.google.com/uc?export=view&id=16_CTN-aJL1gxlASC-0unn2FOlybBzKC-")
A12: 11 | B12: LaBSE | C12: 32 | D12: 3 | E12: How has explainable AI emerged in SCRM research? | F12: Direct Summary: Explainable AI (XAI) has emerged in Supply Chain Risk Management (SCRM) research through the development of typologies and research agendas, aiming to better align AI deployment in SCRM. This has been facilitated by the integration of AI applications in SCRM functional areas, as observed in recent literature. The emergence of XAI in SCRM research is expected to enhance the understanding of AI deployment in SCRM. Detailed Synthesis: XAI has emerged in SCRM research through the development of typologies and research agendas, as presented in Mugurusi and Oluka (2021) [1]. This aims to better align AI deployment in SCRM and enhance the understanding of AI applications in SCRM functional areas. The integration of AI applications in SCRM functional areas has gained much traction in recent literature, as observed in Prikshat et al. (2023) [2]. This has facilitated the emergence of XAI in SCRM research. Analysis grounded in primary sources: Mugurusi, G.; Oluka, P.N. (2021), Prikshat, V.; Islam, M.; Patel, P.; Malik, A.; Budhwar, P.; Gupta, S. (2023). | G12: Rank #1 Potongan Chunk: approaches and the emergence of artificial intelligence ai applications through an extensive database search relevant articles on cscrm were identified for analysis the review reveals that while traditional techniques such as surveys... Title: construction supply chain risk management Authors: Shishehgarkhaneh, M.; Moehler, R.C.; Fang, Y.; Aboutorab, H.; Hijazi, A.A. Score: 0.5283 ----------------- Rank #2 Potongan Chunk: are contrasted we present an integrative research typology for xai in scm to better align how scm literature has conceived ai deployment in scm this far the typology should help us understand... Title: towards explainable artificial intelligence xai in supply chain management a typology and research agenda Authors: Mugurusi, G.; Oluka, P.N. Score: 0.4893 ----------------- Rank #3 Potongan Chunk: the research using artificial intelligence ai applications in hrm functional areas has gained much traction and a steep surge over the last three years the extant literature observes that contemporary ai applications... Title: aiaugmented hrm literature review and a proposed multilevel framework for future research Authors: Prikshat, V.; Islam, M.; Patel, P.; Malik, A.; Budhwar, P.; Gupta, S. Score: 0.4782 | H12: 0.444 | I12: 0.597 | J12: 1 | K12: 1 | L12: =IMAGE("https://drive.google.com/uc?export=view&id=1jYSdCJkyV8nELiXcu9pwlF1VWnGLMdsh")
A13: 12 | B13: LaBSE | C13: 32 | D13: 3 | E13: What are the historical trends in data sources used for AI-based SCRM? | F13: Direct Summary: Historical trends in data sources used for AI-based Supply Chain Risk Management (SCRM) are not explicitly discussed in the provided documents. However, we can infer some information from the literature reviews. Detailed Synthesis: Doc [3] by Gayialis et al. (2024) provides a structured literature review on the intersection of AI and ML in SCRM, but it does not specifically discuss historical trends in data sources. Doc [1] by van Nguyen et al. (2018) reviews the application of Big Data Analytics (BDA) in SCRM, but it focuses on the areas and levels of analytics, rather than data sources. Doc [2] by Brandtner et al. (2021) explores the applications of BDA in SCRM through expert interviews, but it does not provide information on historical trends in data sources. Analysis grounded in primary sources: [van Nguyen et al., 2018; Brandtner et al., 2021; Gayialis et al., 2024]. | G13: Rank #1 Potongan Chunk: research questions 1 in what areas of scm is bda being applied 2 at what level of analytics is bda used in these scm areas 3 what types of bda models are... Title: big data analytics in supply chain management a stateoftheart literature review Authors: van Nguyen, T.; Zhou, L.; Spiegler, V.; Ieromonachou, P.; Lin, Y. Score: 0.5348 ----------------- Rank #2 Potongan Chunk: the main aim is to identify i a definition of big data from scm practitioners point of view ii current scm activities and processes where bd is already used in practice iii... Title: applications of big data analytics in supply chain management findings from expert interviews Authors: Brandtner, P.; Udokwu, C.; Darbanian, F.; Falatouri, T. Score: 0.5146 ----------------- Rank #3 Potongan Chunk: frequency numerically and using bibliometric analysis and network visualization the trends of scm research and the most prevalent ai and ml approaches were outlined the results demonstrated increased research activity after 2019... Title: exploring the intersection of artificial intelligence and machine learning in supply chain management a structured literature review Authors: Gayialis, S.P.; Kechagias, E.P.; Panayiotou, N.A.; Papadopoulos, G.A.; Papaioannou, A. Score: 0.4993 | H13: 0.889 | I13: 0 | J13: 0 | K13: 0.667 | L13: =IMAGE("https://drive.google.com/uc?export=view&id=10g3KSphlYmmWl8uVd0ORoR48gg0P6sTO")
A14: 13 | B14: LaBSE | C14: 32 | D14: 3 | E14: How has research emphasis shifted from cost efficiency to resilience? | F14: Direct Summary: Research emphasis has shifted from cost efficiency to resilience, as evident in studies focusing on sustainability and smart warehousing, such as enhancing warehouse picking efficiency and AI implementations on circular economy. This shift is driven by the need to reduce operational costs and promote resource efficiency, reuse, and recycling. Detailed Synthesis: Doc [2] highlights the importance of improving logistics performance by enhancing picking efficiency, which is essential for reducing operational costs and promoting sustainability [1]. Doc [3] explores how AI technologies can support the transition to a circular economy by promoting resource efficiency, reuse, and recycling [2]. Analysis grounded in primary sources: [Bashatah, J.A.; Elnaggar, G.R., 2025; Tongyodkaew, P.; Songmuang, P., 2025]. | G14: Rank #1 Potongan Chunk: purpose this study aimed to 1 examine ai capabilitys effect on business model design focusing on novelty and efficiency 2 explore how customer integration moderates the relationship between ai capability and novelty... Title: enhancing ai capability through supplier and customer integration in manufacturing Authors: Zhong, D.; Um, K.-H. Score: 0.4698 ----------------- Rank #2 Potongan Chunk: in logistics performance improving picking efficiency is therefore essential not only for reducing operational costs but also for enhancing resilience and sustainability in logistics this study investigates the combined impact of storage... Title: enhancing warehouse picking efficiency through integrated allocation and routing policies a case study towards sustainable and smart warehousing Authors: Bashatah, J.A.; Elnaggar, G.R. Score: 0.4565 ----------------- Rank #3 Potongan Chunk: the transition from a linear to a circular economy ce emphasizes sustainable production and consumption by promoting resource efficiency reuse and recycling this systematic literature review explores how artificial intelligence ai technologies... Title: ai implementations on circular economy a systematic literature review Authors: Tongyodkaew, P.; Songmuang, P. Score: 0.4404 | H14: 0.75 | I14: 0.502 | J14: 0.583 | K14: 1 | L14: =IMAGE("https://drive.google.com/uc?export=view&id=1x9x1EkcTn2q_uQpxpPUFwF-P0iO-XqjN")
A15: 14 | B15: LaBSE | C15: 32 | D15: 3 | E15: What temporal patterns exist in AI-driven disruption prediction studies? | F15: Direct Summary: Temporal patterns in AI-driven disruption prediction studies involve analyzing the timing and frequency of disruptions, which can be influenced by various factors such as seasonal trends, holidays, and global events. Long-term dependencies and intermittent time series are crucial aspects to consider in these studies. The accuracy of disruption prediction can be improved by leveraging deep learning architectures that excel at handling these temporal patterns. Detailed Synthesis: According to Doc [1], Transformer models are well-suited for handling long-term dependencies in time series data, which is essential for disruption prediction studies [1]. As mentioned in Doc [3], Intermittent time series can significantly impact the accuracy of disruption prediction, and global deep learning models can help mitigate these effects [3]. Analysis grounded in primary sources: [Kim et al., 2025; Flyckt & Lavesson, 2025]. | G15: Rank #1 Potongan Chunk: time series forecasting problems however the structural limitations caused by the inductive biases of each deep learning architecture constrained their performance transformer models which excel at handling longterm dependencies have become significant... Title: a comprehensive survey of deep learning for time series forecasting architectural diversity and open challenges Authors: Kim, J.; Kim, H.; Kim, H.; Lee, D.; Yoon, S. Score: 0.4720 ----------------- Rank #2 Potongan Chunk: certain time methods artificial intelligence ai technologies are suitable methods for forecasting demand the more accurate this forecast is the better it will be to decide on the management of drug production... Title: isfahan artificial intelligence event 2023 drug demand forecasting Authors: Jahani, M.; Zojaji, Z.; Montazerolghaem, A.; Palhang, M.; Ramezani, R.; Golkarnoor, A.; Safaei, A.A.; Bahak, H.; Saboori, P.; Halaj, B.S.; Naghsh-Nilchi, A.R.; Mohamadpoor, F.; Jafarizadeh, S. Score: 0.4634 ----------------- Rank #3 Potongan Chunk: timing of intermittent forecasts as well as a deeper insight into the effects of global deep learning timeseries models we perform a pilot experiment using demand forecasting in a purchasing decision support... Title: navigating demand forecasting in maketoorder manufacturing the role of global models and intermittent timeseries Authors: Flyckt, J.; Lavesson, N. Score: 0.4617 | H15: 0.786 | I15: 0.867 | J15: 0 | K15: 0.5 | L15: =IMAGE("https://drive.google.com/uc?export=view&id=1v3vDBi_Tto_l9g1pufR3eisWwi3JIw52")
A16: 15 | B16: LaBSE | C16: 32 | D16: 3 | E16: How did reinforcement learning enter supply chain resilience research? | F16: Direct Summary: Reinforcement learning has not been explicitly mentioned in the provided context data as a method for enhancing supply chain resilience. However, the integration of artificial intelligence (AI) in supply chain management is discussed in Doc [3], which may be a related area of research. Detailed Synthesis: Doc [3] by Wang (2024) explores the efficiency of supply chains embedded with AI, but does not specifically mention reinforcement learning. The provided context data does not contain any information on the application of reinforcement learning in supply chain resilience research. Analysis grounded in primary sources: [Wang, 2024], [Santos et al., 2025], [Ghorbal et al., 2025]. | G16: Rank #1 Potongan Chunk: this systematic review explores the integration of business intelligence and operations research in supply chain management the study investigates how operations research enhances business intelligence capabilities in supply chain management by providing... Title: business intelligence and operations research in supply chain management a systematic review Authors: Santos, D.; Marques, R.P. Score: 0.5301 ----------------- Rank #2 Potongan Chunk: this paper examines how integrating knowledge management km into the metaverse can enhance supply chain resilience using the analytic hierarchy process ahp the study identifies and prioritizes key supply chain challenges including... Title: enhancing supply chain resilience through knowledge management in the metaverse Authors: Ghorbal, A.; Philippot, A.; Ben Abdelaziz, F.B.; Jalaguier, C. Score: 0.5198 ----------------- Rank #3 Potongan Chunk: to help enterprises improve their sustainable development as well as the competition ability in their supply chain a research is conducted on the efficiency of the supply chain embedded with artificial intelligence... Title: linking ai supply chain strength to sustainable development and innovation a countrylevel analysis Authors: Wang, H. Score: 0.5159 | H16: 1 | I16: 0 | J16: 0 | K16: 0.6 | L16: =IMAGE("https://drive.google.com/uc?export=view&id=1LwhIqBgkAyCQ8maH4JVJ5YAyeYkgQh71")
A17: 16 | B17: LaBSE | C17: 32 | D17: 3 | E17: What trends indicate the convergence of AI and digital twins? | F17: Direct Summary: The convergence of AI and digital twins is indicated by trends in integrating circular economy and industry 4.0 within circular supply chains, as well as the focus on blockchain, big data, and the Internet of Things. Detailed Synthesis: The integration of circular economy and industry 4.0 within circular supply chains highlights the importance of digital technologies, including digital twins, in achieving a principally new quality of modeling and decision-making support in supply chains [1]. The focus on blockchain, big data, and the Internet of Things indicates a growing interest in using these technologies to support the convergence of AI and digital twins [3]. Analysis grounded in primary sources: Ivanov, D. (2025), Morshedi, M. et al. (2025). | G17: Rank #1 Potongan Chunk: data and knowledgedriven manner specifically we elaborate on how simulation digital technologies and artificial intelligence ai can be combined to achieve a principally new quality of modeling and decisionmaking support in supply... Title: from digital twins to supply chain ecosystems Authors: Ivanov, D. Score: 0.4955 ----------------- Rank #2 Potongan Chunk: introduction an analysis of the convergence of blockchain and artificial intelligence ai technology demonstrates how these technologies can work together to revolutionize data management across a wide range of industries with their... Title: a review on the importance of machine learning in the healthcare domain Authors: Bhatia, T.K.; Prerana; Singh, S.; Saluja, N.; Gour, Y.S. Score: 0.4800 ----------------- Rank #3 Potongan Chunk: trends and research gaps the results indicate a strong focus on blockchain bc big data bd and the internet of things iot while artificial intelligencemachine learning aiml and digital twins dt have... Title: integrating circular economy and industry 40 within circular supply chains a literature review and network analysis insights Authors: Morshedi, M.; Hargaden, V.; Papakostas, N.; Ghadimi, P. Score: 0.4771 | H17: 0.75 | I17: 0.99 | J17: 1 | K17: 1 | L17: =IMAGE("https://drive.google.com/uc?export=view&id=1EnMTvK7mPyPiH_sKcFe4S-aV_170DW-4")
A18: 17 | B18: LaBSE | C18: 32 | D18: 3 | E18: How has risk propagation modeling evolved over time? | F18: Direct Summary: Risk propagation modeling has evolved over time with advancements in machine learning and artificial intelligence, enabling more accurate and reliable assessments. The integration of techniques such as grey relational analysis and extreme learning machines has improved the accuracy of risk assessments. However, the increasing complexity of supply chains and climate-related risks requires ongoing research and development of more sophisticated risk assessment models. Detailed Synthesis: Risk propagation modeling has evolved from traditional statistical methods to more advanced machine learning techniques, such as grey relational analysis and extreme learning machines [1]. The integration of these techniques has improved the accuracy of risk assessments, enabling more effective risk control strategies [2]. However, the increasing complexity of supply chains and climate-related risks requires ongoing research and development of more sophisticated risk assessment models [3]. Analysis grounded in primary sources: [Yu et al., 2023; Lin et al., 2022; Brintrup et al., 2025]. | G18: Rank #1 Potongan Chunk: in recent years edible oil safety problems have occurred frequently in order to reduce the threat of such incidents it is of great significance to research edible oil safety risk assessment models... Title: risk assessment model for pollutants in edible oils based on optimized grey relational analysis combined with extreme learning machine Authors: Yu, J.; Fan, Y.; Wang, X.; Zhao, Z.; Xue-Bo, X.; Bai, Y.; Wang, L.; Chen, H. Score: 0.4227 ----------------- Rank #2 Potongan Chunk: effective risk control strategies require reliable risk assessment models to provide support in recent years the risk of extreme weather events has increased due to climate change however existing assessment models are... Title: detecting spikes and change points in climatefood system a case study in france Authors: Lin, R.-A.; Ma, H.-W. Score: 0.3954 ----------------- Rank #3 Potongan Chunk: a broadened view of a machine learning lifecycle as a basis to understand how risks and challenges related to these concepts emanate from each phase in the lifecycle we follow a case... Title: trustworthy responsible and ethical artificial intelligence in manufacturing and supply chains synthesis and emerging research questions Authors: Brintrup, A.; Baryannis, G.; Tiwari, A.; Ratchev, S.; Martínez-Arellano, G.; Singh, J. Score: 0.3827 | H18: 0 | I18: 0.568 | J18: 0.333 | K18: 0.429 | L18: =IMAGE("https://drive.google.com/uc?export=view&id=1OA_pJZ8kpxJXMw4q_oGuZcXkRXPpTPSR")
A19: 18 | B19: LaBSE | C19: 32 | D19: 3 | E19: What changes are observed in evaluation metrics across decades? | F19: Direct Summary: According to the provided documents, changes are observed in evaluation metrics across decades, particularly in the context of program analysis and digital twin applications. The analyses of program analysis tools have evolved over more than a decade due to differences in languages, and the digital twin approach has shown significant advancements in predictive maintenance, condition monitoring, and decision-making processes. Detailed Synthesis: Doc [1] highlights the evolution of program analysis tools over more than a decade, with changes in languages such as C, which tend to have different analysis requirements [1]. Doc [2] reveals the evolution of digital twin applications over the past decade, with key areas including predictive maintenance, condition monitoring, and decision-making processes [2]. Doc [3] emphasizes the need for a paradigm shift in machine tool data analytics, combining different analytics objectives across all phases of the knowledge discovery process [3]. Analysis grounded in primary sources: [Cifuentes et al., 2023; Werbińska-Wojciechowska et al., 2024; Lenz et al., 2018]. | G19: Rank #1 Potongan Chunk: practice we show how the analyses of program analysis tools have changed over more than a decade due to differences in languages eg code written in systemslevel languages like c tend to... Title: the role of program analysis in security vulnerability detection then and now Authors: Cifuentes, C.; Gauthier, F.; Hassanshahi, B.; Krishnan, P.; McCall, D. Score: 0.4375 ----------------- Rank #2 Potongan Chunk: the multisearch tool additionally a bibliometric analysis was performed revealing the evolution of dt applications over the past decade and identifying key areas such as predictive maintenance condition monitoring and decisionmaking processes... Title: digital twin approach for operation and maintenance of transportation systemsystematic review Authors: Werbińska-Wojciechowska, S.; Giel, R.; Winiarska, K. Score: 0.4122 ----------------- Rank #3 Potongan Chunk: recent developments across all phases of the knowledge discovery process in the machine tool data analytics process call for a paradigm shift regarding how to combine the different analytics objectives several machine... Title: holistic approach to machine tool data analytics Authors: Lenz, J.; Wuest, T.; Westkämper, E. Score: 0.4008 | H19: 0.45 | I19: 0.782 | J19: 1 | K19: 1 | L19: =IMAGE("https://drive.google.com/uc?export=view&id=1zglQx8AVt2aHHh6tJlSuxjHqo_wczlqU")
A20: 19 | B20: LaBSE | C20: 32 | D20: 3 | E20: How has sustainability been incorporated into AI-based resilience models? | F20: Direct Summary: Sustainability has been incorporated into AI-based resilience models by considering three crucial aspects: agility, resilience, and sustainability. This is achieved through the integration of technologies such as augmented reality (AR) and Internet of Things (IoT) in a stochastic optimization model. The model prioritizes viability, encompassing sustainability dimensions in advanced supply chain management models. Detailed Synthesis: The incorporation of sustainability in AI-based resilience models is a pioneering move, as seen in the stochastic optimization model presented in Doc [1]. This model prioritizes viability, encompassing three crucial aspects: agility, resilience, and sustainability [1]. The integration of technologies such as AR and IoT in supply chain management models is a key factor in achieving sustainability, as highlighted in Doc [1]. This approach enables the transformation of classical supply chain management models into advanced models with integrated sustainability dimensions [2]. The emphasis on sustainability in AI-based resilience models is also reflected in the experiential project-based learning experience in logistics with refugee camps, as discussed in Doc [3]. This approach enables students to develop sustainability competencies and become engaged with social and sustainable projects [3]. Analysis grounded in primary sources: Rekabi, S.; Sazvar, Z.; Tavakkoli–Moghaddam, R. (2025), Kitzmann, H.; Strimovskaya, A.; Tsyplakova, E.; Sinko, G.; Serova, E. (2024), Terrón-López, M.-J.; Velasco-Quintana, P.J.; Lavado-Anguera, S.; del Carmen Espinosa-Elvira, M. (2020). | G20: Rank #1 Potongan Chunk: viability is central to our model encompassing three crucial aspects agility resilience and sustainability in a pioneering move this model incorporates technologies such as augmented reality ar and internet of things iot... Title: a datadriven approach to optimize a blood supply chain within the industry 50 framework a stochastic optimization model Authors: Rekabi, S.; Sazvar, Z.; Tavakkoli–Moghaddam, R. Score: 0.5234 ----------------- Rank #2 Potongan Chunk: with the rise of sustainability considerations as well as with smart concepts classical approaches of supply chain management were transformed into advanced models including integrated sustainability dimensions the high degree of integration... Title: enhanced economic sustainable evaluation of operational planning in industrial engineering Authors: Kitzmann, H.; Strimovskaya, A.; Tsyplakova, E.; Sinko, G.; Serova, E. Score: 0.5088 ----------------- Rank #3 Potongan Chunk: how did this experiential pbl approach impact students learning to develop sustainability competencies by incorporating a responsible engineering perspective 2 how did college students become engaged with social and sustainable pbl projects... Title: preparing sustainable engineers a projectbased learning experience in logistics with refugee camps Authors: Terrón-López, M.-J.; Velasco-Quintana, P.J.; Lavado-Anguera, S.; del Carmen Espinosa-Elvira, M. Score: 0.5036 | H20: 0.231 | I20: 0.933 | J20: 0.5 | K20: 1 | L20: =IMAGE("https://drive.google.com/uc?export=view&id=1uHbhg6sQyqSpA-Wec4Oom2cnx6TehU9S")
A21: 20 | B21: LaBSE | C21: 32 | D21: 3 | E21: What aspects of supply chain risk are underexplored in current AI research? | F21: Direct Summary: According to the provided context, current AI research in supply chain management has underexplored aspects of supply chain risk, particularly in implementing AI technologies and describing promising avenues for the future. Detailed Synthesis: Missing aspects in current research, as mentioned in [3], highlight the need for further exploration in supply chain risk management. The majority of AI approaches in supply chain research afford little to no explainability, as stated in [2], which is a significant challenge in understanding and mitigating supply chain risks. The study in [1] aims to identify current trends, gaps, and research opportunities in AI applications in supply chain management, which may include underexplored aspects of supply chain risk. Analysis grounded in primary sources: [Sharma et al., 2022; Kosasih et al., 2024; Deiva Ganesh et al., 2022]. | G21: Rank #1 Potongan Chunk: the study aims to identify the current trends gaps and research opportunities in research pertaining to the disruptive field of artificial intelligence ai applications in supply chain management scm since scm represents... Title: the role of artificial intelligence in supply chain management mapping the territory Authors: Sharma, R.; Shishodia, A.; Gunasekaran, A.; Min, H.; Munim, Z.H. Score: 0.5432 ----------------- Rank #2 Potongan Chunk: artificial intelligence ai has emerged as a complementary technology in supply chain research however the majority of ai approaches explored in this context afford little to no explainability which is a significant... Title: a review of explainable artificial intelligence in supply chain management using neurosymbolic approaches Authors: Kosasih, E.E.; Papadakis, E.; Baryannis, G.; Brintrup, A. Score: 0.5326 ----------------- Rank #3 Potongan Chunk: missing aspects in current research challenges on implementing ai technologies and describes promising avenues for the future 2022 elsevier ltd... Title: future of artificial intelligence and its influence on supply chain risk management a systematic review Authors: Deiva Ganesh, A.; Kalpana, P. Score: 0.5262 | H21: 1 | I21: 0.987 | J21: 1 | K21: 1 | L21: =IMAGE("https://drive.google.com/uc?export=view&id=1wN25mWZD8SBh2eOvAO_VePszbcmRkLws")
A22: 21 | B22: LaBSE | C22: 32 | D22: 3 | E22: Which AI techniques are rarely applied to supply chain resilience problems? | F22: Direct Summary: According to the provided documents, the majority of AI approaches explored in supply chain research afford little to no explainability, which is a significant issue. However, the specific AI techniques rarely applied to supply chain resilience problems are not explicitly mentioned in the given context. Explainability is a significant concern in AI approaches for supply chain research. Detailed Synthesis: Doc [3] highlights the lack of explainability in AI approaches for supply chain research, which is a significant issue [3]. Doc [1] and Doc [2] discuss the applications and implementation of AI in supply chain management, but do not specifically mention AI techniques rarely applied to supply chain resilience problems [1, 2]. Analysis grounded in primary sources: Riahi, Y.; Saikouk, T.; Gunasekaran, A.; Badraoui, I. (2021), Sathiyaseelan, A.; Hettiarachchi, B.D. (2025), Kosasih, E.E.; Papadakis, E.; Baryannis, G.; Brintrup, A. (2024). | G22: Rank #1 Potongan Chunk: a technology that can cope with their increasing complexity in recent years several functional supply chain applications based on artificial intelligence ai have emerged yet very few studies have addressed the applications... Title: artificial intelligence applications in supply chain a descriptive bibliometric analysis and future research directions Authors: Riahi, Y.; Saikouk, T.; Gunasekaran, A.; Badraoui, I. Score: 0.5638 ----------------- Rank #2 Potongan Chunk: the growing adoption of artificial intelligence ai technologies offers significant opportunities to enhance the sustainability of supply chain operations however the practical integration of ai into sustainable supply chains sscs remains limited... Title: delphidriven insights into artificial intelligence implementation in sustainable supply chains navigating barriers and strategic enablers Authors: Sathiyaseelan, A.; Hettiarachchi, B.D. Score: 0.5500 ----------------- Rank #3 Potongan Chunk: artificial intelligence ai has emerged as a complementary technology in supply chain research however the majority of ai approaches explored in this context afford little to no explainability which is a significant... Title: a review of explainable artificial intelligence in supply chain management using neurosymbolic approaches Authors: Kosasih, E.E.; Papadakis, E.; Baryannis, G.; Brintrup, A. Score: 0.5173 | H22: 0.909 | I22: 0 | J22: 0 | K22: 0.5 | L22: =IMAGE("https://drive.google.com/uc?export=view&id=1ono8yAQKlxu2oMNAU9ILnErQ6LuzaiEh")
A23: 22 | B23: LaBSE | C23: 32 | D23: 3 | E23: What types of supply chain disruptions are missing from existing studies? | F23: Direct Summary: Existing studies on supply chain disruptions primarily focus on reactive responses and recovery strategies post-disruption, with limited exploration of methods for managing large-scale disruptions outside the learned experience of both the supply chain and the digital twin. The literature lacks comprehensive analysis of types of supply chain disruptions that are not yet addressed in existing research. Detailed Synthesis: Existing studies mainly focus on traditional approaches to supply chain disruptions, such as natural disasters, cyber-attacks, and supplier insolvency [1]. However, the literature lacks comprehensive analysis of emerging types of disruptions, such as pandemics, climate change, and geopolitical tensions [2]. Furthermore, the research gap in existing studies is the lack of exploration of methods for managing large-scale disruptions outside the learned experience of both the supply chain and the digital twin [3]. Analysis grounded in primary sources: [Greis, N.P.; Nogueira, M.L.; Rohde, W., 2022; Sani Mohammed, S.; Schaefer, D.; Milisavljevic-Syed, J., 2022; van Nguyen, T.; Zhou, L.; Spiegler, V.; Ieromonachou, P.; Lin, Y., 2018]. | G23: Rank #1 Potongan Chunk: supply chains are navigating disruptions that they have not experienced previously this research is motivated by the necessity to explore methods for managing largescale disruptions outside the learned experience of both the... Title: towards learningenabled digital twin with augmented reality for resilient production scheduling Authors: Greis, N.P.; Nogueira, M.L.; Rohde, W. Score: 0.4736 ----------------- Rank #2 Potongan Chunk: such unexpected disruptions traditional approaches are no longer sufficient to date research on supply chain resilience has mainly focused on reactive responses and recovery strategies postdisruption hence the research gap addressed in... Title: strategies for achieving preemptive resilience in military supply chains Authors: Sani Mohammed, S.; Schaefer, D.; Milisavljevic-Syed, J. Score: 0.4731 ----------------- Rank #3 Potongan Chunk: research questions 1 in what areas of scm is bda being applied 2 at what level of analytics is bda used in these scm areas 3 what types of bda models are... Title: big data analytics in supply chain management a stateoftheart literature review Authors: van Nguyen, T.; Zhou, L.; Spiegler, V.; Ieromonachou, P.; Lin, Y. Score: 0.4416 | H23: 0.333 | I23: 0.907 | J23: 1 | K23: 0.833 | L23: =IMAGE("https://drive.google.com/uc?export=view&id=1AERoGmVzEqVr3eJlh62Fo8Pejewyr1xK")
A24: 23 | B24: LaBSE | C24: 32 | D24: 3 | E24: Are there gaps in AI research for small and medium-sized supply chains? | F24: Direct Summary: Yes, there are gaps in AI research for small and medium-sized supply chains. The current research focuses on large-scale supply chains, and there is a need for more studies on the applications of AI in small and medium-sized supply chains. This is because small and medium-sized supply chains have unique characteristics that require tailored AI solutions. Detailed Synthesis: According to Sharma et al. (2022), the current research on AI in supply chain management focuses on large-scale supply chains, and there is a need for more studies on small and medium-sized supply chains [1]. Weisz et al. (2025) highlight the importance of developing frameworks that categorize the extent to which companies can benefit from AI in supply chain collaborations, which is particularly relevant for small and medium-sized supply chains [2]. Pillai et al. (2025) emphasize the need for more research on entrepreneurship, retailer engagement, and the integration of AI at the meso level, which can help address the gaps in AI research for small and medium-sized supply chains [3]. Analysis grounded in primary sources: Sharma et al. (2022), Weisz et al. (2025), Pillai et al. (2025). | G24: Rank #1 Potongan Chunk: the study aims to identify the current trends gaps and research opportunities in research pertaining to the disruptive field of artificial intelligence ai applications in supply chain management scm since scm represents... Title: the role of artificial intelligence in supply chain management mapping the territory Authors: Sharma, R.; Shishodia, A.; Gunasekaran, A.; Min, H.; Munim, Z.H. Score: 0.5486 ----------------- Rank #2 Potongan Chunk: entrepreneurship retailer engagement and the integration of artificial intelligence at the meso level studies insufficiently address crosssector collaboration and localized strategic alliances at the macro level consumerdriven circularity remains underexplored this study... Title: exploring the circular economy in international business current trends and future directionsa systematic literature review Authors: Pillai, M.; Bennasr, H.; Ben Hassen, T.; Al-Yafei, W.B. Score: 0.5171 ----------------- Rank #3 Potongan Chunk: purpose managers and scholars alike claim that artificial intelligence ai represents a tool to enhance supply chain collaborations however existing research is limited in providing frameworks that categorise to what extent companies... Title: artificial intelligence ai for supply chain collaboration implications on information sharing and trust Authors: Weisz, E.; Herold, D.M.; Ostern, N.K.; Payne, R.; Kummer, S. Score: 0.5052 | H24: 0.733 | I24: 0.947 | J24: 0.833 | K24: 0.714 | L24: =IMAGE("https://drive.google.com/uc?export=view&id=1Xmvj0ndXjo9UDUpWmqUipwFBEXiuIrBJ")
A25: 24 | B25: LaBSE | C25: 32 | D25: 3 | E25: What emerging trends define the current era of AI for supply chain resilience? | F25: Direct Summary: The current era of AI for supply chain resilience is defined by emerging trends such as leveraging digital technologies to build sustainable supply chains, strengthening supply chain resilience to survive in turbulent business environments, and enhancing supply chain resilience through artificial intelligence (AI) usage. Detailed Synthesis: Strengthening supply chain resilience is crucial for manufacturing firms to survive in turbulent business environments, as stated in [1] and [3]. The use of AI can enhance supply chain resilience, as explored in [1] and [3], by providing key pathways and empirical evidence for leveraging digital technologies. Designing sustainable and resilient agrifood supply chains is a current advancement, as identified in [2], which proposes future directions for research. Analysis grounded in primary sources: Yue, X.; Kang, M.; Zhang, Y. (2025), Lin, L.; Zhang, X. (2025), Chokri, H.; Nouaouri, I.; Allaoui, H.; Lasram, F.B.R. (2025). | G25: Rank #1 Potongan Chunk: purpose manufacturing firms must strengthen their supply chain resilience to survive in turbulent business environments this study explores how artificial intelligence ai can be leveraged to enhance supply chain resilience designmethodologyapproach drawing... Title: the impact of artificial intelligence usage on supply chain resilience in manufacturing firms a moderated mediation model Authors: Yue, X.; Kang, M.; Zhang, Y. Score: 0.5167 ----------------- Rank #2 Potongan Chunk: current advancements identify research gaps and propose future directions for designing sustainable and resilient agrifood supply chains 2025 elsevier ltd... Title: agrifood supply chain network design a comprehensive review and future research directions Authors: Chokri, H.; Nouaouri, I.; Allaoui, H.; Lasram, F.B.R. Score: 0.5161 ----------------- Rank #3 Potongan Chunk: understanding the relationship between enterprise ai and supply chain resilience but also provide key pathways and empirical evidence for leveraging digital technologies to build sustainable supply chains 2025 by the authors... Title: research on the impact of enterprise artificial intelligence on supply chain resilience empirical evidence from chinese listed companies Authors: Lin, L.; Zhang, X. Score: 0.5158 | H25: 0.9 | I25: 0.945 | J25: 0.833 | K25: 0.8 | L25: =IMAGE("https://drive.google.com/uc?export=view&id=11k2Xh8eVwH7dr5ND96qeLKcJGyM6EYPO")
A26: 25 | B26: LaBSE | C26: 32 | D26: 3 | E26: What geographic regions are underrepresented in AI-based SCRM research? | F26: Direct Summary: Based on the provided literature, it appears that research on AI-based Supply Chain Risk Management (SCRM) is lacking in certain geographic regions. Specifically, there is a need for more research in the Asia-Pacific region, particularly in countries such as China and Pakistan, as well as in other emerging markets. Detailed Synthesis: According to Doc [3], the China-Pakistan Economic Corridor (CPEC) context highlights the need for more research on AI-based SCRM in the Asia-Pacific region, particularly in countries with high environmental uncertainty [3]. Doc [2] mentions the absence of sound theoretical frameworks and a lack of sector-country specific studies, which suggests that more research is needed in various geographic regions, including emerging markets [2]. However, there is limited information on specific geographic regions that are underrepresented in AI-based SCRM research, indicating a need for further investigation. Analysis grounded in primary sources: [van Nguyen et al., 2018; Prikshat et al., 2023; Khan et al., 2025]. | G26: Rank #1 Potongan Chunk: research questions 1 in what areas of scm is bda being applied 2 at what level of analytics is bda used in these scm areas 3 what types of bda models are... Title: big data analytics in supply chain management a stateoftheart literature review Authors: van Nguyen, T.; Zhou, L.; Spiegler, V.; Ieromonachou, P.; Lin, Y. Score: 0.5407 ----------------- Rank #2 Potongan Chunk: of the smaller number of sectorcountryspecific studies absence of sound theoretical baseframeworks more research on routine hr functionsie recruitment and selection and significantly less empirical research we also found minimal research evidence... Title: aiaugmented hrm literature review and a proposed multilevel framework for future research Authors: Prikshat, V.; Islam, M.; Patel, P.; Malik, A.; Budhwar, P.; Gupta, S. Score: 0.4692 ----------------- Rank #3 Potongan Chunk: in an environment where environmental uncertainty is high the research questions driving this study are 1 how does bdmc enable scr in the cpec context 2 what are the mediating roles of... Title: orchestrating digital capabilities for supply chain resilience evidence from chinapakistan economic corridor Authors: Khan, M.I.M.; Sun, Q.; Ahmed, Z.; Zhang, R.; Khosa, M. Score: 0.4667 | H26: 0.417 | I26: 1 | J26: 0 | K26: 0.833 | L26: =IMAGE("https://drive.google.com/uc?export=view&id=1twjvGs92Q9SZf2CFWlAOaWC0jBL954NB")
A27: 26 | B27: LaBSE | C27: 32 | D27: 3 | E27: Which resilience dimensions lack empirical AI-based evaluation? | F27: Direct Summary: The provided documents do not explicitly mention the resilience dimensions that lack empirical AI-based evaluation. However, they do highlight the importance of trustworthy AI in quality optimisation and AI-driven responsible supply chain management. Detailed Synthesis: The study by Büscher et al. (2024) focuses on the trustworthiness of AI applications in quality optimisation, but it does not specifically address resilience dimensions [1]. The review by Angos-Mediavilla et al. (2022) discusses the use of AI in demand forecasting, but it does not provide information on the evaluation of resilience dimensions [2]. The study by Hong and Kim (2025) explores AI-driven responsible supply chain management, but it does not explicitly mention the evaluation of resilience dimensions [3]. Analysis grounded in primary sources: Büscher et al. (2024), Angos-Mediavilla et al. (2022), Hong and Kim (2025). | G27: Rank #1 Potongan Chunk: trustworthiness of ai applications empirical studies substantiating this trust in the context of quality optimisation remain scarce to address this gap this study explores the implementation of trustworthy ai in quality optimisation... Title: trustworthiness of artificial intelligence applications for quality optimisation in metal additive manufacturing Authors: Büscher, J.; Zajackowski, J.; Rademacher, H.-G.; Tillmann, W.; Deuse, J. Score: 0.4696 ----------------- Rank #2 Potongan Chunk: markets consequently classical statistical methods are not always appropriate for accurate and reliable forecasting algorithms of artificial intelligence ai are currently used to improve statistical methods existing literature only gives a very... Title: review and analysis of artificial intelligence methods for demand forecasting in supply chain management Authors: Angos-Mediavilla, M.A.; Dietrich, F.; Palm, D. Score: 0.4550 ----------------- Rank #3 Potongan Chunk: and quantitative performance evaluation the theoretical contribution lies in bridging aidriven esg evaluation frameworks with sustainable tourism and hospitality literature moving beyond static indicatorbased assessments toward a more systematic replicable and predictive... Title: aidriven responsible supply chain management and ethical issue detection in the tourism industry Authors: Hong, M.; Kim, J. Score: 0.4548 | H27: 0.917 | I27: 0.874 | J27: 0 | K27: 0.667 | L27: =IMAGE("https://drive.google.com/uc?export=view&id=1rwSFn2jMq7gy515qsOkA2P3jNxORmBXX")
A28: 27 | B28: LaBSE | C28: 32 | D28: 3 | E28: What limitations exist in current datasets used for AI-driven SCRM? | F28: Direct Summary: The current limitations in datasets used for AI-driven Supply Chain Risk Management (SCRM) include the lack of standardization, limited availability of real-time data, and the inability to capture complex supply chain dynamics. Detailed Synthesis: The lack of standardization in datasets used for AI-driven SCRM is a significant limitation, as it makes it challenging to compare and integrate data from different sources [1]. The limited availability of real-time data is another limitation, as it can lead to delayed decision-making and reduced accuracy in AI-driven SCRM [2]. The inability to capture complex supply chain dynamics is a limitation, as it can lead to oversimplification of supply chain risks and opportunities [3]. Analysis grounded in primary sources: [van Nguyen et al., 2018; Schoenherr, 2023; Brandtner et al., 2021]. | G28: Rank #1 Potongan Chunk: research questions 1 in what areas of scm is bda being applied 2 at what level of analytics is bda used in these scm areas 3 what types of bda models are... Title: big data analytics in supply chain management a stateoftheart literature review Authors: van Nguyen, T.; Zhou, L.; Spiegler, V.; Ieromonachou, P.; Lin, Y. Score: 0.5202 ----------------- Rank #2 Potongan Chunk: while big data analytics bda carries great potential for supply chain management scm actual advanced applications of these approaches are still limited in practice within this context we seek to identify what... Title: supply chain management professionals proficiency in big data analytics antecedents and impact on performance Authors: Schoenherr, T. Score: 0.5081 ----------------- Rank #3 Potongan Chunk: the main aim is to identify i a definition of big data from scm practitioners point of view ii current scm activities and processes where bd is already used in practice iii... Title: applications of big data analytics in supply chain management findings from expert interviews Authors: Brandtner, P.; Udokwu, C.; Darbanian, F.; Falatouri, T. Score: 0.4989 | H28: 0 | I28: 0.91 | J28: 0.833 | K28: 0 | L28: =IMAGE("https://drive.google.com/uc?export=view&id=1U28eMG8BNVltWp7pEiNNWYgTqYsnAR3t")
A29: 28 | B29: LaBSE | C29: 32 | D29: 3 | E29: Which supply chain stages receive little attention in AI models? | F29: Direct Summary: Supply chain stages that receive little attention in AI models include the majority of AI approaches explored in the context of supply chain management, which afford little to no explainability. Detailed Synthesis: According to Kosasih et al. (2024), the majority of AI approaches explored in supply chain management afford little to no explainability, indicating a lack of attention to this aspect in AI models [1]. Heymann et al. (2024) also highlight the lack of clarity regarding the specific points along the power system supply chain where AI applications are most valuable, suggesting that certain stages may be overlooked in AI models [2]. Riahi et al. (2021) conducted a descriptive bibliometric analysis of AI applications in supply chain management and identified several areas that require further research, including the development of more explainable AI models [3]. Analysis grounded in primary sources: Kosasih et al. (2024), Heymann et al. (2024), Riahi et al. (2021). | G29: Rank #1 Potongan Chunk: artificial intelligence ai has emerged as a complementary technology in supply chain research however the majority of ai approaches explored in this context afford little to no explainability which is a significant... Title: a review of explainable artificial intelligence in supply chain management using neurosymbolic approaches Authors: Kosasih, E.E.; Papadakis, E.; Baryannis, G.; Brintrup, A. Score: 0.4858 ----------------- Rank #2 Potongan Chunk: power systems makes ai extremely valuable for the power industry until now there has been a lack of clarity regarding the specific points along the power system supply chain where ai applications... Title: reviewing 40 years of artificial intelligence applied to power systems a taxonomic perspective Authors: Heymann, F.; Quest, H.; Lopez-Garcia, T.; Ballif, C.; Galus, M. Score: 0.4798 ----------------- Rank #3 Potongan Chunk: structural dimensions level of analytics ai algorithms or techniques sector or industry of application and supply chain processes this study is the first attempt to study the ai applications in sc from... Title: artificial intelligence applications in supply chain a descriptive bibliometric analysis and future research directions Authors: Riahi, Y.; Saikouk, T.; Gunasekaran, A.; Badraoui, I. Score: 0.4787 | H29: 1 | I29: 0.997 | J29: 1 | K29: 1 | L29: =IMAGE("https://drive.google.com/uc?export=view&id=1Geia3CnhkOEgr-lUaUtsACw2vChzGniU")
A30: 29 | B30: LaBSE | C30: 32 | D30: 3 | E30: Are human-in-the-loop approaches missing in AI-based resilience studies? | F30: Direct Summary: Human-in-the-loop approaches are indeed missing in AI-based resilience studies, as the existing literature lacks real-world implementation studies and insufficient discussion of the impact of AI on the human side of SCM, as found in the study by Gayialis et al. (2024). This gap is also highlighted by Kosasih et al. (2024) in their review of explainable AI in SCM, where they note that most AI approaches explored in this context afford little to no explainability, which is a significant issue. Detailed Synthesis: The study by Gayialis et al. (2024) emphasizes the need for more real-world implementation studies in AI-based SCM, which would likely involve human-in-the-loop approaches to ensure the effectiveness and resilience of AI systems [1]. Kosasih et al. (2024) highlight the lack of explainability in most AI approaches explored in SCM, which is a critical issue for human-in-the-loop approaches that require transparency and interpretability [2]. Analysis grounded in primary sources: Gayialis et al. (2024), Kosasih et al. (2024). | G30: Rank #1 Potongan Chunk: the existing literature for example the lack of realworld implementation studies and insufficient discussion of the impact of ai on the human side of scm based on the findings of this study... Title: exploring the intersection of artificial intelligence and machine learning in supply chain management a structured literature review Authors: Gayialis, S.P.; Kechagias, E.P.; Panayiotou, N.A.; Papadopoulos, G.A.; Papaioannou, A. Score: 0.4955 ----------------- Rank #2 Potongan Chunk: artificial intelligence ai has emerged as a complementary technology in supply chain research however the majority of ai approaches explored in this context afford little to no explainability which is a significant... Title: a review of explainable artificial intelligence in supply chain management using neurosymbolic approaches Authors: Kosasih, E.E.; Papadakis, E.; Baryannis, G.; Brintrup, A. Score: 0.4842 ----------------- Rank #3 Potongan Chunk: this research presents a systematic literature review of using artificial intelligence ai in the supply chain sc we examine the works done so far in relation to ai research which still needs... Title: application of artificial intelligence in the supply chain a systematic literature review Authors: Kriouich, M.; Sarir, H.; Mahboub, O. Score: 0.4784 | H30: 0.615 | I30: 0.788 | J30: 1 | K30: 1 | L30: =IMAGE("https://drive.google.com/uc?export=view&id=19uHDXwCi8xNh2zM_zNPikxrJYkrzq3gd")
A31: 30 | B31: LaBSE | C31: 32 | D31: 3 | E31: What gaps exist in explainability for AI-driven risk prediction models? | F31: Direct Summary: The provided context data does not explicitly mention gaps in explainability for AI-driven risk prediction models. However, it highlights challenges in implementing AI technologies, particularly in terms of applicability and scalability, as well as the need for future research in this area. Detailed Synthesis: Doc [1] mentions that a major challenge remains in the applicability and scalability of AI models to practical settings, which may be related to explainability gaps [1]. Doc [3] describes missing aspects in current research, which could include explainability for AI-driven risk prediction models, and highlights promising avenues for future research [2]. However, the context data does not provide specific information on gaps in explainability for AI-driven risk prediction models. Analysis grounded in primary sources: Focker, M. et al. (2025), Deiva Ganesh, A. et al. (2022). | G31: Rank #1 Potongan Chunk: as imaging detection or electronic noses possible a major challenge remains in the applicability and scalability of ai models to practical settings the authors 2025... Title: the use of artificial intelligence to improve mycotoxin management a review Authors: Focker, M.; Liu, C.; Wang, X.; van der Fels-Klerx, H.J. Score: 0.5245 ----------------- Rank #2 Potongan Chunk: in ai for cybersecurity applications key methodologies include aipowered intrusion detection threat analysis leveraging machine learning algorithms predictive maintenance strategies and enhanced authentication protocols results underscore the effectiveness of ai technologies in... Title: cybersecurity in electric and flying vehicles threats challenges ai solutions future directions Authors: Alqahtani, H.; Kumar, G. Score: 0.4939 ----------------- Rank #3 Potongan Chunk: missing aspects in current research challenges on implementing ai technologies and describes promising avenues for the future 2022 elsevier ltd... Title: future of artificial intelligence and its influence on supply chain risk management a systematic review Authors: Deiva Ganesh, A.; Kalpana, P. Score: 0.4917 | H31: 0.636 | I31: 0 | J31: 0 | K31: 0.833 | L31: =IMAGE("https://drive.google.com/uc?export=view&id=16qR0NBfmgUhRWFcgED_caeRK0QVq4OCo")
A32: 31 | B32: LaBSE | C32: 32 | D32: 3 | E32: Which risks are not captured by current AI frameworks? | F32: Direct Summary: Current AI frameworks may not capture risks associated with the use of widely available AI models as carriers for malicious payloads, as well as the limitations of traditional forecasting methods in ecommerce supply chains and the reactive nature of current safety management systems in circular supply chain safety management. Detailed Synthesis: The use of industrial large models as carriers for malicious payloads poses a sophisticated security threat that may not be captured by current AI frameworks, as discussed in [1]. Traditional forecasting methods often fail to provide accurate insights and are time-consuming, which can be overcome using AI algorithms, but may not address the limitations of current AI frameworks, as mentioned in [2]. Current safety management systems in circular supply chain safety management are often reactive and limited in scope, failing to address safety concerns in interorganizational complexities, which may not be captured by current AI frameworks, as discussed in [3]. Analysis grounded in primary sources: [Yuan et al., 2025; Sayyad et al., 2024; Chen et al., 2025]. | G32: Rank #1 Potongan Chunk: nature of attack strategies particularly the use of widely available ai models as carriers for malicious payloads poses increasingly sophisticated security threats most existing embedding techniques struggle in ilm application scenarios where... Title: industrial large models as carriers for malicious payloads a fast and robust approach Authors: Yuan, Y.; Deng, R.; Lu, Z.; Hung, P.C.K. Score: 0.4895 ----------------- Rank #2 Potongan Chunk: to explore future possibilities by adjusting key relational parameters however traditional forecasting methods often fail to provide accurate insights and are timeconsuming these limitations can be overcome using artificial intelligence ai algorithms... Title: optimizing ecommerce supply chains with categorical boosting a predictive modeling framework Authors: Sayyad, J.K.; Attarde, K.; Saadouli, N. Score: 0.4699 ----------------- Rank #3 Potongan Chunk: present significant barriers current safety management systems in cscs are often reactive and limited in scope failing to address safety concerns in interorganizational complexities therefore we explore how generative artificial intelligence gen... Title: integrating generative ai into circular supplychain safety management a forwardlooking perspective Authors: Chen, Z.; Sarkis, J.; Yıldızbaşı, A. Score: 0.4691 | H32: 0.909 | I32: 0.61 | J32: 0.833 | K32: 0.8 | L32: =IMAGE("https://drive.google.com/uc?export=view&id=1w58_q53naUe5yDOpHUZE0eZCypIjtstN")
A33: 32 | B33: LaBSE | C33: 32 | D33: 3 | E33: What industries are rarely studied in AI-based supply chain resilience? | F33: Direct Summary: The provided documents do not explicitly mention industries that are rarely studied in AI-based supply chain resilience. However, based on the context, it can be inferred that certain industries might be understudied due to the lack of research in AI applications in supply chain management. Detailed Synthesis: According to Doc [2], very few studies have addressed the applications of artificial intelligence in supply chain management, suggesting that there might be a gap in research on AI-based supply chain resilience in certain industries. Doc [3] highlights the need for explainable artificial intelligence in supply chain management, which implies that there might be a lack of research on AI-based supply chain resilience in industries that require high explainability. Analysis grounded in primary sources: [Yue, X.; Kang, M.; Zhang, Y., 2025; Riahi, Y.; Saikouk, T.; Gunasekaran, A.; Badraoui, I., 2021; Kosasih, E.E.; Papadakis, E.; Baryannis, G.; Brintrup, A., 2024]. | G33: Rank #1 Potongan Chunk: purpose manufacturing firms must strengthen their supply chain resilience to survive in turbulent business environments this study explores how artificial intelligence ai can be leveraged to enhance supply chain resilience designmethodologyapproach drawing... Title: the impact of artificial intelligence usage on supply chain resilience in manufacturing firms a moderated mediation model Authors: Yue, X.; Kang, M.; Zhang, Y. Score: 0.5565 ----------------- Rank #2 Potongan Chunk: a technology that can cope with their increasing complexity in recent years several functional supply chain applications based on artificial intelligence ai have emerged yet very few studies have addressed the applications... Title: artificial intelligence applications in supply chain a descriptive bibliometric analysis and future research directions Authors: Riahi, Y.; Saikouk, T.; Gunasekaran, A.; Badraoui, I. Score: 0.5474 ----------------- Rank #3 Potongan Chunk: artificial intelligence ai has emerged as a complementary technology in supply chain research however the majority of ai approaches explored in this context afford little to no explainability which is a significant... Title: a review of explainable artificial intelligence in supply chain management using neurosymbolic approaches Authors: Kosasih, E.E.; Papadakis, E.; Baryannis, G.; Brintrup, A. Score: 0.5312 | H33: 0.875 | I33: 1 | J33: 0.583 | K33: 0.4 | L33: =IMAGE("https://drive.google.com/uc?export=view&id=1sej2nsS3g8Z8JVXnU2hEDexNryCnV1y9")
A34: 33 | B34: LaBSE | C34: 32 | D34: 3 | E34: Are real-time adaptation mechanisms sufficiently addressed? | F34: Direct Summary: Real-time adaptation mechanisms are not sufficiently addressed in the provided context. The documents focus on various aspects of supply chain security, quantum neural networks, and AI adoption, but do not explicitly discuss real-time adaptation mechanisms. Detailed Synthesis: Doc [1] highlights the need for a proper reference model for supply chain security implementation, but does not address real-time adaptation mechanisms [1]. Doc [2] discusses the potential of hybrid classical-quantum algorithms for supply chain logistics, but does not specifically mention real-time adaptation [2]. Doc [3] identifies challenges in AI adoption, including lack of standardization and contextual awareness, which may impact real-time adaptation, but does not directly address the issue [3]. Analysis grounded in primary sources: Hassija et al. (2021), Correll et al. (2023), Mishra et al. (2023). | G34: Rank #1 Potongan Chunk: however a proper reference model for their implementation in complex supply chains is still missing 2014 ieee... Title: a survey on supply chain security application areas security threats and solution architectures Authors: Hassija, V.; Chamola, V.; Gupta, V.; Jain, S.; Guizani, N. Score: 0.4253 ----------------- Rank #2 Potongan Chunk: problem instances of a size suitable for practical applications are not likely to be addressed during the noisy intermediatescale quantum nisq period with almost pure quantum algorithms hybrid classicalquantum algorithms have potential... Title: quantum neural networks for a supply chain logistics application Authors: Correll, R.; Weinberg, S.J.; Sanches, F.; Ide, T.; Suzuki, T. Score: 0.4244 ----------------- Rank #3 Potongan Chunk: modelling ism micmac and stepwiseassessment and ratioanalysis swara response time and accuracy level lack of standardization availability of support for big data big data support implementation costs flexibility lack of contextual awareness... Title: challenges facing artificial intelligence adoption during covid19 pandemic an investigation into the agriculture and agrifood supply chain in india Authors: Mishra, D.; Muduli, K.; Raut, R.D.; Narkhede, B.E.; Shee, H.K.; Jana, S.K. Score: 0.4218 | H34: 1 | I34: 0.781 | J34: 0 | K34: 0 | L34: =IMAGE("https://drive.google.com/uc?export=view&id=1_7Fkg3Ap8HPDFWWp45NdGVyyl7LRjthD")
A35: 34 | B35: LaBSE | C35: 32 | D35: 3 | E35: What evaluation metrics are missing in resilience-focused AI research? | F35: Direct Summary: Evaluation metrics are missing in resilience-focused AI research, particularly in the context of quality optimisation in metal additive manufacturing. The current literature lacks a comprehensive study that evaluates the enablers impacting the implementation of AI in production systems, which is crucial for assessing the resilience of AI applications. This gap is evident in the scarcity of empirical studies substantiating trust in AI applications for quality optimisation. Detailed Synthesis: The current literature lacks a comprehensive study that evaluates the enablers impacting the implementation of AI in production systems [1]. This is crucial for assessing the resilience of AI applications, particularly in the context of quality optimisation in metal additive manufacturing [2]. Empirical studies substantiating trust in AI applications for quality optimisation remain scarce, which is a significant gap in the current research [3]. This gap is evident in the lack of evaluation metrics for assessing the resilience of AI applications in production systems [4]. Analysis grounded in primary sources: [Büscher et al., 2024; Merhi & Harfouche, 2024; Bag et al., 2021]. | G35: Rank #1 Potongan Chunk: trustworthiness of ai applications empirical studies substantiating this trust in the context of quality optimisation remain scarce to address this gap this study explores the implementation of trustworthy ai in quality optimisation... Title: trustworthiness of artificial intelligence applications for quality optimisation in metal additive manufacturing Authors: Büscher, J.; Zajackowski, J.; Rademacher, H.-G.; Tillmann, W.; Deuse, J. Score: 0.5130 ----------------- Rank #2 Potongan Chunk: extant literature lacks a comprehensive study that evaluates the enablers impacting the implementation of ai in production systems this research fills this gap by identifying defining and evaluating the critical enablers influencing... Title: enablers of artificial intelligence adoption and implementation in production systems Authors: Merhi, M.I.; Harfouche, A. Score: 0.4672 ----------------- Rank #3 Potongan Chunk: performance but there is limited research concerning the reasons for which firms engaging in manufacturing activities adopt big data analyticspowered artificial intelligence to address this gap our study employs institutional theory and... Title: role of institutional pressures and resources in the adoption of big data analytics powered artificial intelligence sustainable manufacturing practices and circular economy capabilities Authors: Bag, S.; Pretorius, J.H.C.; Gupta, S.; Dwivedi, Y.K. Score: 0.4616 | H35: 0.5 | I35: 0.687 | J35: 1 | K35: 1 | L35: =IMAGE("https://drive.google.com/uc?export=view&id=1GYZS0Vk8guz6U0Xq94z-QejuTsPhPZKD")
A36: 35 | B36: LaBSE | C36: 32 | D36: 3 | E36: Which AI models fail to generalize across supply chain contexts? | F36: Direct Summary: Traditional inventory classification models, such as those mentioned in Doc [3], fail to generalize across supply chain contexts due to their inability to meet the complexity of various inventory types. Detailed Synthesis: Traditional inventory classification models, as discussed in Doc [3] [1], divide SKUs into broad categories, which may not be sufficient to capture the nuances of different supply chain contexts. These models, as highlighted in Doc [3] [1], are not able to meet the complexity of various inventory types, leading to a lack of generalizability across supply chain contexts. Analysis grounded in primary sources: [Hassija et al., 2021; Jain et al., 2015; Wang et al., 2018]. | G36: Rank #1 Potongan Chunk: however a proper reference model for their implementation in complex supply chains is still missing 2014 ieee... Title: a survey on supply chain security application areas security threats and solution architectures Authors: Hassija, V.; Chamola, V.; Gupta, V.; Jain, S.; Guizani, N. Score: 0.5673 ----------------- Rank #2 Potongan Chunk: competitive models offer superiority in maximizing only a buyers profit and do not satisfy all members in a supply chain however coordinative models give benefit to the whole supply chain research has... Title: a chaotic bee colony approach for supplier selectionorder allocation with different discounting policies in a coopetitive multiechelon supply chain Authors: Jain, V.; Kundu, A.; Chan, F.T.S.; Patel, M. Score: 0.5288 ----------------- Rank #3 Potongan Chunk: traditional inventory classification models divide skus into a few broad categories and help companies to sort inventories using a simple and intuitive way however these classification approaches are not able to meet... Title: novel sku classification approach for autonomous inventory planning Authors: Wang, F.; Ng, H.Y.; Ng, T.E. Score: 0.5111 | H36: 0.167 | I36: 0.633 | J36: 0.333 | K36: 0.75 | L36: =IMAGE("https://drive.google.com/uc?export=view&id=1g9J73cfCWCbyNuXCrjNt522MTfFsAYX8")
A37: 36 | B37: LaBSE | C37: 32 | D37: 3 | E37: Are ethical and governance issues underexplored in AI-based SCRM? | F37: Direct Summary: Yes, ethical and governance issues are underexplored in AI-based Supply Chain Risk Management (SCRM). This is evident from the lack of robust frameworks for organizational decision-making systems, as highlighted in the literature. The use of AI in SCRM raises concerns about algorithmic bias, lack of transparency, and accountability gaps. Detailed Synthesis: The use of AI in SCRM has emerged as a critical research area, but it is still underexplored in terms of ethical and governance issues [1]. Organizations need robust frameworks for decision-making systems to address challenges like algorithmic bias, lack of transparency, and accountability gaps [1]. The application of AI in SCRM raises concerns about medical liability, diagnostic accuracy, and the need for systematic reviews to address these issues [2]. The evolution of AI research in technological forecasting and social change highlights the need for interdisciplinary approaches to address the complexities of AI-based SCRM [3]. Analysis grounded in primary sources: [Besri, 2025; Cestonaro et al., 2023; Dwivedi et al., 2023]. | G37: Rank #1 Potongan Chunk: ethical governance of artificial intelligence ai in organizational systems has emerged as a critical research area with challenges like algorithmic bias lack of transparency and accountability gaps organizations need robust frameworks for... Title: fuzzy logic for ethical ai governance a framework for organizational decisionmaking systems and integration with intuitionist fuzzy methods for digital transformation Authors: Besri, Z. Score: 0.5085 ----------------- Rank #2 Potongan Chunk: diagnostic accuracy the use of ai raises ethical and legal concerns to which there is still no unanimous response a systematic literature review on medical professional liability related to the use of... Title: defining medical liability when artificial intelligence is applied on diagnostic algorithms a systematic review Authors: Cestonaro, C.; Delicati, A.; Marcante, B.; Caenazzo, L.; Tozzo, P. Score: 0.4849 ----------------- Rank #3 Potongan Chunk: visualize the latent topics from the ai research literature further the disciplinary patterns in the intellectual structure of ai research are examined with the additional objective of assessing the disciplinary impact of... Title: evolution of artificial intelligence research in technological forecasting and social change research topics trends and future directions Authors: Dwivedi, Y.K.; Sharma, A.; Rana, N.P.; Giannakis, M.; Goel, P.; Dutot, V. Score: 0.4790 | H37: 0.421 | I37: 0.888 | J37: 1 | K37: 0.375 | L37: =IMAGE("https://drive.google.com/uc?export=view&id=1hTT1B6gIhiEZlrQEkr0HlX3oyXdMTj1B")
A38: 37 | B38: LaBSE | C38: 32 | D38: 3 | E38: What gaps exist between theoretical models and real-world deployment? | F38: Direct Summary: Theoretical models often have gaps with real-world deployment, including the potential to bridge the gap between theoretical models and real-world applications, as well as the gap between complex models and real-world decision-making. Detailed Synthesis: The gap between theoretical models and real-world deployment can be attributed to the potential to bridge the gap between theoretical models and real-world applications, as mentioned in [1] by Cicek et al. (2025). Additionally, complex models often have a gap between their predictions and real-world decision-making, as highlighted in [3] by Rahmat et al. (2025). Analysis grounded in primary sources: [Cicek, D.; Simsek, M.; Kantarci, B., 2025], [Rahmat, F.; Zulkafli, Z.; Ishak, A.J.; Abdul Rahman, R.Z.; Tahir, W.; Ab Rahman, J.; Jayaramu, V.; De Stercke, S.; Ibrahim, S.; Ismail, M., 2025]. | G38: Rank #1 Potongan Chunk: potential to bridge the gap between theoretical models and realworld applications 2025 by the authors... Title: machine learningdriven truckdrone collaborative delivery for time and energyefficient lastmile deliveries Authors: Cicek, D.; Simsek, M.; Kantarci, B. Score: 0.5706 ----------------- Rank #2 Potongan Chunk: differences between counterfeit and authentic ic samples 2022 ieee... Title: machine learning assisted counterfeit ic detection through nondestructive infrared ir spectroscopy material characterization Authors: Xi, C.; Jessurun, N.; True, J.; Khan, A.A.; Tehranipoor, M.M.; Asadizanjani, N. Score: 0.4724 ----------------- Rank #3 Potongan Chunk: the gap between complex models and realworld decisionmaking 2025 elsevier ltd... Title: interpretable spatiotemporal prediction using deep neural network local interpretable modelagnostic explanations a case study on leptospirosis outbreaks in malaysia Authors: Rahmat, F.; Zulkafli, Z.; Ishak, A.J.; Abdul Rahman, R.Z.; Tahir, W.; Ab Rahman, J.; Jayaramu, V.; De Stercke, S.; Ibrahim, S.; Ismail, M. Score: 0.4714 | H38: 0.556 | I38: 0.993 | J38: 1 | K38: 1 | L38: =IMAGE("https://drive.google.com/uc?export=view&id=1fc26K7JoNzJqOhnJvK3R3069HDiuUNg8")
A39: 38 | B39: LaBSE | C39: 32 | D39: 3 | E39: Which resilience strategies lack AI-based optimization? | F39: Direct Summary: Traditional forecasting methods lack AI-based optimization, which can be overcome using artificial intelligence algorithms. Detailed Synthesis: Classical statistical methods are not always appropriate for accurate and reliable forecasting, as mentioned in [2]. Traditional forecasting methods often fail to provide accurate insights and are time-consuming, as stated in [3]. Analysis grounded in primary sources: [Alqahtani, H.; Kumar, G., 2024; Angos-Mediavilla, M.A.; Dietrich, F.; Palm, D., 2022; Sayyad, J.K.; Attarde, K.; Saadouli, N., 2024]. | G39: Rank #1 Potongan Chunk: in ai for cybersecurity applications key methodologies include aipowered intrusion detection threat analysis leveraging machine learning algorithms predictive maintenance strategies and enhanced authentication protocols results underscore the effectiveness of ai technologies in... Title: cybersecurity in electric and flying vehicles threats challenges ai solutions future directions Authors: Alqahtani, H.; Kumar, G. Score: 0.4858 ----------------- Rank #2 Potongan Chunk: markets consequently classical statistical methods are not always appropriate for accurate and reliable forecasting algorithms of artificial intelligence ai are currently used to improve statistical methods existing literature only gives a very... Title: review and analysis of artificial intelligence methods for demand forecasting in supply chain management Authors: Angos-Mediavilla, M.A.; Dietrich, F.; Palm, D. Score: 0.4770 ----------------- Rank #3 Potongan Chunk: to explore future possibilities by adjusting key relational parameters however traditional forecasting methods often fail to provide accurate insights and are timeconsuming these limitations can be overcome using artificial intelligence ai algorithms... Title: optimizing ecommerce supply chains with categorical boosting a predictive modeling framework Authors: Sayyad, J.K.; Attarde, K.; Saadouli, N. Score: 0.4451 | H39: 1 | I39: 0.529 | J39: 0.583 | K39: 1 | L39: =IMAGE("https://drive.google.com/uc?export=view&id=1WDloIopKysj6AnT744_jMJ0rcjeoOC8m")
A40: 39 | B40: LaBSE | C40: 32 | D40: 3 | E40: Are multimodal data sources underutilized? | F40: Direct Summary: Yes, multimodal data sources are underutilized, as stated in Doc [2] that highlights a big level forward in utilizing diverse data sources to enhance model effectiveness and decision-making. Detailed Synthesis: According to Doc [2], transforming AI-enabled information systems (ISS) with synthesized big data analytics and multimodal data fusion is a significant step forward in utilizing diverse data sources, indicating that multimodal data sources are underutilized. Doc [1] also mentions that various data resources have not yet been fully harnessed, including unstructured data, which suggests that multimodal data sources are underutilized. Analysis grounded in primary sources: [Nguyen et al., 2022; Li et al., 2025]. | G40: Rank #1 Potongan Chunk: from machine learning algorithms to address drug shortages and inventories optimisation the various data resources have not yet been fully harnessed unstructured data have barely been used and combined with other types... Title: data analytics in pharmaceutical supply chains state of the art opportunities and challenges Authors: Nguyen, A.; Lamouri, S.; Pellerin, R.; Tamayo, S.; Lekens, B. Score: 0.4687 ----------------- Rank #2 Potongan Chunk: transforming aibased information systems iss with synthesized big data analytics and multimodal data fusion highlights a big level forward in utilizing diverse data sources to enhance model effectiveness and decisionmaking the integration... Title: revolutionizing aienabled information systems using integrated big data analytics and multimodal data fusion Authors: Li, F.; Xu, J. Score: 0.4609 ----------------- Rank #3 Potongan Chunk: internet of things iotgenerated data are characterized by its continuous generation large amount and unstructured format the existing relational database technologies are inadequate to handle such iotgenerated data due to the limited... Title: mongodbbased repository design for iotgenerated rfidsensor big data Authors: Kang, Y.-S.; Park, I.-H.; Rhee, J.; Lee, Y.-H. Score: 0.4550 | H40: 0.857 | I40: 0.914 | J40: 1 | K40: 0.75 | L40: =IMAGE("https://drive.google.com/uc?export=view&id=1XoAzIZW89y4y49fQNjcBSdn81B0M2Yix")
A41: 40 | B41: LaBSE | C41: 32 | D41: 3 | E41: What future research opportunities emerge from these gaps? | F41: Direct Summary: Future research opportunities emerge from the gaps in software security analysis, sustainable industry development, and supply chain management. These opportunities include promoting a circular economy, sustainable development, and the implementation of digital technologies within supply chain management. Detailed Synthesis: One opportunity is to promote a circular economy, as suggested by the authors of Doc [2] [1]. This involves reducing waste and the consumption of resources, and promoting the reuse and recycling of materials. Another opportunity is to implement digital technologies within supply chain management, as proposed by the authors of Doc [3] [2]. This could include the use of artificial intelligence, blockchain, and the Internet of Things (IoT) to improve supply chain efficiency and sustainability. Additionally, the authors of Doc [1] [3] suggest that future research should focus on software security analysis for the systems of the future. This could involve developing new methods and tools for analyzing and mitigating software security risks. Analysis grounded in primary sources: [Böhme et al., 2025; Wang et al., 2025; Varriale et al., 2023]. | G41: Rank #1 Potongan Chunk: with unprecedented research challenges but also with exciting new opportunities in this roadmap article we outline our vision of software security analysis for the systems of the future given the recent advances... Title: software security analysis in 2030 and beyond a research roadmap Authors: Böhme, M.; Bodden, E.; Bultan, T.; Cadar, C.; Liu, Y.; Scanniello, G. Score: 0.5188 ----------------- Rank #2 Potongan Chunk: recent bursting keyword the insights from this review identify research gaps and challenges based on which the proposing directions for future research are suggested including promoting a circular economy the sustainable development... Title: the role of government procurement in sustainable industry developmentthe trends and research agenda Authors: Wang, N.; Cui, N.; Hao, J.; Chai, Y. Score: 0.5167 ----------------- Rank #3 Potongan Chunk: practices for scm it highlights potential research gaps by proposing scenarios of future research developments for the latter the article aims to identify opportunities for the implementation of digital technologies within own... Title: industry 50 and triple bottom line approach in supply chain management the stateoftheart Authors: Varriale, V.; Cammarano, A.; Michelino, F.; Caputo, M. Score: 0.5072 | H41: 0.381 | I41: 0.617 | J41: 1 | K41: 0.333 | L41: =IMAGE("https://drive.google.com/uc?export=view&id=1mubrba--d0x7zjdfChjJQBSlxlI1xslI")
A42: 41 | B42: LaBSE | C42: 32 | D42: 3 | E42: How do machine learning and deep learning approaches differ in SCRM applications? | F42: Direct Summary: Machine learning and deep learning approaches differ in SCRM applications primarily in terms of complexity, scalability, and adaptability. Machine learning focuses on learning from data to make predictions or decisions, whereas deep learning involves the use of neural networks to analyze complex patterns in data. This difference in approach affects the type of problems that can be solved and the level of accuracy achieved. Detailed Synthesis: Machine learning approaches in SCRM applications typically involve supervised or unsupervised learning methods, such as regression, classification, or clustering, to analyze historical data and make predictions about future events [1]. Deep learning approaches, on the other hand, involve the use of neural networks to analyze complex patterns in data, such as images or sensor readings, to make predictions or decisions [2]. The choice between machine learning and deep learning approaches depends on the specific problem being addressed and the type of data available. Machine learning is often more suitable for problems with well-defined boundaries and clear patterns, while deep learning is better suited for problems with complex, high-dimensional data [3]. Analysis grounded in primary sources: [Osborne, P.; Singh, K.; Taylor, M.E., 2022; Naeem, M.Y.; Selamoglu, B.; Danebekovna, K.G.; Selamoğlu, M.; Selamoglu, Z., 2025; Lüke, K.-H.; Eichler, G.; Royer, D., 2025]. | G42: Rank #1 Potongan Chunk: offer but also the challenges and risks associated with applying it in practice specifically these sections illustrate the differences between reinforcement learning and other machine learning approaches as well as how wellknown... Title: applying reinforcement learning on realworld data with practical examples in python Authors: Osborne, P.; Singh, K.; Taylor, M.E. Score: 0.5031 ----------------- Rank #2 Potongan Chunk: artificial intelligence ai refers to a variety of computing approaches including machine learning ml deep learning dl natural language processing nlp and computer vision ai has transformed healthcare with applications ranging from... Title: the use and importance of artificial intelligence in vaccine research development and production Authors: Naeem, M.Y.; Selamoglu, B.; Danebekovna, K.G.; Selamoğlu, M.; Selamoglu, Z. Score: 0.4849 ----------------- Rank #3 Potongan Chunk: tasks that traditionally require human intelligence such as machine learning deep learning and decisionmaking ai applications span numerous industries with supply chain management scm being a particularly relevant domain ai technologies optimize... Title: artificial intelligence application scenarios considering objective and subjective influence factors for industrial solutions in supply chain management Authors: Lüke, K.-H.; Eichler, G.; Royer, D. Score: 0.4828 | H42: 0.308 | I42: 0.935 | J42: 0.833 | K42: 0 | L42: =IMAGE("https://drive.google.com/uc?export=view&id=1W4xIx8yezp7_U-WJLwsUbgFbErv_kfhQ")
A43: 42 | B43: LaBSE | C43: 32 | D43: 3 | E43: Compare AI models used for disruption prediction versus resilience optimization. | F43: Direct Summary: AI models used for disruption prediction and resilience optimization have different approaches and strengths. Disruption prediction models, such as those discussed in Doc [2], focus on forecasting potential disruptions using statistical machine learning and hybrid models. In contrast, resilience optimization models, such as those discussed in Doc [3], aim to reduce peak cycle times and improve warehouse efficiency through real-time decision-making. Detailed Synthesis: Disruption prediction models, such as those in Doc [2], use statistical machine learning and hybrid models to forecast potential disruptions. These models are effective in identifying potential risks but may not provide actionable insights for resilience optimization [2]. Resilience optimization models, such as those in Doc [3], focus on reducing peak cycle times and improving warehouse efficiency through real-time decision-making. These models leverage machine learning-based forecasting and alerting systems to optimize warehouse operations [3]. A comparison of disruption prediction and resilience optimization models is not explicitly discussed in the provided documents. However, it is clear that these models have different objectives and approaches, and a more comprehensive analysis would be necessary to determine their relative effectiveness [1, 2, 3]. Analysis grounded in primary sources: [Xiao, P.; Tan, L.; Salleh, M.I., 2025; Fu, L., 2025; Aloini, D.; Benevento, E.; Dulmin, R.; Guerrazzi, E.; Mininno, V., 2025]. | G43: Rank #1 Potongan Chunk: the prediction model which were used to calculate and compare the strengths and weaknesses of credit risk assessment models as well as their predictive capabilities the empirical result indicate that the adaboost... Title: research on smes credit risk assessment based on blockchaindriven supply chain finance Authors: Xiao, P.; Tan, L.; Salleh, M.I. Score: 0.5416 ----------------- Rank #2 Potongan Chunk: of forecasting models to predict global supply chain disruptions and their efficacy and limitations a comparison of statistical machine learning and hybrid models is performed and the best methods for predicting disruptions... Title: forecasting models for predicting global supply chain disruptions in trade economics Authors: Fu, L. Score: 0.5205 ----------------- Rank #3 Potongan Chunk: were tested to find the best forecasting model leveraging a set of predictors tailored to the characteristics of the warehouse simulation with real data demonstrates significant reductions of peak cycle times and... Title: unlocking realtime decisionmaking in warehouses a machine learningbased forecasting and alerting system for cycle time prediction Authors: Aloini, D.; Benevento, E.; Dulmin, R.; Guerrazzi, E.; Mininno, V. Score: 0.5048 | H43: 0.733 | I43: 0.724 | J43: 0.5 | K43: 0 | L43: =IMAGE("https://drive.google.com/uc?export=view&id=13KAnbvmNygz_-roDb2gZhhkePpSJEFVw")
A44: 43 | B44: LaBSE | C44: 32 | D44: 3 | E44: How do rule-based systems compare with data-driven AI in risk management? | F44: Direct Summary: Unfortunately, the provided context does not contain information directly comparing rule-based systems with data-driven AI in risk management. However, it does mention the application of artificial intelligence (AI) in risk management practices, improving security assessments, risk prediction, security control implementation, and continuous monitoring. Detailed Synthesis: Doc [3] discusses the application of AI in risk management practices, leveraging AI algorithms to analyze large data volumes from various sources, improving security assessments, risk prediction, security control implementation, and continuous monitoring. However, the provided context does not contain information on the comparison between rule-based systems and data-driven AI in risk management, making it difficult to provide a direct comparison. Analysis grounded in primary sources: [Kioskli, K.; Grigoriou, E.; Islam, S.; Yiorkas, A.M.; Christofi, L.; Mouratidis, H., 2025], [Cohen, M.A., 2022]. | G44: Rank #1 Potongan Chunk: ip management strategies furthermore we explore how emerging technologies like blockchain and ai can address persistent information security challenges by synthesizing theoretical perspectives with practical recommendations this research not only advances the... Title: building better defence overcoming challenges in product development through supplier integration in india Authors: Singh, A.; Kaushik, N.; Pandey, P.K. Score: 0.4901 ----------------- Rank #2 Potongan Chunk: concludes with a illustration of how such analytics tools based on the application of machine learning to big data can support a data driven exploration of policy alternatives in the context of... Title: application of analytics to achieve supply chain resilience Authors: Cohen, M.A. Score: 0.4694 ----------------- Rank #3 Potongan Chunk: of healthcare systems the framework leverages artificial intelligence ai in risk management practices improving security assessments risk prediction security control implementation and continuous monitoring ai algorithms analyze large data volumes from various... Title: a risk and conformity assessment framework to ensure security and resilience of healthcare systems and medical supply chain Authors: Kioskli, K.; Grigoriou, E.; Islam, S.; Yiorkas, A.M.; Christofi, L.; Mouratidis, H. Score: 0.4673 | H44: 0.875 | I44: 0 | J44: 0 | K44: 0.2 | L44: =IMAGE("https://drive.google.com/uc?export=view&id=1p0umA6oALCJiPY5_Irhm8Vuc9Jwd-tGq")
A45: 44 | B45: LaBSE | C45: 32 | D45: 3 | E45: What differences exist between supervised and unsupervised models in SCRM? | F45: Direct Summary: Unfortunately, the provided context data does not contain information about the differences between supervised and unsupervised models in Supply Chain Risk Management (SCRM). The documents focus on predictive analysis of microbial water quality, big data analytics in supply chain management, and economic strategic plans with SCRM, but do not address the specific question of supervised vs. unsupervised models in SCRM. Detailed Synthesis: Document [1] discusses the performance of various ANN model configurations and regression SVM kernel functions, but does not mention supervised or unsupervised models. Document [2] provides a literature review on big data analytics in supply chain management, but does not address the differences between supervised and unsupervised models in SCRM. Document [3] focuses on economic strategic plans with SCRM, but does not discuss the specific topic of supervised vs. unsupervised models. Analysis grounded in primary sources: [Mohammed, H.; Longva, A.; Seidu, R., 2018], [van Nguyen, T.; Zhou, L.; Spiegler, V.; Ieromonachou, P.; Lin, Y., 2018], [Aljabhan, B., 2023]. | G45: Rank #1 Potongan Chunk: mse values among the various ann model configurations no distinct disparity was found in the performances of the various solvers of regression svm in the estimations for the regression svm kernel functions... Title: predictive analysis of microbial water quality using machinelearning algorithms mikrobinio vandens kokybs prognozin analiz naudojant algoritmus Authors: Mohammed, H.; Longva, A.; Seidu, R. Score: 0.4766 ----------------- Rank #2 Potongan Chunk: research questions 1 in what areas of scm is bda being applied 2 at what level of analytics is bda used in these scm areas 3 what types of bda models are... Title: big data analytics in supply chain management a stateoftheart literature review Authors: van Nguyen, T.; Zhou, L.; Spiegler, V.; Ieromonachou, P.; Lin, Y. Score: 0.4579 ----------------- Rank #3 Potongan Chunk: why organizations use the scrm model risk identification and assessment risk analysis environmental monitoring and risk management the organizations scrm is more complicated and constantly changing and numerous teams including those for... Title: economic strategic plans with supply chain risk management scrm for organizational growth and development Authors: Aljabhan, B. Score: 0.4268 | H45: 0.667 | I45: 0 | J45: 0 | K45: 0.333 | L45: =IMAGE("https://drive.google.com/uc?export=view&id=1mqSHgo2h4GpJNcjeUwDWg6YbRXGip_bh")
A46: 45 | B46: LaBSE | C46: 32 | D46: 3 | E46: How do predictive and prescriptive AI models differ in objectives? | F46: Direct Summary: Predictive and prescriptive AI models differ in objectives, with predictive models focusing on forecasting future events or outcomes, whereas prescriptive models aim to provide recommendations or actions to achieve a desired outcome. Detailed Synthesis: Predictive AI models, such as those discussed in Doc [1] [1], focus on forecasting future events or outcomes based on historical data and patterns. This is often achieved through machine learning algorithms that identify relationships between variables and make predictions about future behavior. Prescriptive AI models, on the other hand, aim to provide recommendations or actions to achieve a desired outcome. As noted in Doc [2] [2], prescriptive models can be used for theory building and testing in operations management, where the goal is to identify the best course of action to achieve a specific objective. Analysis grounded in primary sources: [Raco et al., 2022; Chou et al., 2023]. | G46: Rank #1 Potongan Chunk: investigate both different ways of data modelling even with a view to the development of predictive algorithms and of visualisation and information management the study illustrates part of the results of the... Title: inspire project integrated technologies for smart buildings and predictive maintenance Authors: Raco, F.; Balzani, M.; Planu, F.; Cittadino, A. Score: 0.4882 ----------------- Rank #2 Potongan Chunk: modeling applications in om studies notwithstanding it remains unclear how om scholars can effectively leverage supervised ml for theory building and theory testing the primary goals of scientific research we attempt to... Title: supervised machine learning for theory building and testing opportunities in operations management Authors: Chou, Y.-C.; Chuang, H.H.-C.; Chou, P.; Oliva, R. Score: 0.4837 ----------------- Rank #3 Potongan Chunk: differences between counterfeit and authentic ic samples 2022 ieee... Title: machine learning assisted counterfeit ic detection through nondestructive infrared ir spectroscopy material characterization Authors: Xi, C.; Jessurun, N.; True, J.; Khan, A.A.; Tehranipoor, M.M.; Asadizanjani, N. Score: 0.4810 | H46: 0.111 | I46: 0.863 | J46: 0 | K46: 0 | L46: =IMAGE("https://drive.google.com/uc?export=view&id=1yPmKAELlL9sBrFvofBw-OVm1mQaxVPwR")
A47: 46 | B47: LaBSE | C47: 32 | D47: 3 | E47: Compare AI approaches for short-term versus long-term supply chain resilience. | F47: Direct Summary: The comparison of AI approaches for short-term versus long-term supply chain resilience involves examining the correlation between AI technology and supply chain resilience. Studies suggest that AI can improve supply chain resilience by enhancing coordination and dynamism, as well as leveraging digital technologies like IoT and AI-driven innovative practices. However, the effectiveness of AI approaches may vary depending on the level of supply chain dynamism and the specific context of the supply chain. Detailed Synthesis: Doc [1] suggests that AI technology can improve supply chain resilience by analyzing the correlation between supply chain resilience and AI technology, and identifying specific mechanisms for improvement [1]. Doc [2] examines the relationships among generative AI usage depth, supply chain coordination, and supply chain performance at different levels of supply chain dynamism, highlighting the critical role of coordination and dynamism in AI-enabled supply chain management [2]. Doc [3] investigates the transformative interaction among digital resilience, IoT-oriented supply chain practices, AI-driven innovative practices, and sustainable supply chain performance in the context of high-tech SMEs, suggesting that AI and IoT can enhance digital resilience and sustainable supply chain performance [3]. Analysis grounded in primary sources: [Zheng et al., 2022; Li et al., 2024; Khan et al., 2025]. | G47: Rank #1 Potongan Chunk: of using artificial intelligence technology to improve supply chain resilience studies the correlation between supply chain resilience and artificial intelligence technology analysis of artificial intelligence in improving supply chain resilience mechanism specific... Title: the role of artificial intelligence technology in improving the resilience of supply chain during covid19 Authors: Zheng, Z.; Zhang, G.; Lin, Y.; Pan, Y.; He, Y. Score: 0.5675 ----------------- Rank #2 Potongan Chunk: the relational view to examine the relationships among generative ai usage depth supply chain coordination and supply chain performance at different levels of supply chain dynamism we analyze survey data from 236... Title: generative aienabled supply chain management the critical role of coordination and dynamism Authors: Li, L.; Liu, Y.; Jin, Y.; Cheng, T.C.E.; Zhang, Q. Score: 0.5318 ----------------- Rank #3 Potongan Chunk: this study investigates the transformative interaction among digital resilience dr internet of thingsoriented supply chain practices iotp aidriven innovative practices aidip and sustainable supply chain performance sscp in the context of the... Title: digital resilience in hightech smes exploring the synergy of ai and iot in supply chains Authors: Khan, A.; Murtaza, S.H.; Maroufkhani, P.; Mirza, S.S. Score: 0.5160 | H47: 1 | I47: 0.889 | J47: 1 | K47: 1 | L47: =IMAGE("https://drive.google.com/uc?export=view&id=1fkidZgCJZo8Fna4aJigCzZr52MHiqXhe")
A48: 47 | B48: LaBSE | C48: 32 | D48: 3 | E48: How do data requirements differ across AI models for SCRM? | F48: Direct Summary: Data requirements differ across AI models for Supply Chain Risk Management (SCRM) as they are influenced by the specific objectives and challenges addressed by each model. For instance, some models may require large datasets to train machine learning algorithms, while others may need smaller datasets to focus on specific risk factors. The diversity in data requirements is also reflected in the various forms of model hybridization achieved by different AI models. Detailed Synthesis: Data requirements for AI models in SCRM vary depending on the specific objectives, such as risk identification, prediction, or mitigation. For example, a model focused on risk identification may require a large dataset to train a machine learning algorithm, while a model focused on risk prediction may require a smaller dataset to focus on specific risk factors [1]. The diversity in data requirements is also reflected in the various forms of model hybridization achieved by different AI models. For instance, some models may combine machine learning with simulation techniques to better capture complex supply chain dynamics [2]. Analysis grounded in primary sources: [Badakhshan, E.; Mustafee, N.; Bahadori, R., 2024; Hassan, A.P., 2019; Kou, A.; Cheng, Y.; Guo, L.; Xia, X., 2025]. | G48: Rank #1 Potongan Chunk: different demand and supply scenarios numerical results indicate that the linear machine learning lml method incorporating data features outperforms the sample average approximation saa method in terms of optimization performance incorporating l2... Title: a datadriven newsvendor model with unknown demand and supply distribution Authors: Kou, A.; Cheng, Y.; Guo, L.; Xia, X. Score: 0.4772 ----------------- Rank #2 Potongan Chunk: significant diversity in how simml models are used to address supply chain challenges key findings include the recognition of the breadth of study objectives identifying various forms of model hybridization achieved by... Title: application of simulation and machine learning in supply chain management a synthesis of the literature using the simml literature classification framework Authors: Badakhshan, E.; Mustafee, N.; Bahadori, R. Score: 0.4740 ----------------- Rank #3 Potongan Chunk: this addresses the requirement to see the direct connection between data analytics and scm ii an experiment in which a prototype is evaluated contributes the requirement to have more empirical insight in... Title: enhancing supply chain risk management by applying machine learning to identify risks Authors: Hassan, A.P. Score: 0.4620 | H48: 1 | I48: 0.821 | J48: 1 | K48: 1 | L48: =IMAGE("https://drive.google.com/uc?export=view&id=1GuRIAmAzLBH6Tsyc9-roTRnBoP0XbWvv")
A49: 48 | B49: LaBSE | C49: 32 | D49: 3 | E49: What performance differences exist between traditional ML and deep learning models? | F49: Direct Summary: Traditional ML and deep learning models exhibit distinct performance differences, with deep learning models generally offering superior accuracy and adaptability, but requiring more complex algorithms and computational resources. Detailed Synthesis: Deep learning models, such as those utilizing convolutional neural networks (CNNs) and recurrent neural networks (RNNs), have been shown to outperform traditional ML models in various applications, including image and speech recognition [1]. However, traditional ML models, such as decision trees and support vector machines (SVMs), are often preferred in situations where interpretability and simplicity are crucial, as they provide more transparent and explainable results [2]. The choice between traditional ML and deep learning models ultimately depends on the specific problem domain, data characteristics, and computational resources available [3]. Analysis grounded in primary sources: [Ghribi, Y.; Graha, E.R.; Wicaksono, H., 2025; Rios-Ochoa, E.; Pérez Díaz, J.A.; García-Ceja, E.; Rodriguez-Hernandez, G., 2025; Yu, S.; Gu, C.; Liu, W.; Maire O'Neill, M., 2020]. | G49: Rank #1 Potongan Chunk: techniques due to their simplicity and understandable algorithms easytouse nature characteristics the research conducted for each model analyzes how traditional statistical machine learning ml and deep learning dl models can be used... Title: comparative analysis of statistical and machine learning models for enhancing demand forecasting accuracy in the medical device industry Authors: Ghribi, Y.; Graha, E.R.; Wicaksono, H. Score: 0.5390 ----------------- Rank #2 Potongan Chunk: timeliness class separability and feature variability we then train four traditional machine learning ml and two deep learning dl models applying consistent preprocessing and hyperparameter tuning for fair comparisons next we propose... Title: ransomware family attribution with ml a comprehensive evaluation of datasets quality models comparison and a simulated deployment Authors: Rios-Ochoa, E.; Pérez Díaz, J.A.; García-Ceja, E.; Rodriguez-Hernandez, G. Score: 0.5080 ----------------- Rank #3 Potongan Chunk: design are different from the data types in the ml models to efficiently extract ht features from complex ic designs and utilize common mlbased detection approaches is challenging in this paper a... Title: a novel feature extraction strategy for hardware trojan detection Authors: Yu, S.; Gu, C.; Liu, W.; Maire O'Neill, M. Score: 0.5011 | H49: 0.4 | I49: 0.995 | J49: 1 | K49: 0 | L49: =IMAGE("https://drive.google.com/uc?export=view&id=1lF4BBMER-oKPQT-ArVcPLKZI6AYJrP0v")
A50: 49 | B50: LaBSE | C50: 32 | D50: 3 | E50: Compare centralized and decentralized AI architectures for supply chain resilience. | F50: Direct Summary: Comparing centralized and decentralized AI architectures for supply chain resilience, research suggests that decentralized AI architectures offer greater flexibility and adaptability, while centralized architectures provide better control and coordination. However, the choice between the two ultimately depends on the specific needs and requirements of the supply chain. Detailed Synthesis: Decentralized AI architectures, such as blockchain-based systems, offer greater flexibility and adaptability by allowing multiple nodes to make decisions independently [1]. This can improve supply chain resilience by enabling faster response times and greater autonomy. Centralized AI architectures, on the other hand, provide better control and coordination by allowing a single node to make decisions and manage the supply chain [2]. This can improve supply chain resilience by enabling more efficient resource allocation and better risk management. The choice between centralized and decentralized AI architectures ultimately depends on the specific needs and requirements of the supply chain, including factors such as complexity, scalability, and security [3]. Analysis grounded in primary sources: [Zheng et al., 2022; Wang et al., 2023]. | G50: Rank #1 Potongan Chunk: of using artificial intelligence technology to improve supply chain resilience studies the correlation between supply chain resilience and artificial intelligence technology analysis of artificial intelligence in improving supply chain resilience mechanism specific... Title: the role of artificial intelligence technology in improving the resilience of supply chain during covid19 Authors: Zheng, Z.; Zhang, G.; Lin, Y.; Pan, Y.; He, Y. Score: 0.5115 ----------------- Rank #2 Potongan Chunk: technical framework and construct a preliminary scheme for the integration of artificial intelligence and supply chain resilience in order to provide for the outbreak to improve supply chain resilience reference and guiding... Title: the role of artificial intelligence technology in improving the resilience of supply chain during covid19 Authors: Zheng, Z.; Zhang, G.; Lin, Y.; Pan, Y.; He, Y. Score: 0.5064 ----------------- Rank #3 Potongan Chunk: improved the efficiency of capital use and enhanced the competitiveness of enterprises the authors compared the traditional supply chain management mode with the management mode under the combination of ai and bt... Title: supply chain resources and economic security based on artificial intelligence and blockchain multichannel technology Authors: Wang, D.; Yu, A. Score: 0.5010 | H50: 0 | I50: 0.764 | J50: 1 | K50: 1 | L50: =IMAGE("https://drive.google.com/uc?export=view&id=1JQPWoOeZZZPErLDL25Fd3tI_Kci-3ycf")
A51: 50 | B51: LaBSE | C51: 32 | D51: 3 | E51: How do simulation-based AI models compare with real-time predictive systems? | F51: Direct Summary: Simulation-based AI models and real-time predictive systems have different approaches to improving supply chain operations. While simulation-based AI models rely on historical data and modeling to predict future outcomes, real-time predictive systems use current data to make autonomous decisions without human intervention. Detailed Synthesis: Simulation-based AI models, as discussed in Doc [1], combine modeling and simulation with artificial intelligence and data analytics to support decision makers in reengineering processes and redesigning business models. This approach relies on historical data and modeling to predict future outcomes. Real-time predictive systems, as examined in Doc [2], use techniques like predictive modeling, optimization algorithms, and self-decision making to improve supply chain operations. These systems make autonomous decisions based on real-time data without human intervention. The collaboration between human experts and artificial intelligence-based systems, as explored in Doc [3], can also be applied to simulation-based AI models to improve their accuracy and efficiency. Analysis grounded in primary sources: [Bruzzone, A.G.; Massei, M.; Frosolini, M., 2022; Elkabtane, K.; Benazzouz, T.; Dahbi, S.; Auhmani, K., 2025; Jackson, I.; Saenz, M.; Ivanov, D., 2024]. | G51: Rank #1 Potongan Chunk: how combining modeling and simulation artificial intelligence and data analytics in closed loop with real data it could be possible to support decision makers in reengineering processes and redesigning business models even... Title: redesign of supply chain in fashion industry based on strategic engineering Authors: Bruzzone, A.G.; Massei, M.; Frosolini, M. Score: 0.5233 ----------------- Rank #2 Potongan Chunk: to 2024 to examine how techniques like predictive modeling optimization algorithms and selfdecision making ie systems capable of making autonomous decisions based on realtime data without human intervention improve sc operations the... Title: the transformative role of ml algorithms in supply chain management a systematic literature review Authors: Elkabtane, K.; Benazzouz, T.; Dahbi, S.; Auhmani, K. Score: 0.5190 ----------------- Rank #3 Potongan Chunk: our research strives to examine how simulation models of logistics systems can be produced automatically from verbal descriptions in natural language and how human experts and artificial intelligence aibased systems can collaborate... Title: from natural language to simulations applying ai to automate simulation modelling of logistics systems Authors: Jackson, I.; Saenz, M.; Ivanov, D. Score: 0.5080 | H51: 0.222 | I51: 0.389 | J51: 0.333 | K51: 0 | L51: =IMAGE("https://drive.google.com/uc?export=view&id=1F0M_5Bgc1foHunLrgY4xgC33q47AMySd")
A52: 51 | B52: LaBSE | C52: 32 | D52: 3 | E52: Compare AI models using structured versus unstructured data. | F52: Direct Summary: The comparison of AI models using structured versus unstructured data is not directly addressed in the provided documents. However, we can infer some insights from the content of the documents. Detailed Synthesis: Doc [1] employs the ISIC 2018 dataset, which is a structured dataset, to test the performance of the proposed training model. However, the document does not explicitly compare the performance of AI models using structured versus unstructured data. Doc [2] presents a comparative analysis between a MILP model and a single-agent AI model trained with DRL, but it does not address the comparison of AI models using structured versus unstructured data. Doc [3] discusses the use of AI and ML methods for quality control in metal powder bed fusion, but it does not provide any information on the comparison of AI models using structured versus unstructured data. Analysis grounded in primary sources: [Cai et al., 2023; Seni et al., 2025; Ravalji et al., 2023]. | G52: Rank #1 Potongan Chunk: we employ the isic 2018 dataset to test the performance of the proposed training model under different situations including using identically distributed data nonidentically distributed data a sparse convolutional neural network and... Title: a manyobjective optimization based federal deep generation model for enhancing data processing capability in iot Authors: Cai, X.; Lan, Y.; Zhang, Z.; Wen, J.; Cui, Z.; Garralda-Guillem, W. Score: 0.5291 ----------------- Rank #2 Potongan Chunk: this study presents a comparative analysis between a mixed integer linear programming milp model and a singleagent artificial intelligence ai model trained with deep reinforcement learning drl to optimize procurement decisions in... Title: a deep reinforcement learning model for the automation of a collaborative purchasing process Authors: Seni, M.J.; Peidro, D. Score: 0.5265 ----------------- Rank #3 Potongan Chunk: models physicsbased analytical models insitu control using artificial intelligence ai and machine learning ml methods and statistical approaches a comparison is also prepared among these strategies based on their suitability and limitations... Title: review of quality issues and mitigation strategies for metal powder bed fusion Authors: Ravalji, J.M.; Raval, S.J. Score: 0.5263 | H52: 1 | I52: 0 | J52: 0 | K52: 0.571 | L52: =IMAGE("https://drive.google.com/uc?export=view&id=18anli5Uya-MohZyBN7MI6gZYWv8SLaQj")
A53: 52 | B53: LaBSE | C53: 32 | D53: 3 | E53: How do evaluation metrics differ across AI-driven resilience studies? | F53: Direct Summary: Evaluation metrics differ across AI-driven resilience studies due to varying AI technologies, disciplinary perspectives, and supply chain contexts. The studies reviewed in Smyth et al. (2024) highlight the fragmentation of research into streams based on different AI technologies, which affects the evaluation metrics used. This fragmentation is also reflected in the distinct decision-making areas explored in Jackson et al. (2024). Detailed Synthesis: The use of AI technologies in supply chain resilience studies leads to diverse evaluation metrics, as seen in Smyth et al. (2024) [1]. The resource-based view and key AI capabilities, such as learning, perception, prediction, interaction, adaptation, and reasoning, influence the evaluation metrics used in AI-driven resilience studies, as explored in Jackson et al. (2024) [2]. The distinct decision-making areas in supply chain operations management (SCOM) impacted by AI and generative AI (GAI) also affect the evaluation metrics used, as discussed in Jackson et al. (2024) [2]. Analysis grounded in primary sources: Smyth, C.; Dennehy, D.; Fosso Wamba, S.F.; Scott, M.; Harfouche, A. (2024) and Jackson, I.; Ivanov, D.; Dolgui, A.; Namdar, J. (2024). | G53: Rank #1 Potongan Chunk: develop their understanding of ai applications in supply chain management the guiding research question was as follows does repeated use of adaptive comparative judgment as a learn by evaluation tool lead to... Title: repeated use of adaptive comparative judgment to develop student understanding of artificial intelligence in problem based learning assignments Authors: Bosman, L.; Madamanchi, A.; Bartholomew, S.; Byrd, V. Score: 0.5038 ----------------- Rank #2 Potongan Chunk: of ai and analytics in general research is largely fragmented into streams based on different types of ai technologies across several sc contexts and through varying disciplinary perspectives in response we curate... Title: artificial intelligence and prescriptive analytics for supply chain resilience a systematic literature review and research agenda Authors: Smyth, C.; Dennehy, D.; Fosso Wamba, S.F.; Scott, M.; Harfouche, A. Score: 0.4918 ----------------- Rank #3 Potongan Chunk: the resourcebased view and based on key ai capabilities such as learning perception prediction interaction adaptation and reasoning we explore how ai and gai can impact 13 distinct scom decisionmaking areas these... Title: generative artificial intelligence in supply chain and operations management a capabilitybased framework for analysis and implementation Authors: Jackson, I.; Ivanov, D.; Dolgui, A.; Namdar, J. Score: 0.4719 | H53: 0.25 | I53: 0.862 | J53: 0.5 | K53: 0.857 | L53: =IMAGE("https://drive.google.com/uc?export=view&id=1KutkJ5-U0ZD_Jli1HXn7GZrZJXLyz6YJ")
A54: 53 | B54: LaBSE | C54: 32 | D54: 3 | E54: Compare explainable AI models and black-box models in SCRM. | F54: Direct Summary: Explainable AI models in Supply Chain Risk Management (SCRM) provide transparency and interpretability of predictions, whereas black-box models lack transparency and are difficult to interpret. Explainable AI models are essential for building trust in AI-driven decision-making in SCRM. Detailed Synthesis: Explainable AI models, such as SHAP (SHapley Additive exPlanations) and LIME (Local Interpretable Model-agnostic Explanations), provide feature importance and partial dependence plots to understand the relationships between input variables and predictions [1]. Black-box models, such as Deep Neural Networks, are difficult to interpret and lack transparency, making it challenging to understand the decision-making process [2]. Explainable AI models are essential for building trust in AI-driven decision-making in SCRM, as they provide insights into the decision-making process and enable stakeholders to understand the reasoning behind predictions [3]. Analysis grounded in primary sources: [Nguyen et al., 2025; Seni et al., 2025; Cai et al., 2021]. | G54: Rank #1 Potongan Chunk: integrates arimax and lstm models to improve the ability to capture different combinations of linear and nonlinear patterns in time series our proposed model is validated in a case study of coffee... Title: toward a smart forecasting model in supply chain management a case study of coffee in vietnam Authors: Nguyen, T.T.H.; Bekrar, A.; Le, T.M.; Abed, M.; Kantasa-Ard, A. Score: 0.4951 ----------------- Rank #2 Potongan Chunk: this study presents a comparative analysis between a mixed integer linear programming milp model and a singleagent artificial intelligence ai model trained with deep reinforcement learning drl to optimize procurement decisions in... Title: a deep reinforcement learning model for the automation of a collaborative purchasing process Authors: Seni, M.J.; Peidro, D. Score: 0.4834 ----------------- Rank #3 Potongan Chunk: csi including clearsky irradiance models csim and machine learning ml models in this study 61 csim and 23 ml models for estimating hourly csi are evaluated across the land of china using... Title: hourly clearsky solar irradiance estimation in china model review and validations Authors: Cai, H.; Qin, W.; Wang, L.; Hu, B.; Zhang, M. Score: 0.4753 | H54: 0.462 | I54: 0.605 | J54: 0 | K54: 1 | L54: =IMAGE("https://drive.google.com/uc?export=view&id=1BjIT34BE5CT_6n7GJnrYjIuv9NDs9gft")
A55: 54 | B55: LaBSE | C55: 32 | D55: 3 | E55: How do AI approaches differ across manufacturing and service supply chains? | F55: Direct Summary: AI approaches differ across manufacturing and service supply chains due to distinct characteristics and requirements of each sector. In manufacturing, AI is used for predictive maintenance, quality control, and production planning, whereas in service supply chains, AI focuses on customer service, demand forecasting, and route optimization. This difference is attributed to the unique nature of each sector, with manufacturing involving physical products and service supply chains dealing with intangible services. Detailed Synthesis: Manufacturing supply chains utilize AI for predictive maintenance, quality control, and production planning, as seen in the application of digital twins in Doc [3] [1]. This enables manufacturers to optimize production processes, reduce downtime, and improve product quality. Service supply chains, on the other hand, employ AI for customer service, demand forecasting, and route optimization, as discussed in Doc [2] [2]. This helps service providers to enhance customer experience, improve operational efficiency, and make data-driven decisions. The difference in AI approaches between manufacturing and service supply chains is also influenced by the unique characteristics of each sector, such as the physical nature of manufacturing products and the intangible nature of service supply chains [3]. Analysis grounded in primary sources: [Haldorai, A.; Murugan, S.; Ramu, A., 2021; Lebhar, I.; Dadda, A.; Ezzine, L., 2023; Kaivo-Oja, J.; Kuusi, O.; Knudsen, M.S.; Lauraéus, I.T., 2020]. | G55: Rank #1 Potongan Chunk: ict technologies are critical in supporting the various aspects of industrial operations which include sales marketing processes supply chains product and service delivery and support frameworks for instance substantial implication of the... Title: evolution challenges and application of intelligent ict education an overview Authors: Haldorai, A.; Murugan, S.; Ramu, A. Score: 0.5325 ----------------- Rank #2 Potongan Chunk: most businesses strive to be reactive and agile by incorporating new technologies such as artificial intelligence ai in supply chain management nowadays supply chains sc differ from those of just a few... Title: artificial intelligence applications in the global supply chain benefits and challenges Authors: Lebhar, I.; Dadda, A.; Ezzine, L. Score: 0.5250 ----------------- Rank #3 Potongan Chunk: we are in the midst of a significant transformation regarding the way we produce products and deliver services thanks to the digitisation of manufacturing and new connected supplychains and cocreation systems this... Title: digital twin current shifts and their future implications in the conditions of technological disruption Authors: Kaivo-Oja, J.; Kuusi, O.; Knudsen, M.S.; Lauraéus, I.T. Score: 0.5181 | H55: 0 | I55: 1 | J55: 0.5 | K55: 0 | L55: =IMAGE("https://drive.google.com/uc?export=view&id=1BnknDk_7LOEv8jrFLoPv7Fm6YJTa_p_9")
